Workbook
Name AcoesRecursosHidricos_IDs: "MAPEAMENTO_ACOES!$A$5#"
Name Actions: [2]Lists!$L$2:$L$61
Name Diroconnector_: #REF!
Name ImpactActionIDs: 'Bank of actions'!$A$3:$A$55
Name ImpactScaledActionIDs: Table24[ActionID]
Name ImpactScaledActionIDs: [1]!Table24[ActionID]
Name ImpactScaledActionIDs: Table24[ActionID]
Name ImpactScaledActionIDs: Table24[ActionID]
Name ImpactScaledActionIDs: Table24[ActionID]
Name ImpactScaledActionIDs: Table24[ActionID]
Name ImpactScaledActionIDs: Table24[ActionID]
Name ImpactScaledActionIDs: Table24[ActionID]
Name Palm_indonesia: #REF!
Name Palm_malaysia: #REF!
Name WR_AccessStatus: tbl_Lists_AccessStatus[AccessStatus]
Name WR_AccessStatus: tbl_Lists_AccessStatus[AccessStatus]
Name WR_AccessStatus: tbl_Lists_AccessStatus[AccessStatus]
Name WR_AccessStatus: tbl_Lists_AccessStatus[AccessStatus]
Name WR_AccessStatus: tbl_Lists_AccessStatus[AccessStatus]
Name WR_AccessStatus: tbl_Lists_AccessStatus[AccessStatus]
Name WR_EffectivenessLevel: tbl_Lists_EffectivenessLevel[EffectivenessLevel]
Name WR_EffectivenessLevel: tbl_Lists_EffectivenessLevel[EffectivenessLevel]
Name WR_EffectivenessLevel: tbl_Lists_EffectivenessLevel[EffectivenessLevel]
Name WR_EffectivenessLevel: tbl_Lists_EffectivenessLevel[EffectivenessLevel]
Name WR_EffectivenessLevel: tbl_Lists_EffectivenessLevel[EffectivenessLevel]
Name WR_EffectivenessLevel: tbl_Lists_EffectivenessLevel[EffectivenessLevel]
Name WR_EvidenceStrength: tbl_Lists_EvidenceStrength[EvidenceStrength]
Name WR_EvidenceStrength: tbl_Lists_EvidenceStrength[EvidenceStrength]
Name WR_EvidenceStrength: tbl_Lists_EvidenceStrength[EvidenceStrength]
Name WR_EvidenceStrength: tbl_Lists_EvidenceStrength[EvidenceStrength]
Name WR_EvidenceStrength: tbl_Lists_EvidenceStrength[EvidenceStrength]
Name WR_EvidenceStrength: tbl_Lists_EvidenceStrength[EvidenceStrength]
Name WR_ExposureComponents: _xlfn.ANCHORARRAY(Lists!$E$22)
Name WR_ExposureSectors: _xlfn.ANCHORARRAY(Lists!$D$22)
Name WR_HumanValidated: tbl_Lists_HumanValidated[HumanValidated]
Name WR_HumanValidated: tbl_Lists_HumanValidated[HumanValidated]
Name WR_HumanValidated: tbl_Lists_HumanValidated[HumanValidated]
Name WR_HumanValidated: tbl_Lists_HumanValidated[HumanValidated]
Name WR_HumanValidated: tbl_Lists_HumanValidated[HumanValidated]
Name WR_HumanValidated: tbl_Lists_HumanValidated[HumanValidated]
Name WR_RelevantComponent: tbl_Lists_RelevantComponent[RelevantComponent]
Name WR_RelevantComponent: tbl_Lists_RelevantComponent[RelevantComponent]
Name WR_RelevantComponent: tbl_Lists_RelevantComponent[RelevantComponent]
Name WR_RelevantComponent: tbl_Lists_RelevantComponent[RelevantComponent]
Name WR_RelevantComponent: tbl_Lists_RelevantComponent[RelevantComponent]
Name WR_RelevantComponent: tbl_Lists_RelevantComponent[RelevantComponent]
Name WR_ReviewStatus: tbl_Lists_ReviewStatus[ReviewStatus]
Name WR_ReviewStatus: tbl_Lists_ReviewStatus[ReviewStatus]
Name WR_ReviewStatus: tbl_Lists_ReviewStatus[ReviewStatus]
Name WR_ReviewStatus: tbl_Lists_ReviewStatus[ReviewStatus]
Name WR_ReviewStatus: tbl_Lists_ReviewStatus[ReviewStatus]
Name WR_ReviewStatus: tbl_Lists_ReviewStatus[ReviewStatus]
Name WR_SourceScope: tbl_Lists_SourceScope[SourceScope]
Name WR_SourceScope: tbl_Lists_SourceScope[SourceScope]
Name WR_SourceScope: tbl_Lists_SourceScope[SourceScope]
Name WR_SourceScope: tbl_Lists_SourceScope[SourceScope]
Name WR_SourceScope: tbl_Lists_SourceScope[SourceScope]
Name WR_SourceScope: tbl_Lists_SourceScope[SourceScope]
Name WR_VulnerabilityComponents: _xlfn.ANCHORARRAY(Lists!$B$22)
Name WR_VulnerabilitySectors: _xlfn.ANCHORARRAY(Lists!$A$22)

Sheet Home
B2: Sector-action linkage assessment
B3: Methodological workbook for sector eligibility and effectiveness assessment using AI-supported evidence review
B6: Date | C6: 26/08/2026
B7: Author | C7: I Care Brasil
B8: Version | C8: Working draft
B10: What is this workbook for?
B11: This workbook establishes direct links between adaptation actions and sectors. Eligibility is assessed first; effectiveness is assessed only for eligible actions. The resulting effectiveness values are intended to become inputs to the Impact Assessment.
B12: How is the process structured?
B13: CURRENT PROCESS 1. Step 0 — Indicator Framework Construction: build the approved sector framework by grouping Level 6 Vulnerability and Exposure indicators under their respective Level 3 components. 2. Step 1 — Source Identification: identify and validate 5 Brazilian and 5 international PDF sources. 3. Step 2 — Combined Assessment: the same prompt assesses sector eligibility and effectiveness together using the available evidence.
B16: Target process
B17: TARGET PROCESS 1. Step 0 — Indicator Framework Construction: retain the same approved sector framework. 2. Step 1 — Source Identification: retain the same validated PDF portfolio. 3. Step 2A — Eligibility Assessment: run a dedicated prompt that determines only whether each action has a direct relationship with approved Vulnerability or Exposure indicators. No effectiveness level is assigned. 4. Human review: validate the eligibility results before proceeding. 5. Step 2B — Effectiveness Assessment: run a separate prompt, limited to actions already classified as Eligible, and progressively append evidence from reviewed PDFs.
B20: Why separate eligibility and effectiveness?
B21: Eligibility asks: “Does the action belong to this sector through a direct indicator relationship?” Effectiveness asks: “How strong is the evidence that this action reduces the approved indicator?” Keeping them in separate prompts prevents the effectiveness evidence from influencing the prior eligibility decision.
B24: Important note on AI use
B25: AI is used as a decision-support tool. Outputs depend on source quality, PDF coverage, prompt design and interpretation of evidence. Extensive validation rules reduce risks, but limitations and uncertainty remain. Human review is recommended for critical methodological decisions. Results should be interpreted as evidence-supported expert judgement, not fully automated conclusions.
B29: How to use the workbook
B30: 1. The current sector worksheets still use a combined Step 2 prompt. 2. Use Water Resources x actions as the completed current-process example. 3. For the target process, run a standalone Step 2A prompt, validate eligibility, then run a separate Step 2B prompt for Eligible actions only. 4. Review consolidated results in Summary Matrix and use effectiveness values in the Impact Assessment.
B34: Key worksheets
B35: Summary Matrix | E35: Consolidated links and effectiveness values
B36: Water Resources x actions | E36: Completed pilot and reference workflow
B37: Other sector worksheets | E37: Run Step 2A and Step 2B independently for each sector
B38: Score assessments | E38: Downstream Impact Assessment tests

Sheet Summary Matrix
B2: SUMMARY MATRIX - AUTOMATIC VALUES FROM SECTOR BLOCKS
B3: ActionID | C3: ActionName | D3: Water Resources | E3: Food Security | F3: Energy Security | G3: Health | H3: Geohydrological Disasters | I3: Biodiversity
B4: c40_0046 | C4: Strengthen coastal protection infrastructure | D4: =IFERROR(_xlfn.LET(_xlpm.v,_xlfn.XLOOKUP(tbl_Summary_Linkage[[#This Row],[ActionID]],tbl_WR_Assessment[ActionID],tbl_WR_Assessment[Effectiveness on Vulnerability],""),_xlpm.e,_xlfn.XLOOKUP(tbl_Summary_Linkage[[#This Row],[ActionID]],tbl_WR_Assessment[ActionID],tbl_WR_Assessment[Effectiveness on Exposure],""),IF(OR(_xlpm.v="High effectiveness",_xlpm.v="Medium effectiveness",_xlpm.v="Low effectiveness",_xlpm.e="High effectiveness",_xlpm.e="Medium effectiveness",_xlpm.e="Low effectiveness"),"Yes","")),"") | E4: =IFERROR(_xlfn.LET(_xlpm.v,_xlfn.XLOOKUP(tbl_Summary_Linkage[[#This Row],[ActionID]],tbl_FS_Assessment[ActionID],tbl_FS_Assessment[Effectiveness on Vulnerability],""),_xlpm.e,_xlfn.XLOOKUP(tbl_Summary_Linkage[[#This Row],[ActionID]],tbl_FS_Assessment[ActionID],tbl_FS_Assessment[Effectiveness on Exposure],""),IF(OR(_xlpm.v="High effectiveness",_xlpm.v="Medium effectiveness",_xlpm.v="Low effectiveness",_xlpm.e="High effectiveness",_xlpm.e="Medium effectiveness",_xlpm.e="Low effectiveness"),"Yes","")),"") | F4: =IFERROR(_xlfn.LET(_xlpm.v,_xlfn.XLOOKUP(tbl_Summary_Linkage[[#This Row],[ActionID]],tbl_ES_Assessment[ActionID],tbl_ES_Assessment[Effectiveness on Vulnerability],""),_xlpm.e,_xlfn.XLOOKUP(tbl_Summary_Linkage[[#This Row],[ActionID]],tbl_ES_Assessment[ActionID],tbl_ES_Assessment[Effectiveness on Exposure],""),IF(OR(_xlpm.v="High effectiveness",_xlpm.v="Medium effectiveness",_xlpm.v="Low effectiveness",_xlpm.e="High effectiveness",_xlpm.e="Medium effectiveness",_xlpm.e="Low effectiveness"),"Yes","")),"") | G4: =IFERROR(_xlfn.LET(_xlpm.v,_xlfn.XLOOKUP(tbl_Summary_Linkage[[#This Row],[ActionID]],tbl_H_Assessment[ActionID],tbl_H_Assessment[Effectiveness on Vulnerability],""),_xlpm.e,_xlfn.XLOOKUP(tbl_Summary_Linkage[[#This Row],[ActionID]],tbl_H_Assessment[ActionID],tbl_H_Assessment[Effectiveness on Exposure],""),IF(OR(_xlpm.v="High effectiveness",_xlpm.v="Medium effectiveness",_xlpm.v="Low effectiveness",_xlpm.e="High effectiveness",_xlpm.e="Medium effectiveness",_xlpm.e="Low effectiveness"),"Yes","")),"") | H4: =IFERROR(_xlfn.LET(_xlpm.v,_xlfn.XLOOKUP(tbl_Summary_Linkage[[#This Row],[ActionID]],tbl_GS_Assessment[ActionID],tbl_GS_Assessment[Effectiveness on Vulnerability],""),_xlpm.e,_xlfn.XLOOKUP(tbl_Summary_Linkage[[#This Row],[ActionID]],tbl_GS_Assessment[ActionID],tbl_GS_Assessment[Effectiveness on Exposure],""),IF(OR(_xlpm.v="High effectiveness",_xlpm.v="Medium effectiveness",_xlpm.v="Low effectiveness",_xlpm.e="High effectiveness",_xlpm.e="Medium effectiveness",_xlpm.e="Low effectiveness"),"Yes","")),"") | I4: =IFERROR(_xlfn.LET(_xlpm.v,_xlfn.XLOOKUP(tbl_Summary_Linkage[[#This Row],[ActionID]],tbl_B_Assessment[ActionID],tbl_B_Assessment[Effectiveness on Vulnerability],""),_xlpm.e,_xlfn.XLOOKUP(tbl_Summary_Linkage[[#This Row],[ActionID]],tbl_B_Assessment[ActionID],tbl_B_Assessment[Effectiveness on Exposure],""),IF(OR(_xlpm.v="High effectiveness",_xlpm.v="Medium effectiveness",_xlpm.v="Low effectiveness",_xlpm.e="High effectiveness",_xlpm.e="Medium effectiveness",_xlpm.e="Low effectiveness"),"Yes","")),"")
B5: c40_0048 | C5: Upgrade urban drainage systems | D5: =IFERROR(_xlfn.LET(_xlpm.v,_xlfn.XLOOKUP(tbl_Summary_Linkage[[#This Row],[ActionID]],tbl_WR_Assessment[ActionID],tbl_WR_Assessment[Effectiveness on Vulnerability],""),_xlpm.e,_xlfn.XLOOKUP(tbl_Summary_Linkage[[#This Row],[ActionID]],tbl_WR_Assessment[ActionID],tbl_WR_Assessment[Effectiveness on Exposure],""),IF(OR(_xlpm.v="High effectiveness",_xlpm.v="Medium effectiveness",_xlpm.v="Low effectiveness",_xlpm.e="High effectiveness",_xlpm.e="Medium effectiveness",_xlpm.e="Low effectiveness"),"Yes","")),"") -> Yes | E5: =IFERROR(_xlfn.LET(_xlpm.v,_xlfn.XLOOKUP(tbl_Summary_Linkage[[#This Row],[ActionID]],tbl_FS_Assessment[ActionID],tbl_FS_Assessment[Effectiveness on Vulnerability],""),_xlpm.e,_xlfn.XLOOKUP(tbl_Summary_Linkage[[#This Row],[ActionID]],tbl_FS_Assessment[ActionID],tbl_FS_Assessment[Effectiveness on Exposure],""),IF(OR(_xlpm.v="High effectiveness",_xlpm.v="Medium effectiveness",_xlpm.v="Low effectiveness",_xlpm.e="High effectiveness",_xlpm.e="Medium effectiveness",_xlpm.e="Low effectiveness"),"Yes","")),"") | F5: =IFERROR(_xlfn.LET(_xlpm.v,_xlfn.XLOOKUP(tbl_Summary_Linkage[[#This Row],[ActionID]],tbl_ES_Assessment[ActionID],tbl_ES_Assessment[Effectiveness on Vulnerability],""),_xlpm.e,_xlfn.XLOOKUP(tbl_Summary_Linkage[[#This Row],[ActionID]],tbl_ES_Assessment[ActionID],tbl_ES_Assessment[Effectiveness on Exposure],""),IF(OR(_xlpm.v="High effectiveness",_xlpm.v="Medium effectiveness",_xlpm.v="Low effectiveness",_xlpm.e="High effectiveness",_xlpm.e="Medium effectiveness",_xlpm.e="Low effectiveness"),"Yes","")),"") | G5: =IFERROR(_xlfn.LET(_xlpm.v,_xlfn.XLOOKUP(tbl_Summary_Linkage[[#This Row],[ActionID]],tbl_H_Assessment[ActionID],tbl_H_Assessment[Effectiveness on Vulnerability],""),_xlpm.e,_xlfn.XLOOKUP(tbl_Summary_Linkage[[#This Row],[ActionID]],tbl_H_Assessment[ActionID],tbl_H_Assessment[Effectiveness on Exposure],""),IF(OR(_xlpm.v="High effectiveness",_xlpm.v="Medium effectiveness",_xlpm.v="Low effectiveness",_xlpm.e="High effectiveness",_xlpm.e="Medium effectiveness",_xlpm.e="Low effectiveness"),"Yes","")),"") | H5: =IFERROR(_xlfn.LET(_xlpm.v,_xlfn.XLOOKUP(tbl_Summary_Linkage[[#This Row],[ActionID]],tbl_GS_Assessment[ActionID],tbl_GS_Assessment[Effectiveness on Vulnerability],""),_xlpm.e,_xlfn.XLOOKUP(tbl_Summary_Linkage[[#This Row],[ActionID]],tbl_GS_Assessment[ActionID],tbl_GS_Assessment[Effectiveness on Exposure],""),IF(OR(_xlpm.v="High effectiveness",_xlpm.v="Medium effectiveness",_xlpm.v="Low effectiveness",_xlpm.e="High effectiveness",_xlpm.e="Medium effectiveness",_xlpm.e="Low effectiveness"),"Yes","")),"") | I5: =IFERROR(_xlfn.LET(_xlpm.v,_xlfn.XLOOKUP(tbl_Summary_Linkage[[#This Row],[ActionID]],tbl_B_Assessment[ActionID],tbl_B_Assessment[Effectiveness on Vulnerability],""),_xlpm.e,_xlfn.XLOOKUP(tbl_Summary_Linkage[[#This Row],[ActionID]],tbl_B_Assessment[ActionID],tbl_B_Assessment[Effectiveness on Exposure],""),IF(OR(_xlpm.v="High effectiveness",_xlpm.v="Medium effectiveness",_xlpm.v="Low effectiveness",_xlpm.e="High effectiveness",_xlpm.e="Medium effectiveness",_xlpm.e="Low effectiveness"),"Yes","")),"")
B6: c40_0049 | C6: Build and maintain shelters for critical climate hazards | D6: =IFERROR(_xlfn.LET(_xlpm.v,_xlfn.XLOOKUP(tbl_Summary_Linkage[[#This Row],[ActionID]],tbl_WR_Assessment[ActionID],tbl_WR_Assessment[Effectiveness on Vulnerability],""),_xlpm.e,_xlfn.XLOOKUP(tbl_Summary_Linkage[[#This Row],[ActionID]],tbl_WR_Assessment[ActionID],tbl_WR_Assessment[Effectiveness on Exposure],""),IF(OR(_xlpm.v="High effectiveness",_xlpm.v="Medium effectiveness",_xlpm.v="Low effectiveness",_xlpm.e="High effectiveness",_xlpm.e="Medium effectiveness",_xlpm.e="Low effectiveness"),"Yes","")),"") | E6: =IFERROR(_xlfn.LET(_xlpm.v,_xlfn.XLOOKUP(tbl_Summary_Linkage[[#This Row],[ActionID]],tbl_FS_Assessment[ActionID],tbl_FS_Assessment[Effectiveness on Vulnerability],""),_xlpm.e,_xlfn.XLOOKUP(tbl_Summary_Linkage[[#This Row],[ActionID]],tbl_FS_Assessment[ActionID],tbl_FS_Assessment[Effectiveness on Exposure],""),IF(OR(_xlpm.v="High effectiveness",_xlpm.v="Medium effectiveness",_xlpm.v="Low effectiveness",_xlpm.e="High effectiveness",_xlpm.e="Medium effectiveness",_xlpm.e="Low effectiveness"),"Yes","")),"") | F6: =IFERROR(_xlfn.LET(_xlpm.v,_xlfn.XLOOKUP(tbl_Summary_Linkage[[#This Row],[ActionID]],tbl_ES_Assessment[ActionID],tbl_ES_Assessment[Effectiveness on Vulnerability],""),_xlpm.e,_xlfn.XLOOKUP(tbl_Summary_Linkage[[#This Row],[ActionID]],tbl_ES_Assessment[ActionID],tbl_ES_Assessment[Effectiveness on Exposure],""),IF(OR(_xlpm.v="High effectiveness",_xlpm.v="Medium effectiveness",_xlpm.v="Low effectiveness",_xlpm.e="High effectiveness",_xlpm.e="Medium effectiveness",_xlpm.e="Low effectiveness"),"Yes","")),"") | G6: =IFERROR(_xlfn.LET(_xlpm.v,_xlfn.XLOOKUP(tbl_Summary_Linkage[[#This Row],[ActionID]],tbl_H_Assessment[ActionID],tbl_H_Assessment[Effectiveness on Vulnerability],""),_xlpm.e,_xlfn.XLOOKUP(tbl_Summary_Linkage[[#This Row],[ActionID]],tbl_H_Assessment[ActionID],tbl_H_Assessment[Effectiveness on Exposure],""),IF(OR(_xlpm.v="High effectiveness",_xlpm.v="Medium effectiveness",_xlpm.v="Low effectiveness",_xlpm.e="High effectiveness",_xlpm.e="Medium effectiveness",_xlpm.e="Low effectiveness"),"Yes","")),"") | H6: =IFERROR(_xlfn.LET(_xlpm.v,_xlfn.XLOOKUP(tbl_Summary_Linkage[[#This Row],[ActionID]],tbl_GS_Assessment[ActionID],tbl_GS_Assessment[Effectiveness on Vulnerability],""),_xlpm.e,_xlfn.XLOOKUP(tbl_Summary_Linkage[[#This Row],[ActionID]],tbl_GS_Assessment[ActionID],tbl_GS_Assessment[Effectiveness on Exposure],""),IF(OR(_xlpm.v="High effectiveness",_xlpm.v="Medium effectiveness",_xlpm.v="Low effectiveness",_xlpm.e="High effectiveness",_xlpm.e="Medium effectiveness",_xlpm.e="Low effectiveness"),"Yes","")),"") | I6: =IFERROR(_xlfn.LET(_xlpm.v,_xlfn.XLOOKUP(tbl_Summary_Linkage[[#This Row],[ActionID]],tbl_B_Assessment[ActionID],tbl_B_Assessment[Effectiveness on Vulnerability],""),_xlpm.e,_xlfn.XLOOKUP(tbl_Summary_Linkage[[#This Row],[ActionID]],tbl_B_Assessment[ActionID],tbl_B_Assessment[Effectiveness on Exposure],""),IF(OR(_xlpm.v="High effectiveness",_xlpm.v="Medium effectiveness",_xlpm.v="Low effectiveness",_xlpm.e="High effectiveness",_xlpm.e="Medium effectiveness",_xlpm.e="Low effectiveness"),"Yes","")),"")
B7: c40_0051 | C7: Provide public shading in heat hotspots | D7: =IFERROR(_xlfn.LET(_xlpm.v,_xlfn.XLOOKUP(tbl_Summary_Linkage[[#This Row],[ActionID]],tbl_WR_Assessment[ActionID],tbl_WR_Assessment[Effectiveness on Vulnerability],""),_xlpm.e,_xlfn.XLOOKUP(tbl_Summary_Linkage[[#This Row],[ActionID]],tbl_WR_Assessment[ActionID],tbl_WR_Assessment[Effectiveness on Exposure],""),IF(OR(_xlpm.v="High effectiveness",_xlpm.v="Medium effectiveness",_xlpm.v="Low effectiveness",_xlpm.e="High effectiveness",_xlpm.e="Medium effectiveness",_xlpm.e="Low effectiveness"),"Yes","")),"") | E7: =IFERROR(_xlfn.LET(_xlpm.v,_xlfn.XLOOKUP(tbl_Summary_Linkage[[#This Row],[ActionID]],tbl_FS_Assessment[ActionID],tbl_FS_Assessment[Effectiveness on Vulnerability],""),_xlpm.e,_xlfn.XLOOKUP(tbl_Summary_Linkage[[#This Row],[ActionID]],tbl_FS_Assessment[ActionID],tbl_FS_Assessment[Effectiveness on Exposure],""),IF(OR(_xlpm.v="High effectiveness",_xlpm.v="Medium effectiveness",_xlpm.v="Low effectiveness",_xlpm.e="High effectiveness",_xlpm.e="Medium effectiveness",_xlpm.e="Low effectiveness"),"Yes","")),"") | F7: =IFERROR(_xlfn.LET(_xlpm.v,_xlfn.XLOOKUP(tbl_Summary_Linkage[[#This Row],[ActionID]],tbl_ES_Assessment[ActionID],tbl_ES_Assessment[Effectiveness on Vulnerability],""),_xlpm.e,_xlfn.XLOOKUP(tbl_Summary_Linkage[[#This Row],[ActionID]],tbl_ES_Assessment[ActionID],tbl_ES_Assessment[Effectiveness on Exposure],""),IF(OR(_xlpm.v="High effectiveness",_xlpm.v="Medium effectiveness",_xlpm.v="Low effectiveness",_xlpm.e="High effectiveness",_xlpm.e="Medium effectiveness",_xlpm.e="Low effectiveness"),"Yes","")),"") | G7: =IFERROR(_xlfn.LET(_xlpm.v,_xlfn.XLOOKUP(tbl_Summary_Linkage[[#This Row],[ActionID]],tbl_H_Assessment[ActionID],tbl_H_Assessment[Effectiveness on Vulnerability],""),_xlpm.e,_xlfn.XLOOKUP(tbl_Summary_Linkage[[#This Row],[ActionID]],tbl_H_Assessment[ActionID],tbl_H_Assessment[Effectiveness on Exposure],""),IF(OR(_xlpm.v="High effectiveness",_xlpm.v="Medium effectiveness",_xlpm.v="Low effectiveness",_xlpm.e="High effectiveness",_xlpm.e="Medium effectiveness",_xlpm.e="Low effectiveness"),"Yes","")),"") | H7: =IFERROR(_xlfn.LET(_xlpm.v,_xlfn.XLOOKUP(tbl_Summary_Linkage[[#This Row],[ActionID]],tbl_GS_Assessment[ActionID],tbl_GS_Assessment[Effectiveness on Vulnerability],""),_xlpm.e,_xlfn.XLOOKUP(tbl_Summary_Linkage[[#This Row],[ActionID]],tbl_GS_Assessment[ActionID],tbl_GS_Assessment[Effectiveness on Exposure],""),IF(OR(_xlpm.v="High effectiveness",_xlpm.v="Medium effectiveness",_xlpm.v="Low effectiveness",_xlpm.e="High effectiveness",_xlpm.e="Medium effectiveness",_xlpm.e="Low effectiveness"),"Yes","")),"") | I7: =IFERROR(_xlfn.LET(_xlpm.v,_xlfn.XLOOKUP(tbl_Summary_Linkage[[#This Row],[ActionID]],tbl_B_Assessment[ActionID],tbl_B_Assessment[Effectiveness on Vulnerability],""),_xlpm.e,_xlfn.XLOOKUP(tbl_Summary_Linkage[[#This Row],[ActionID]],tbl_B_Assessment[ActionID],tbl_B_Assessment[Effectiveness on Exposure],""),IF(OR(_xlpm.v="High effectiveness",_xlpm.v="Medium effectiveness",_xlpm.v="Low effectiveness",_xlpm.e="High effectiveness",_xlpm.e="Medium effectiveness",_xlpm.e="Low effectiveness"),"Yes","")),"")
B8: c40_0052 | C8: Deploy cool pavements and cool roofs on heat‑exposed streets and buildings | D8: =IFERROR(_xlfn.LET(_xlpm.v,_xlfn.XLOOKUP(tbl_Summary_Linkage[[#This Row],[ActionID]],tbl_WR_Assessment[ActionID],tbl_WR_Assessment[Effectiveness on Vulnerability],""),_xlpm.e,_xlfn.XLOOKUP(tbl_Summary_Linkage[[#This Row],[ActionID]],tbl_WR_Assessment[ActionID],tbl_WR_Assessment[Effectiveness on Exposure],""),IF(OR(_xlpm.v="High effectiveness",_xlpm.v="Medium effectiveness",_xlpm.v="Low effectiveness",_xlpm.e="High effectiveness",_xlpm.e="Medium effectiveness",_xlpm.e="Low effectiveness"),"Yes","")),"") | E8: =IFERROR(_xlfn.LET(_xlpm.v,_xlfn.XLOOKUP(tbl_Summary_Linkage[[#This Row],[ActionID]],tbl_FS_Assessment[ActionID],tbl_FS_Assessment[Effectiveness on Vulnerability],""),_xlpm.e,_xlfn.XLOOKUP(tbl_Summary_Linkage[[#This Row],[ActionID]],tbl_FS_Assessment[ActionID],tbl_FS_Assessment[Effectiveness on Exposure],""),IF(OR(_xlpm.v="High effectiveness",_xlpm.v="Medium effectiveness",_xlpm.v="Low effectiveness",_xlpm.e="High effectiveness",_xlpm.e="Medium effectiveness",_xlpm.e="Low effectiveness"),"Yes","")),"") | F8: =IFERROR(_xlfn.LET(_xlpm.v,_xlfn.XLOOKUP(tbl_Summary_Linkage[[#This Row],[ActionID]],tbl_ES_Assessment[ActionID],tbl_ES_Assessment[Effectiveness on Vulnerability],""),_xlpm.e,_xlfn.XLOOKUP(tbl_Summary_Linkage[[#This Row],[ActionID]],tbl_ES_Assessment[ActionID],tbl_ES_Assessment[Effectiveness on Exposure],""),IF(OR(_xlpm.v="High effectiveness",_xlpm.v="Medium effectiveness",_xlpm.v="Low effectiveness",_xlpm.e="High effectiveness",_xlpm.e="Medium effectiveness",_xlpm.e="Low effectiveness"),"Yes","")),"") | G8: =IFERROR(_xlfn.LET(_xlpm.v,_xlfn.XLOOKUP(tbl_Summary_Linkage[[#This Row],[ActionID]],tbl_H_Assessment[ActionID],tbl_H_Assessment[Effectiveness on Vulnerability],""),_xlpm.e,_xlfn.XLOOKUP(tbl_Summary_Linkage[[#This Row],[ActionID]],tbl_H_Assessment[ActionID],tbl_H_Assessment[Effectiveness on Exposure],""),IF(OR(_xlpm.v="High effectiveness",_xlpm.v="Medium effectiveness",_xlpm.v="Low effectiveness",_xlpm.e="High effectiveness",_xlpm.e="Medium effectiveness",_xlpm.e="Low effectiveness"),"Yes","")),"") | H8: =IFERROR(_xlfn.LET(_xlpm.v,_xlfn.XLOOKUP(tbl_Summary_Linkage[[#This Row],[ActionID]],tbl_GS_Assessment[ActionID],tbl_GS_Assessment[Effectiveness on Vulnerability],""),_xlpm.e,_xlfn.XLOOKUP(tbl_Summary_Linkage[[#This Row],[ActionID]],tbl_GS_Assessment[ActionID],tbl_GS_Assessment[Effectiveness on Exposure],""),IF(OR(_xlpm.v="High effectiveness",_xlpm.v="Medium effectiveness",_xlpm.v="Low effectiveness",_xlpm.e="High effectiveness",_xlpm.e="Medium effectiveness",_xlpm.e="Low effectiveness"),"Yes","")),"") | I8: =IFERROR(_xlfn.LET(_xlpm.v,_xlfn.XLOOKUP(tbl_Summary_Linkage[[#This Row],[ActionID]],tbl_B_Assessment[ActionID],tbl_B_Assessment[Effectiveness on Vulnerability],""),_xlpm.e,_xlfn.XLOOKUP(tbl_Summary_Linkage[[#This Row],[ActionID]],tbl_B_Assessment[ActionID],tbl_B_Assessment[Effectiveness on Exposure],""),IF(OR(_xlpm.v="High effectiveness",_xlpm.v="Medium effectiveness",_xlpm.v="Low effectiveness",_xlpm.e="High effectiveness",_xlpm.e="Medium effectiveness",_xlpm.e="Low effectiveness"),"Yes","")),"")
B9: c40_0053 | C9: Promote water-saving technologies and practices | D9: =IFERROR(_xlfn.LET(_xlpm.v,_xlfn.XLOOKUP(tbl_Summary_Linkage[[#This Row],[ActionID]],tbl_WR_Assessment[ActionID],tbl_WR_Assessment[Effectiveness on Vulnerability],""),_xlpm.e,_xlfn.XLOOKUP(tbl_Summary_Linkage[[#This Row],[ActionID]],tbl_WR_Assessment[ActionID],tbl_WR_Assessment[Effectiveness on Exposure],""),IF(OR(_xlpm.v="High effectiveness",_xlpm.v="Medium effectiveness",_xlpm.v="Low effectiveness",_xlpm.e="High effectiveness",_xlpm.e="Medium effectiveness",_xlpm.e="Low effectiveness"),"Yes","")),"") -> Yes | E9: =IFERROR(_xlfn.LET(_xlpm.v,_xlfn.XLOOKUP(tbl_Summary_Linkage[[#This Row],[ActionID]],tbl_FS_Assessment[ActionID],tbl_FS_Assessment[Effectiveness on Vulnerability],""),_xlpm.e,_xlfn.XLOOKUP(tbl_Summary_Linkage[[#This Row],[ActionID]],tbl_FS_Assessment[ActionID],tbl_FS_Assessment[Effectiveness on Exposure],""),IF(OR(_xlpm.v="High effectiveness",_xlpm.v="Medium effectiveness",_xlpm.v="Low effectiveness",_xlpm.e="High effectiveness",_xlpm.e="Medium effectiveness",_xlpm.e="Low effectiveness"),"Yes","")),"") | F9: =IFERROR(_xlfn.LET(_xlpm.v,_xlfn.XLOOKUP(tbl_Summary_Linkage[[#This Row],[ActionID]],tbl_ES_Assessment[ActionID],tbl_ES_Assessment[Effectiveness on Vulnerability],""),_xlpm.e,_xlfn.XLOOKUP(tbl_Summary_Linkage[[#This Row],[ActionID]],tbl_ES_Assessment[ActionID],tbl_ES_Assessment[Effectiveness on Exposure],""),IF(OR(_xlpm.v="High effectiveness",_xlpm.v="Medium effectiveness",_xlpm.v="Low effectiveness",_xlpm.e="High effectiveness",_xlpm.e="Medium effectiveness",_xlpm.e="Low effectiveness"),"Yes","")),"") | G9: =IFERROR(_xlfn.LET(_xlpm.v,_xlfn.XLOOKUP(tbl_Summary_Linkage[[#This Row],[ActionID]],tbl_H_Assessment[ActionID],tbl_H_Assessment[Effectiveness on Vulnerability],""),_xlpm.e,_xlfn.XLOOKUP(tbl_Summary_Linkage[[#This Row],[ActionID]],tbl_H_Assessment[ActionID],tbl_H_Assessment[Effectiveness on Exposure],""),IF(OR(_xlpm.v="High effectiveness",_xlpm.v="Medium effectiveness",_xlpm.v="Low effectiveness",_xlpm.e="High effectiveness",_xlpm.e="Medium effectiveness",_xlpm.e="Low effectiveness"),"Yes","")),"") | H9: =IFERROR(_xlfn.LET(_xlpm.v,_xlfn.XLOOKUP(tbl_Summary_Linkage[[#This Row],[ActionID]],tbl_GS_Assessment[ActionID],tbl_GS_Assessment[Effectiveness on Vulnerability],""),_xlpm.e,_xlfn.XLOOKUP(tbl_Summary_Linkage[[#This Row],[ActionID]],tbl_GS_Assessment[ActionID],tbl_GS_Assessment[Effectiveness on Exposure],""),IF(OR(_xlpm.v="High effectiveness",_xlpm.v="Medium effectiveness",_xlpm.v="Low effectiveness",_xlpm.e="High effectiveness",_xlpm.e="Medium effectiveness",_xlpm.e="Low effectiveness"),"Yes","")),"") | I9: =IFERROR(_xlfn.LET(_xlpm.v,_xlfn.XLOOKUP(tbl_Summary_Linkage[[#This Row],[ActionID]],tbl_B_Assessment[ActionID],tbl_B_Assessment[Effectiveness on Vulnerability],""),_xlpm.e,_xlfn.XLOOKUP(tbl_Summary_Linkage[[#This Row],[ActionID]],tbl_B_Assessment[ActionID],tbl_B_Assessment[Effectiveness on Exposure],""),IF(OR(_xlpm.v="High effectiveness",_xlpm.v="Medium effectiveness",_xlpm.v="Low effectiveness",_xlpm.e="High effectiveness",_xlpm.e="Medium effectiveness",_xlpm.e="Low effectiveness"),"Yes","")),"")
B10: c40_0056 | C10: Improve Watershed Protection and Management | D10: =IFERROR(_xlfn.LET(_xlpm.v,_xlfn.XLOOKUP(tbl_Summary_Linkage[[#This Row],[ActionID]],tbl_WR_Assessment[ActionID],tbl_WR_Assessment[Effectiveness on Vulnerability],""),_xlpm.e,_xlfn.XLOOKUP(tbl_Summary_Linkage[[#This Row],[ActionID]],tbl_WR_Assessment[ActionID],tbl_WR_Assessment[Effectiveness on Exposure],""),IF(OR(_xlpm.v="High effectiveness",_xlpm.v="Medium effectiveness",_xlpm.v="Low effectiveness",_xlpm.e="High effectiveness",_xlpm.e="Medium effectiveness",_xlpm.e="Low effectiveness"),"Yes","")),"") -> Yes | E10: =IFERROR(_xlfn.LET(_xlpm.v,_xlfn.XLOOKUP(tbl_Summary_Linkage[[#This Row],[ActionID]],tbl_FS_Assessment[ActionID],tbl_FS_Assessment[Effectiveness on Vulnerability],""),_xlpm.e,_xlfn.XLOOKUP(tbl_Summary_Linkage[[#This Row],[ActionID]],tbl_FS_Assessment[ActionID],tbl_FS_Assessment[Effectiveness on Exposure],""),IF(OR(_xlpm.v="High effectiveness",_xlpm.v="Medium effectiveness",_xlpm.v="Low effectiveness",_xlpm.e="High effectiveness",_xlpm.e="Medium effectiveness",_xlpm.e="Low effectiveness"),"Yes","")),"") | F10: =IFERROR(_xlfn.LET(_xlpm.v,_xlfn.XLOOKUP(tbl_Summary_Linkage[[#This Row],[ActionID]],tbl_ES_Assessment[ActionID],tbl_ES_Assessment[Effectiveness on Vulnerability],""),_xlpm.e,_xlfn.XLOOKUP(tbl_Summary_Linkage[[#This Row],[ActionID]],tbl_ES_Assessment[ActionID],tbl_ES_Assessment[Effectiveness on Exposure],""),IF(OR(_xlpm.v="High effectiveness",_xlpm.v="Medium effectiveness",_xlpm.v="Low effectiveness",_xlpm.e="High effectiveness",_xlpm.e="Medium effectiveness",_xlpm.e="Low effectiveness"),"Yes","")),"") | G10: =IFERROR(_xlfn.LET(_xlpm.v,_xlfn.XLOOKUP(tbl_Summary_Linkage[[#This Row],[ActionID]],tbl_H_Assessment[ActionID],tbl_H_Assessment[Effectiveness on Vulnerability],""),_xlpm.e,_xlfn.XLOOKUP(tbl_Summary_Linkage[[#This Row],[ActionID]],tbl_H_Assessment[ActionID],tbl_H_Assessment[Effectiveness on Exposure],""),IF(OR(_xlpm.v="High effectiveness",_xlpm.v="Medium effectiveness",_xlpm.v="Low effectiveness",_xlpm.e="High effectiveness",_xlpm.e="Medium effectiveness",_xlpm.e="Low effectiveness"),"Yes","")),"") | H10: =IFERROR(_xlfn.LET(_xlpm.v,_xlfn.XLOOKUP(tbl_Summary_Linkage[[#This Row],[ActionID]],tbl_GS_Assessment[ActionID],tbl_GS_Assessment[Effectiveness on Vulnerability],""),_xlpm.e,_xlfn.XLOOKUP(tbl_Summary_Linkage[[#This Row],[ActionID]],tbl_GS_Assessment[ActionID],tbl_GS_Assessment[Effectiveness on Exposure],""),IF(OR(_xlpm.v="High effectiveness",_xlpm.v="Medium effectiveness",_xlpm.v="Low effectiveness",_xlpm.e="High effectiveness",_xlpm.e="Medium effectiveness",_xlpm.e="Low effectiveness"),"Yes","")),"") | I10: =IFERROR(_xlfn.LET(_xlpm.v,_xlfn.XLOOKUP(tbl_Summary_Linkage[[#This Row],[ActionID]],tbl_B_Assessment[ActionID],tbl_B_Assessment[Effectiveness on Vulnerability],""),_xlpm.e,_xlfn.XLOOKUP(tbl_Summary_Linkage[[#This Row],[ActionID]],tbl_B_Assessment[ActionID],tbl_B_Assessment[Effectiveness on Exposure],""),IF(OR(_xlpm.v="High effectiveness",_xlpm.v="Medium effectiveness",_xlpm.v="Low effectiveness",_xlpm.e="High effectiveness",_xlpm.e="Medium effectiveness",_xlpm.e="Low effectiveness"),"Yes","")),"")
B11: c40_0062 | C11: Reform water tariffs to support efficiency and equity | D11: =IFERROR(_xlfn.LET(_xlpm.v,_xlfn.XLOOKUP(tbl_Summary_Linkage[[#This Row],[ActionID]],tbl_WR_Assessment[ActionID],tbl_WR_Assessment[Effectiveness on Vulnerability],""),_xlpm.e,_xlfn.XLOOKUP(tbl_Summary_Linkage[[#This Row],[ActionID]],tbl_WR_Assessment[ActionID],tbl_WR_Assessment[Effectiveness on Exposure],""),IF(OR(_xlpm.v="High effectiveness",_xlpm.v="Medium effectiveness",_xlpm.v="Low effectiveness",_xlpm.e="High effectiveness",_xlpm.e="Medium effectiveness",_xlpm.e="Low effectiveness"),"Yes","")),"") -> Yes | E11: =IFERROR(_xlfn.LET(_xlpm.v,_xlfn.XLOOKUP(tbl_Summary_Linkage[[#This Row],[ActionID]],tbl_FS_Assessment[ActionID],tbl_FS_Assessment[Effectiveness on Vulnerability],""),_xlpm.e,_xlfn.XLOOKUP(tbl_Summary_Linkage[[#This Row],[ActionID]],tbl_FS_Assessment[ActionID],tbl_FS_Assessment[Effectiveness on Exposure],""),IF(OR(_xlpm.v="High effectiveness",_xlpm.v="Medium effectiveness",_xlpm.v="Low effectiveness",_xlpm.e="High effectiveness",_xlpm.e="Medium effectiveness",_xlpm.e="Low effectiveness"),"Yes","")),"") | F11: =IFERROR(_xlfn.LET(_xlpm.v,_xlfn.XLOOKUP(tbl_Summary_Linkage[[#This Row],[ActionID]],tbl_ES_Assessment[ActionID],tbl_ES_Assessment[Effectiveness on Vulnerability],""),_xlpm.e,_xlfn.XLOOKUP(tbl_Summary_Linkage[[#This Row],[ActionID]],tbl_ES_Assessment[ActionID],tbl_ES_Assessment[Effectiveness on Exposure],""),IF(OR(_xlpm.v="High effectiveness",_xlpm.v="Medium effectiveness",_xlpm.v="Low effectiveness",_xlpm.e="High effectiveness",_xlpm.e="Medium effectiveness",_xlpm.e="Low effectiveness"),"Yes","")),"") | G11: =IFERROR(_xlfn.LET(_xlpm.v,_xlfn.XLOOKUP(tbl_Summary_Linkage[[#This Row],[ActionID]],tbl_H_Assessment[ActionID],tbl_H_Assessment[Effectiveness on Vulnerability],""),_xlpm.e,_xlfn.XLOOKUP(tbl_Summary_Linkage[[#This Row],[ActionID]],tbl_H_Assessment[ActionID],tbl_H_Assessment[Effectiveness on Exposure],""),IF(OR(_xlpm.v="High effectiveness",_xlpm.v="Medium effectiveness",_xlpm.v="Low effectiveness",_xlpm.e="High effectiveness",_xlpm.e="Medium effectiveness",_xlpm.e="Low effectiveness"),"Yes","")),"") | H11: =IFERROR(_xlfn.LET(_xlpm.v,_xlfn.XLOOKUP(tbl_Summary_Linkage[[#This Row],[ActionID]],tbl_GS_Assessment[ActionID],tbl_GS_Assessment[Effectiveness on Vulnerability],""),_xlpm.e,_xlfn.XLOOKUP(tbl_Summary_Linkage[[#This Row],[ActionID]],tbl_GS_Assessment[ActionID],tbl_GS_Assessment[Effectiveness on Exposure],""),IF(OR(_xlpm.v="High effectiveness",_xlpm.v="Medium effectiveness",_xlpm.v="Low effectiveness",_xlpm.e="High effectiveness",_xlpm.e="Medium effectiveness",_xlpm.e="Low effectiveness"),"Yes","")),"") | I11: =IFERROR(_xlfn.LET(_xlpm.v,_xlfn.XLOOKUP(tbl_Summary_Linkage[[#This Row],[ActionID]],tbl_B_Assessment[ActionID],tbl_B_Assessment[Effectiveness on Vulnerability],""),_xlpm.e,_xlfn.XLOOKUP(tbl_Summary_Linkage[[#This Row],[ActionID]],tbl_B_Assessment[ActionID],tbl_B_Assessment[Effectiveness on Exposure],""),IF(OR(_xlpm.v="High effectiveness",_xlpm.v="Medium effectiveness",_xlpm.v="Low effectiveness",_xlpm.e="High effectiveness",_xlpm.e="Medium effectiveness",_xlpm.e="Low effectiveness"),"Yes","")),"")
B12: icare_0144 | C12: Establish a financial support program for extreme weather events | D12: =IFERROR(_xlfn.LET(_xlpm.v,_xlfn.XLOOKUP(tbl_Summary_Linkage[[#This Row],[ActionID]],tbl_WR_Assessment[ActionID],tbl_WR_Assessment[Effectiveness on Vulnerability],""),_xlpm.e,_xlfn.XLOOKUP(tbl_Summary_Linkage[[#This Row],[ActionID]],tbl_WR_Assessment[ActionID],tbl_WR_Assessment[Effectiveness on Exposure],""),IF(OR(_xlpm.v="High effectiveness",_xlpm.v="Medium effectiveness",_xlpm.v="Low effectiveness",_xlpm.e="High effectiveness",_xlpm.e="Medium effectiveness",_xlpm.e="Low effectiveness"),"Yes","")),"") | E12: =IFERROR(_xlfn.LET(_xlpm.v,_xlfn.XLOOKUP(tbl_Summary_Linkage[[#This Row],[ActionID]],tbl_FS_Assessment[ActionID],tbl_FS_Assessment[Effectiveness on Vulnerability],""),_xlpm.e,_xlfn.XLOOKUP(tbl_Summary_Linkage[[#This Row],[ActionID]],tbl_FS_Assessment[ActionID],tbl_FS_Assessment[Effectiveness on Exposure],""),IF(OR(_xlpm.v="High effectiveness",_xlpm.v="Medium effectiveness",_xlpm.v="Low effectiveness",_xlpm.e="High effectiveness",_xlpm.e="Medium effectiveness",_xlpm.e="Low effectiveness"),"Yes","")),"") | F12: =IFERROR(_xlfn.LET(_xlpm.v,_xlfn.XLOOKUP(tbl_Summary_Linkage[[#This Row],[ActionID]],tbl_ES_Assessment[ActionID],tbl_ES_Assessment[Effectiveness on Vulnerability],""),_xlpm.e,_xlfn.XLOOKUP(tbl_Summary_Linkage[[#This Row],[ActionID]],tbl_ES_Assessment[ActionID],tbl_ES_Assessment[Effectiveness on Exposure],""),IF(OR(_xlpm.v="High effectiveness",_xlpm.v="Medium effectiveness",_xlpm.v="Low effectiveness",_xlpm.e="High effectiveness",_xlpm.e="Medium effectiveness",_xlpm.e="Low effectiveness"),"Yes","")),"") | G12: =IFERROR(_xlfn.LET(_xlpm.v,_xlfn.XLOOKUP(tbl_Summary_Linkage[[#This Row],[ActionID]],tbl_H_Assessment[ActionID],tbl_H_Assessment[Effectiveness on Vulnerability],""),_xlpm.e,_xlfn.XLOOKUP(tbl_Summary_Linkage[[#This Row],[ActionID]],tbl_H_Assessment[ActionID],tbl_H_Assessment[Effectiveness on Exposure],""),IF(OR(_xlpm.v="High effectiveness",_xlpm.v="Medium effectiveness",_xlpm.v="Low effectiveness",_xlpm.e="High effectiveness",_xlpm.e="Medium effectiveness",_xlpm.e="Low effectiveness"),"Yes","")),"") | H12: =IFERROR(_xlfn.LET(_xlpm.v,_xlfn.XLOOKUP(tbl_Summary_Linkage[[#This Row],[ActionID]],tbl_GS_Assessment[ActionID],tbl_GS_Assessment[Effectiveness on Vulnerability],""),_xlpm.e,_xlfn.XLOOKUP(tbl_Summary_Linkage[[#This Row],[ActionID]],tbl_GS_Assessment[ActionID],tbl_GS_Assessment[Effectiveness on Exposure],""),IF(OR(_xlpm.v="High effectiveness",_xlpm.v="Medium effectiveness",_xlpm.v="Low effectiveness",_xlpm.e="High effectiveness",_xlpm.e="Medium effectiveness",_xlpm.e="Low effectiveness"),"Yes","")),"") | I12: =IFERROR(_xlfn.LET(_xlpm.v,_xlfn.XLOOKUP(tbl_Summary_Linkage[[#This Row],[ActionID]],tbl_B_Assessment[ActionID],tbl_B_Assessment[Effectiveness on Vulnerability],""),_xlpm.e,_xlfn.XLOOKUP(tbl_Summary_Linkage[[#This Row],[ActionID]],tbl_B_Assessment[ActionID],tbl_B_Assessment[Effectiveness on Exposure],""),IF(OR(_xlpm.v="High effectiveness",_xlpm.v="Medium effectiveness",_xlpm.v="Low effectiveness",_xlpm.e="High effectiveness",_xlpm.e="Medium effectiveness",_xlpm.e="Low effectiveness"),"Yes","")),"")
B13: icare_0145 | C13: Strengthen the healthcare system to respond effectively to extreme events | D13: =IFERROR(_xlfn.LET(_xlpm.v,_xlfn.XLOOKUP(tbl_Summary_Linkage[[#This Row],[ActionID]],tbl_WR_Assessment[ActionID],tbl_WR_Assessment[Effectiveness on Vulnerability],""),_xlpm.e,_xlfn.XLOOKUP(tbl_Summary_Linkage[[#This Row],[ActionID]],tbl_WR_Assessment[ActionID],tbl_WR_Assessment[Effectiveness on Exposure],""),IF(OR(_xlpm.v="High effectiveness",_xlpm.v="Medium effectiveness",_xlpm.v="Low effectiveness",_xlpm.e="High effectiveness",_xlpm.e="Medium effectiveness",_xlpm.e="Low effectiveness"),"Yes","")),"") | E13: =IFERROR(_xlfn.LET(_xlpm.v,_xlfn.XLOOKUP(tbl_Summary_Linkage[[#This Row],[ActionID]],tbl_FS_Assessment[ActionID],tbl_FS_Assessment[Effectiveness on Vulnerability],""),_xlpm.e,_xlfn.XLOOKUP(tbl_Summary_Linkage[[#This Row],[ActionID]],tbl_FS_Assessment[ActionID],tbl_FS_Assessment[Effectiveness on Exposure],""),IF(OR(_xlpm.v="High effectiveness",_xlpm.v="Medium effectiveness",_xlpm.v="Low effectiveness",_xlpm.e="High effectiveness",_xlpm.e="Medium effectiveness",_xlpm.e="Low effectiveness"),"Yes","")),"") | F13: =IFERROR(_xlfn.LET(_xlpm.v,_xlfn.XLOOKUP(tbl_Summary_Linkage[[#This Row],[ActionID]],tbl_ES_Assessment[ActionID],tbl_ES_Assessment[Effectiveness on Vulnerability],""),_xlpm.e,_xlfn.XLOOKUP(tbl_Summary_Linkage[[#This Row],[ActionID]],tbl_ES_Assessment[ActionID],tbl_ES_Assessment[Effectiveness on Exposure],""),IF(OR(_xlpm.v="High effectiveness",_xlpm.v="Medium effectiveness",_xlpm.v="Low effectiveness",_xlpm.e="High effectiveness",_xlpm.e="Medium effectiveness",_xlpm.e="Low effectiveness"),"Yes","")),"") | G13: =IFERROR(_xlfn.LET(_xlpm.v,_xlfn.XLOOKUP(tbl_Summary_Linkage[[#This Row],[ActionID]],tbl_H_Assessment[ActionID],tbl_H_Assessment[Effectiveness on Vulnerability],""),_xlpm.e,_xlfn.XLOOKUP(tbl_Summary_Linkage[[#This Row],[ActionID]],tbl_H_Assessment[ActionID],tbl_H_Assessment[Effectiveness on Exposure],""),IF(OR(_xlpm.v="High effectiveness",_xlpm.v="Medium effectiveness",_xlpm.v="Low effectiveness",_xlpm.e="High effectiveness",_xlpm.e="Medium effectiveness",_xlpm.e="Low effectiveness"),"Yes","")),"") | H13: =IFERROR(_xlfn.LET(_xlpm.v,_xlfn.XLOOKUP(tbl_Summary_Linkage[[#This Row],[ActionID]],tbl_GS_Assessment[ActionID],tbl_GS_Assessment[Effectiveness on Vulnerability],""),_xlpm.e,_xlfn.XLOOKUP(tbl_Summary_Linkage[[#This Row],[ActionID]],tbl_GS_Assessment[ActionID],tbl_GS_Assessment[Effectiveness on Exposure],""),IF(OR(_xlpm.v="High effectiveness",_xlpm.v="Medium effectiveness",_xlpm.v="Low effectiveness",_xlpm.e="High effectiveness",_xlpm.e="Medium effectiveness",_xlpm.e="Low effectiveness"),"Yes","")),"") | I13: =IFERROR(_xlfn.LET(_xlpm.v,_xlfn.XLOOKUP(tbl_Summary_Linkage[[#This Row],[ActionID]],tbl_B_Assessment[ActionID],tbl_B_Assessment[Effectiveness on Vulnerability],""),_xlpm.e,_xlfn.XLOOKUP(tbl_Summary_Linkage[[#This Row],[ActionID]],tbl_B_Assessment[ActionID],tbl_B_Assessment[Effectiveness on Exposure],""),IF(OR(_xlpm.v="High effectiveness",_xlpm.v="Medium effectiveness",_xlpm.v="Low effectiveness",_xlpm.e="High effectiveness",_xlpm.e="Medium effectiveness",_xlpm.e="Low effectiveness"),"Yes","")),"")
B14: icare_0154 | C14: Clean and unclog drainage channels and install eco-barriers | D14: =IFERROR(_xlfn.LET(_xlpm.v,_xlfn.XLOOKUP(tbl_Summary_Linkage[[#This Row],[ActionID]],tbl_WR_Assessment[ActionID],tbl_WR_Assessment[Effectiveness on Vulnerability],""),_xlpm.e,_xlfn.XLOOKUP(tbl_Summary_Linkage[[#This Row],[ActionID]],tbl_WR_Assessment[ActionID],tbl_WR_Assessment[Effectiveness on Exposure],""),IF(OR(_xlpm.v="High effectiveness",_xlpm.v="Medium effectiveness",_xlpm.v="Low effectiveness",_xlpm.e="High effectiveness",_xlpm.e="Medium effectiveness",_xlpm.e="Low effectiveness"),"Yes","")),"") | E14: =IFERROR(_xlfn.LET(_xlpm.v,_xlfn.XLOOKUP(tbl_Summary_Linkage[[#This Row],[ActionID]],tbl_FS_Assessment[ActionID],tbl_FS_Assessment[Effectiveness on Vulnerability],""),_xlpm.e,_xlfn.XLOOKUP(tbl_Summary_Linkage[[#This Row],[ActionID]],tbl_FS_Assessment[ActionID],tbl_FS_Assessment[Effectiveness on Exposure],""),IF(OR(_xlpm.v="High effectiveness",_xlpm.v="Medium effectiveness",_xlpm.v="Low effectiveness",_xlpm.e="High effectiveness",_xlpm.e="Medium effectiveness",_xlpm.e="Low effectiveness"),"Yes","")),"") | F14: =IFERROR(_xlfn.LET(_xlpm.v,_xlfn.XLOOKUP(tbl_Summary_Linkage[[#This Row],[ActionID]],tbl_ES_Assessment[ActionID],tbl_ES_Assessment[Effectiveness on Vulnerability],""),_xlpm.e,_xlfn.XLOOKUP(tbl_Summary_Linkage[[#This Row],[ActionID]],tbl_ES_Assessment[ActionID],tbl_ES_Assessment[Effectiveness on Exposure],""),IF(OR(_xlpm.v="High effectiveness",_xlpm.v="Medium effectiveness",_xlpm.v="Low effectiveness",_xlpm.e="High effectiveness",_xlpm.e="Medium effectiveness",_xlpm.e="Low effectiveness"),"Yes","")),"") | G14: =IFERROR(_xlfn.LET(_xlpm.v,_xlfn.XLOOKUP(tbl_Summary_Linkage[[#This Row],[ActionID]],tbl_H_Assessment[ActionID],tbl_H_Assessment[Effectiveness on Vulnerability],""),_xlpm.e,_xlfn.XLOOKUP(tbl_Summary_Linkage[[#This Row],[ActionID]],tbl_H_Assessment[ActionID],tbl_H_Assessment[Effectiveness on Exposure],""),IF(OR(_xlpm.v="High effectiveness",_xlpm.v="Medium effectiveness",_xlpm.v="Low effectiveness",_xlpm.e="High effectiveness",_xlpm.e="Medium effectiveness",_xlpm.e="Low effectiveness"),"Yes","")),"") | H14: =IFERROR(_xlfn.LET(_xlpm.v,_xlfn.XLOOKUP(tbl_Summary_Linkage[[#This Row],[ActionID]],tbl_GS_Assessment[ActionID],tbl_GS_Assessment[Effectiveness on Vulnerability],""),_xlpm.e,_xlfn.XLOOKUP(tbl_Summary_Linkage[[#This Row],[ActionID]],tbl_GS_Assessment[ActionID],tbl_GS_Assessment[Effectiveness on Exposure],""),IF(OR(_xlpm.v="High effectiveness",_xlpm.v="Medium effectiveness",_xlpm.v="Low effectiveness",_xlpm.e="High effectiveness",_xlpm.e="Medium effectiveness",_xlpm.e="Low effectiveness"),"Yes","")),"") | I14: =IFERROR(_xlfn.LET(_xlpm.v,_xlfn.XLOOKUP(tbl_Summary_Linkage[[#This Row],[ActionID]],tbl_B_Assessment[ActionID],tbl_B_Assessment[Effectiveness on Vulnerability],""),_xlpm.e,_xlfn.XLOOKUP(tbl_Summary_Linkage[[#This Row],[ActionID]],tbl_B_Assessment[ActionID],tbl_B_Assessment[Effectiveness on Exposure],""),IF(OR(_xlpm.v="High effectiveness",_xlpm.v="Medium effectiveness",_xlpm.v="Low effectiveness",_xlpm.e="High effectiveness",_xlpm.e="Medium effectiveness",_xlpm.e="Low effectiveness"),"Yes","")),"")
B15: icare_0156 | C15: Improve Implementation of urban gardens | D15: =IFERROR(_xlfn.LET(_xlpm.v,_xlfn.XLOOKUP(tbl_Summary_Linkage[[#This Row],[ActionID]],tbl_WR_Assessment[ActionID],tbl_WR_Assessment[Effectiveness on Vulnerability],""),_xlpm.e,_xlfn.XLOOKUP(tbl_Summary_Linkage[[#This Row],[ActionID]],tbl_WR_Assessment[ActionID],tbl_WR_Assessment[Effectiveness on Exposure],""),IF(OR(_xlpm.v="High effectiveness",_xlpm.v="Medium effectiveness",_xlpm.v="Low effectiveness",_xlpm.e="High effectiveness",_xlpm.e="Medium effectiveness",_xlpm.e="Low effectiveness"),"Yes","")),"") | E15: =IFERROR(_xlfn.LET(_xlpm.v,_xlfn.XLOOKUP(tbl_Summary_Linkage[[#This Row],[ActionID]],tbl_FS_Assessment[ActionID],tbl_FS_Assessment[Effectiveness on Vulnerability],""),_xlpm.e,_xlfn.XLOOKUP(tbl_Summary_Linkage[[#This Row],[ActionID]],tbl_FS_Assessment[ActionID],tbl_FS_Assessment[Effectiveness on Exposure],""),IF(OR(_xlpm.v="High effectiveness",_xlpm.v="Medium effectiveness",_xlpm.v="Low effectiveness",_xlpm.e="High effectiveness",_xlpm.e="Medium effectiveness",_xlpm.e="Low effectiveness"),"Yes","")),"") | F15: =IFERROR(_xlfn.LET(_xlpm.v,_xlfn.XLOOKUP(tbl_Summary_Linkage[[#This Row],[ActionID]],tbl_ES_Assessment[ActionID],tbl_ES_Assessment[Effectiveness on Vulnerability],""),_xlpm.e,_xlfn.XLOOKUP(tbl_Summary_Linkage[[#This Row],[ActionID]],tbl_ES_Assessment[ActionID],tbl_ES_Assessment[Effectiveness on Exposure],""),IF(OR(_xlpm.v="High effectiveness",_xlpm.v="Medium effectiveness",_xlpm.v="Low effectiveness",_xlpm.e="High effectiveness",_xlpm.e="Medium effectiveness",_xlpm.e="Low effectiveness"),"Yes","")),"") | G15: =IFERROR(_xlfn.LET(_xlpm.v,_xlfn.XLOOKUP(tbl_Summary_Linkage[[#This Row],[ActionID]],tbl_H_Assessment[ActionID],tbl_H_Assessment[Effectiveness on Vulnerability],""),_xlpm.e,_xlfn.XLOOKUP(tbl_Summary_Linkage[[#This Row],[ActionID]],tbl_H_Assessment[ActionID],tbl_H_Assessment[Effectiveness on Exposure],""),IF(OR(_xlpm.v="High effectiveness",_xlpm.v="Medium effectiveness",_xlpm.v="Low effectiveness",_xlpm.e="High effectiveness",_xlpm.e="Medium effectiveness",_xlpm.e="Low effectiveness"),"Yes","")),"") | H15: =IFERROR(_xlfn.LET(_xlpm.v,_xlfn.XLOOKUP(tbl_Summary_Linkage[[#This Row],[ActionID]],tbl_GS_Assessment[ActionID],tbl_GS_Assessment[Effectiveness on Vulnerability],""),_xlpm.e,_xlfn.XLOOKUP(tbl_Summary_Linkage[[#This Row],[ActionID]],tbl_GS_Assessment[ActionID],tbl_GS_Assessment[Effectiveness on Exposure],""),IF(OR(_xlpm.v="High effectiveness",_xlpm.v="Medium effectiveness",_xlpm.v="Low effectiveness",_xlpm.e="High effectiveness",_xlpm.e="Medium effectiveness",_xlpm.e="Low effectiveness"),"Yes","")),"") | I15: =IFERROR(_xlfn.LET(_xlpm.v,_xlfn.XLOOKUP(tbl_Summary_Linkage[[#This Row],[ActionID]],tbl_B_Assessment[ActionID],tbl_B_Assessment[Effectiveness on Vulnerability],""),_xlpm.e,_xlfn.XLOOKUP(tbl_Summary_Linkage[[#This Row],[ActionID]],tbl_B_Assessment[ActionID],tbl_B_Assessment[Effectiveness on Exposure],""),IF(OR(_xlpm.v="High effectiveness",_xlpm.v="Medium effectiveness",_xlpm.v="Low effectiveness",_xlpm.e="High effectiveness",_xlpm.e="Medium effectiveness",_xlpm.e="Low effectiveness"),"Yes","")),"")
... B56: ipcc_0104 | C56: Plan and support permanent climate‑related migration | D56: =IFERROR(_xlfn.LET(_xlpm.v,_xlfn.XLOOKUP(tbl_Summary_Linkage[[#This Row],[ActionID]],tbl_WR_Assessment[ActionID],tbl_WR_Assessment[Effectiveness on Vulnerability],""),_xlpm.e,_xlfn.XLOOKUP(tbl_Summary_Linkage[[#This Row],[ActionID]],tbl_WR_Assessment[ActionID],tbl_WR_Assessment[Effectiveness on Exposure],""),IF(OR(_xlpm.v="High effectiveness",_xlpm.v="Medium effectiveness",_xlpm.v="Low effectiveness",_xlpm.e="High effectiveness",_xlpm.e="Medium effectiveness",_xlpm.e="Low effectiveness"),"Yes","")),"") | E56: =IFERROR(_xlfn.LET(_xlpm.v,_xlfn.XLOOKUP(tbl_Summary_Linkage[[#This Row],[ActionID]],tbl_FS_Assessment[ActionID],tbl_FS_Assessment[Effectiveness on Vulnerability],""),_xlpm.e,_xlfn.XLOOKUP(tbl_Summary_Linkage[[#This Row],[ActionID]],tbl_FS_Assessment[ActionID],tbl_FS_Assessment[Effectiveness on Exposure],""),IF(OR(_xlpm.v="High effectiveness",_xlpm.v="Medium effectiveness",_xlpm.v="Low effectiveness",_xlpm.e="High effectiveness",_xlpm.e="Medium effectiveness",_xlpm.e="Low effectiveness"),"Yes","")),"") | F56: =IFERROR(_xlfn.LET(_xlpm.v,_xlfn.XLOOKUP(tbl_Summary_Linkage[[#This Row],[ActionID]],tbl_ES_Assessment[ActionID],tbl_ES_Assessment[Effectiveness on Vulnerability],""),_xlpm.e,_xlfn.XLOOKUP(tbl_Summary_Linkage[[#This Row],[ActionID]],tbl_ES_Assessment[ActionID],tbl_ES_Assessment[Effectiveness on Exposure],""),IF(OR(_xlpm.v="High effectiveness",_xlpm.v="Medium effectiveness",_xlpm.v="Low effectiveness",_xlpm.e="High effectiveness",_xlpm.e="Medium effectiveness",_xlpm.e="Low effectiveness"),"Yes","")),"") | G56: =IFERROR(_xlfn.LET(_xlpm.v,_xlfn.XLOOKUP(tbl_Summary_Linkage[[#This Row],[ActionID]],tbl_H_Assessment[ActionID],tbl_H_Assessment[Effectiveness on Vulnerability],""),_xlpm.e,_xlfn.XLOOKUP(tbl_Summary_Linkage[[#This Row],[ActionID]],tbl_H_Assessment[ActionID],tbl_H_Assessment[Effectiveness on Exposure],""),IF(OR(_xlpm.v="High effectiveness",_xlpm.v="Medium effectiveness",_xlpm.v="Low effectiveness",_xlpm.e="High effectiveness",_xlpm.e="Medium effectiveness",_xlpm.e="Low effectiveness"),"Yes","")),"") | H56: =IFERROR(_xlfn.LET(_xlpm.v,_xlfn.XLOOKUP(tbl_Summary_Linkage[[#This Row],[ActionID]],tbl_GS_Assessment[ActionID],tbl_GS_Assessment[Effectiveness on Vulnerability],""),_xlpm.e,_xlfn.XLOOKUP(tbl_Summary_Linkage[[#This Row],[ActionID]],tbl_GS_Assessment[ActionID],tbl_GS_Assessment[Effectiveness on Exposure],""),IF(OR(_xlpm.v="High effectiveness",_xlpm.v="Medium effectiveness",_xlpm.v="Low effectiveness",_xlpm.e="High effectiveness",_xlpm.e="Medium effectiveness",_xlpm.e="Low effectiveness"),"Yes","")),"") | I56: =IFERROR(_xlfn.LET(_xlpm.v,_xlfn.XLOOKUP(tbl_Summary_Linkage[[#This Row],[ActionID]],tbl_B_Assessment[ActionID],tbl_B_Assessment[Effectiveness on Vulnerability],""),_xlpm.e,_xlfn.XLOOKUP(tbl_Summary_Linkage[[#This Row],[ActionID]],tbl_B_Assessment[ActionID],tbl_B_Assessment[Effectiveness on Exposure],""),IF(OR(_xlpm.v="High effectiveness",_xlpm.v="Medium effectiveness",_xlpm.v="Low effectiveness",_xlpm.e="High effectiveness",_xlpm.e="Medium effectiveness",_xlpm.e="Low effectiveness"),"Yes","")),"")
B59: PARAMETER TABLE
B60: Parameter | C60: Default value
B61: High effectiveness | C61: -1
B62: Medium effectiveness | C62: -0.5
B63: Low effectiveness | C63: -0.25
B64: No effectiveness | C64: 0
B67: SUMMARY MATRIX
B68: ActionID | C68: ActionName | D68: Water Resources - Effectiveness on Vulnerability | E68: Water Resources - Effectiveness on Exposure | F68: Food Security - Effectiveness on Vulnerability | G68: Food Security - Effectiveness on Exposure | H68: Energy Security - Effectiveness on Vulnerability | I68: Energy Security - Effectiveness on Exposure | J68: Health - Effectiveness on Vulnerability | K68: Health - Effectiveness on Exposure | L68: Geohydrological Disasters - Effectiveness on Vulnerability | M68: Geohydrological Disasters - Effectiveness on Exposure | N68: Biodiversity - Effectiveness on Vulnerability | O68: Biodiversity - Effectiveness on Exposure
B69: c40_0046 | C69: Strengthen coastal protection infrastructure | D69: =IFERROR(IF(_xlfn.XLOOKUP(tbl_Summary_Numerical[[#This Row],[ActionID]],tbl_WR_EligibilitySummary[Action ID],tbl_WR_EligibilitySummary[Vulnerability Eligibility],"")="Eligible",_xlfn.XLOOKUP(_xlfn.XLOOKUP(tbl_Summary_Numerical[[#This Row],[ActionID]],tbl_WR_Assessment[ActionID],tbl_WR_Assessment[Effectiveness on Vulnerability],""),'Summary Matrix'!$B$61:$B$64,'Summary Matrix'!$C$61:$C$64,""),""),"") | E69: =IFERROR(IF(_xlfn.XLOOKUP(tbl_Summary_Numerical[[#This Row],[ActionID]],tbl_WR_EligibilitySummary[Action ID],tbl_WR_EligibilitySummary[Exposure Eligibility],"")="Eligible",_xlfn.XLOOKUP(_xlfn.XLOOKUP(tbl_Summary_Numerical[[#This Row],[ActionID]],tbl_WR_Assessment[ActionID],tbl_WR_Assessment[Effectiveness on Exposure],""),'Summary Matrix'!$B$61:$B$64,'Summary Matrix'!$C$61:$C$64,""),""),"") | F69: =IFERROR(IF(_xlfn.XLOOKUP(tbl_Summary_Numerical[[#This Row],[ActionID]],tbl_FS_EligibilitySummary[Action ID],tbl_FS_EligibilitySummary[Vulnerability Eligibility],"")="Eligible",_xlfn.XLOOKUP(_xlfn.XLOOKUP(tbl_Summary_Numerical[[#This Row],[ActionID]],tbl_FS_Assessment[ActionID],tbl_FS_Assessment[Effectiveness on Vulnerability],""),'Summary Matrix'!$B$61:$B$64,'Summary Matrix'!$C$61:$C$64,""),""),"") | G69: =IFERROR(IF(_xlfn.XLOOKUP(tbl_Summary_Numerical[[#This Row],[ActionID]],tbl_FS_EligibilitySummary[Action ID],tbl_FS_EligibilitySummary[Exposure Eligibility],"")="Eligible",_xlfn.XLOOKUP(_xlfn.XLOOKUP(tbl_Summary_Numerical[[#This Row],[ActionID]],tbl_FS_Assessment[ActionID],tbl_FS_Assessment[Effectiveness on Exposure],""),'Summary Matrix'!$B$61:$B$64,'Summary Matrix'!$C$61:$C$64,""),""),"") | H69: =IFERROR(IF(_xlfn.XLOOKUP(tbl_Summary_Numerical[[#This Row],[ActionID]],tbl_ES_EligibilitySummary[Action ID],tbl_ES_EligibilitySummary[Vulnerability Eligibility],"")="Eligible",_xlfn.XLOOKUP(_xlfn.XLOOKUP(tbl_Summary_Numerical[[#This Row],[ActionID]],tbl_ES_Assessment[ActionID],tbl_ES_Assessment[Effectiveness on Vulnerability],""),'Summary Matrix'!$B$61:$B$64,'Summary Matrix'!$C$61:$C$64,""),""),"") | I69: =IFERROR(IF(_xlfn.XLOOKUP(tbl_Summary_Numerical[[#This Row],[ActionID]],tbl_ES_EligibilitySummary[Action ID],tbl_ES_EligibilitySummary[Exposure Eligibility],"")="Eligible",_xlfn.XLOOKUP(_xlfn.XLOOKUP(tbl_Summary_Numerical[[#This Row],[ActionID]],tbl_ES_Assessment[ActionID],tbl_ES_Assessment[Effectiveness on Exposure],""),'Summary Matrix'!$B$61:$B$64,'Summary Matrix'!$C$61:$C$64,""),""),"") | J69: =IFERROR(IF(_xlfn.XLOOKUP(tbl_Summary_Numerical[[#This Row],[ActionID]],tbl_H_EligibilitySummary[Action ID],tbl_H_EligibilitySummary[Vulnerability Eligibility],"")="Eligible",_xlfn.XLOOKUP(_xlfn.XLOOKUP(tbl_Summary_Numerical[[#This Row],[ActionID]],tbl_H_Assessment[ActionID],tbl_H_Assessment[Effectiveness on Vulnerability],""),'Summary Matrix'!$B$61:$B$64,'Summary Matrix'!$C$61:$C$64,""),""),"") | K69: =IFERROR(IF(_xlfn.XLOOKUP(tbl_Summary_Numerical[[#This Row],[ActionID]],tbl_H_EligibilitySummary[Action ID],tbl_H_EligibilitySummary[Exposure Eligibility],"")="Eligible",_xlfn.XLOOKUP(_xlfn.XLOOKUP(tbl_Summary_Numerical[[#This Row],[ActionID]],tbl_H_Assessment[ActionID],tbl_H_Assessment[Effectiveness on Exposure],""),'Summary Matrix'!$B$61:$B$64,'Summary Matrix'!$C$61:$C$64,""),""),"") | L69: =IFERROR(IF(_xlfn.XLOOKUP(tbl_Summary_Numerical[[#This Row],[ActionID]],tbl_GS_EligibilitySummary[Action ID],tbl_GS_EligibilitySummary[Vulnerability Eligibility],"")="Eligible",_xlfn.XLOOKUP(_xlfn.XLOOKUP(tbl_Summary_Numerical[[#This Row],[ActionID]],tbl_GS_Assessment[ActionID],tbl_GS_Assessment[Effectiveness on Vulnerability],""),'Summary Matrix'!$B$61:$B$64,'Summary Matrix'!$C$61:$C$64,""),""),"") | M69: =IFERROR(IF(_xlfn.XLOOKUP(tbl_Summary_Numerical[[#This Row],[ActionID]],tbl_GS_EligibilitySummary[Action ID],tbl_GS_EligibilitySummary[Exposure Eligibility],"")="Eligible",_xlfn.XLOOKUP(_xlfn.XLOOKUP(tbl_Summary_Numerical[[#This Row],[ActionID]],tbl_GS_Assessment[ActionID],tbl_GS_Assessment[Effectiveness on Exposure],""),'Summary Matrix'!$B$61:$B$64,'Summary Matrix'!$C$61:$C$64,""),""),"") | N69: =IFERROR(IF(_xlfn.XLOOKUP(tbl_Summary_Numerical[[#This Row],[ActionID]],tbl_B_EligibilitySummary[Action ID],tbl_B_EligibilitySummary[Vulnerability Eligibility],"")="Eligible",_xlfn.XLOOKUP(_xlfn.XLOOKUP(tbl_Summary_Numerical[[#This Row],[ActionID]],tbl_B_Assessment[ActionID],tbl_B_Assessment[Effectiveness on Vulnerability],""),'Summary Matrix'!$B$61:$B$64,'Summary Matrix'!$C$61:$C$64,""),""),"") | O69: =IFERROR(IF(_xlfn.XLOOKUP(tbl_Summary_Numerical[[#This Row],[ActionID]],tbl_B_EligibilitySummary[Action ID],tbl_B_EligibilitySummary[Exposure Eligibility],"")="Eligible",_xlfn.XLOOKUP(_xlfn.XLOOKUP(tbl_Summary_Numerical[[#This Row],[ActionID]],tbl_B_Assessment[ActionID],tbl_B_Assessment[Effectiveness on Exposure],""),'Summary Matrix'!$B$61:$B$64,'Summary Matrix'!$C$61:$C$64,""),""),"")
B70: c40_0048 | C70: Upgrade urban drainage systems | D70: =IFERROR(IF(_xlfn.XLOOKUP(tbl_Summary_Numerical[[#This Row],[ActionID]],tbl_WR_EligibilitySummary[Action ID],tbl_WR_EligibilitySummary[Vulnerability Eligibility],"")="Eligible",_xlfn.XLOOKUP(_xlfn.XLOOKUP(tbl_Summary_Numerical[[#This Row],[ActionID]],tbl_WR_Assessment[ActionID],tbl_WR_Assessment[Effectiveness on Vulnerability],""),'Summary Matrix'!$B$61:$B$64,'Summary Matrix'!$C$61:$C$64,""),""),"") | E70: =IFERROR(IF(_xlfn.XLOOKUP(tbl_Summary_Numerical[[#This Row],[ActionID]],tbl_WR_EligibilitySummary[Action ID],tbl_WR_EligibilitySummary[Exposure Eligibility],"")="Eligible",_xlfn.XLOOKUP(_xlfn.XLOOKUP(tbl_Summary_Numerical[[#This Row],[ActionID]],tbl_WR_Assessment[ActionID],tbl_WR_Assessment[Effectiveness on Exposure],""),'Summary Matrix'!$B$61:$B$64,'Summary Matrix'!$C$61:$C$64,""),""),"") | F70: =IFERROR(IF(_xlfn.XLOOKUP(tbl_Summary_Numerical[[#This Row],[ActionID]],tbl_FS_EligibilitySummary[Action ID],tbl_FS_EligibilitySummary[Vulnerability Eligibility],"")="Eligible",_xlfn.XLOOKUP(_xlfn.XLOOKUP(tbl_Summary_Numerical[[#This Row],[ActionID]],tbl_FS_Assessment[ActionID],tbl_FS_Assessment[Effectiveness on Vulnerability],""),'Summary Matrix'!$B$61:$B$64,'Summary Matrix'!$C$61:$C$64,""),""),"") | G70: =IFERROR(IF(_xlfn.XLOOKUP(tbl_Summary_Numerical[[#This Row],[ActionID]],tbl_FS_EligibilitySummary[Action ID],tbl_FS_EligibilitySummary[Exposure Eligibility],"")="Eligible",_xlfn.XLOOKUP(_xlfn.XLOOKUP(tbl_Summary_Numerical[[#This Row],[ActionID]],tbl_FS_Assessment[ActionID],tbl_FS_Assessment[Effectiveness on Exposure],""),'Summary Matrix'!$B$61:$B$64,'Summary Matrix'!$C$61:$C$64,""),""),"") | H70: =IFERROR(IF(_xlfn.XLOOKUP(tbl_Summary_Numerical[[#This Row],[ActionID]],tbl_ES_EligibilitySummary[Action ID],tbl_ES_EligibilitySummary[Vulnerability Eligibility],"")="Eligible",_xlfn.XLOOKUP(_xlfn.XLOOKUP(tbl_Summary_Numerical[[#This Row],[ActionID]],tbl_ES_Assessment[ActionID],tbl_ES_Assessment[Effectiveness on Vulnerability],""),'Summary Matrix'!$B$61:$B$64,'Summary Matrix'!$C$61:$C$64,""),""),"") | I70: =IFERROR(IF(_xlfn.XLOOKUP(tbl_Summary_Numerical[[#This Row],[ActionID]],tbl_ES_EligibilitySummary[Action ID],tbl_ES_EligibilitySummary[Exposure Eligibility],"")="Eligible",_xlfn.XLOOKUP(_xlfn.XLOOKUP(tbl_Summary_Numerical[[#This Row],[ActionID]],tbl_ES_Assessment[ActionID],tbl_ES_Assessment[Effectiveness on Exposure],""),'Summary Matrix'!$B$61:$B$64,'Summary Matrix'!$C$61:$C$64,""),""),"") | J70: =IFERROR(IF(_xlfn.XLOOKUP(tbl_Summary_Numerical[[#This Row],[ActionID]],tbl_H_EligibilitySummary[Action ID],tbl_H_EligibilitySummary[Vulnerability Eligibility],"")="Eligible",_xlfn.XLOOKUP(_xlfn.XLOOKUP(tbl_Summary_Numerical[[#This Row],[ActionID]],tbl_H_Assessment[ActionID],tbl_H_Assessment[Effectiveness on Vulnerability],""),'Summary Matrix'!$B$61:$B$64,'Summary Matrix'!$C$61:$C$64,""),""),"") | K70: =IFERROR(IF(_xlfn.XLOOKUP(tbl_Summary_Numerical[[#This Row],[ActionID]],tbl_H_EligibilitySummary[Action ID],tbl_H_EligibilitySummary[Exposure Eligibility],"")="Eligible",_xlfn.XLOOKUP(_xlfn.XLOOKUP(tbl_Summary_Numerical[[#This Row],[ActionID]],tbl_H_Assessment[ActionID],tbl_H_Assessment[Effectiveness on Exposure],""),'Summary Matrix'!$B$61:$B$64,'Summary Matrix'!$C$61:$C$64,""),""),"") | L70: =IFERROR(IF(_xlfn.XLOOKUP(tbl_Summary_Numerical[[#This Row],[ActionID]],tbl_GS_EligibilitySummary[Action ID],tbl_GS_EligibilitySummary[Vulnerability Eligibility],"")="Eligible",_xlfn.XLOOKUP(_xlfn.XLOOKUP(tbl_Summary_Numerical[[#This Row],[ActionID]],tbl_GS_Assessment[ActionID],tbl_GS_Assessment[Effectiveness on Vulnerability],""),'Summary Matrix'!$B$61:$B$64,'Summary Matrix'!$C$61:$C$64,""),""),"") | M70: =IFERROR(IF(_xlfn.XLOOKUP(tbl_Summary_Numerical[[#This Row],[ActionID]],tbl_GS_EligibilitySummary[Action ID],tbl_GS_EligibilitySummary[Exposure Eligibility],"")="Eligible",_xlfn.XLOOKUP(_xlfn.XLOOKUP(tbl_Summary_Numerical[[#This Row],[ActionID]],tbl_GS_Assessment[ActionID],tbl_GS_Assessment[Effectiveness on Exposure],""),'Summary Matrix'!$B$61:$B$64,'Summary Matrix'!$C$61:$C$64,""),""),"") | N70: =IFERROR(IF(_xlfn.XLOOKUP(tbl_Summary_Numerical[[#This Row],[ActionID]],tbl_B_EligibilitySummary[Action ID],tbl_B_EligibilitySummary[Vulnerability Eligibility],"")="Eligible",_xlfn.XLOOKUP(_xlfn.XLOOKUP(tbl_Summary_Numerical[[#This Row],[ActionID]],tbl_B_Assessment[ActionID],tbl_B_Assessment[Effectiveness on Vulnerability],""),'Summary Matrix'!$B$61:$B$64,'Summary Matrix'!$C$61:$C$64,""),""),"") | O70: =IFERROR(IF(_xlfn.XLOOKUP(tbl_Summary_Numerical[[#This Row],[ActionID]],tbl_B_EligibilitySummary[Action ID],tbl_B_EligibilitySummary[Exposure Eligibility],"")="Eligible",_xlfn.XLOOKUP(_xlfn.XLOOKUP(tbl_Summary_Numerical[[#This Row],[ActionID]],tbl_B_Assessment[ActionID],tbl_B_Assessment[Effectiveness on Exposure],""),'Summary Matrix'!$B$61:$B$64,'Summary Matrix'!$C$61:$C$64,""),""),"")
B71: c40_0049 | C71: Build and maintain shelters for critical climate hazards | D71: =IFERROR(IF(_xlfn.XLOOKUP(tbl_Summary_Numerical[[#This Row],[ActionID]],tbl_WR_EligibilitySummary[Action ID],tbl_WR_EligibilitySummary[Vulnerability Eligibility],"")="Eligible",_xlfn.XLOOKUP(_xlfn.XLOOKUP(tbl_Summary_Numerical[[#This Row],[ActionID]],tbl_WR_Assessment[ActionID],tbl_WR_Assessment[Effectiveness on Vulnerability],""),'Summary Matrix'!$B$61:$B$64,'Summary Matrix'!$C$61:$C$64,""),""),"") | E71: =IFERROR(IF(_xlfn.XLOOKUP(tbl_Summary_Numerical[[#This Row],[ActionID]],tbl_WR_EligibilitySummary[Action ID],tbl_WR_EligibilitySummary[Exposure Eligibility],"")="Eligible",_xlfn.XLOOKUP(_xlfn.XLOOKUP(tbl_Summary_Numerical[[#This Row],[ActionID]],tbl_WR_Assessment[ActionID],tbl_WR_Assessment[Effectiveness on Exposure],""),'Summary Matrix'!$B$61:$B$64,'Summary Matrix'!$C$61:$C$64,""),""),"") | F71: =IFERROR(IF(_xlfn.XLOOKUP(tbl_Summary_Numerical[[#This Row],[ActionID]],tbl_FS_EligibilitySummary[Action ID],tbl_FS_EligibilitySummary[Vulnerability Eligibility],"")="Eligible",_xlfn.XLOOKUP(_xlfn.XLOOKUP(tbl_Summary_Numerical[[#This Row],[ActionID]],tbl_FS_Assessment[ActionID],tbl_FS_Assessment[Effectiveness on Vulnerability],""),'Summary Matrix'!$B$61:$B$64,'Summary Matrix'!$C$61:$C$64,""),""),"") | G71: =IFERROR(IF(_xlfn.XLOOKUP(tbl_Summary_Numerical[[#This Row],[ActionID]],tbl_FS_EligibilitySummary[Action ID],tbl_FS_EligibilitySummary[Exposure Eligibility],"")="Eligible",_xlfn.XLOOKUP(_xlfn.XLOOKUP(tbl_Summary_Numerical[[#This Row],[ActionID]],tbl_FS_Assessment[ActionID],tbl_FS_Assessment[Effectiveness on Exposure],""),'Summary Matrix'!$B$61:$B$64,'Summary Matrix'!$C$61:$C$64,""),""),"") | H71: =IFERROR(IF(_xlfn.XLOOKUP(tbl_Summary_Numerical[[#This Row],[ActionID]],tbl_ES_EligibilitySummary[Action ID],tbl_ES_EligibilitySummary[Vulnerability Eligibility],"")="Eligible",_xlfn.XLOOKUP(_xlfn.XLOOKUP(tbl_Summary_Numerical[[#This Row],[ActionID]],tbl_ES_Assessment[ActionID],tbl_ES_Assessment[Effectiveness on Vulnerability],""),'Summary Matrix'!$B$61:$B$64,'Summary Matrix'!$C$61:$C$64,""),""),"") | I71: =IFERROR(IF(_xlfn.XLOOKUP(tbl_Summary_Numerical[[#This Row],[ActionID]],tbl_ES_EligibilitySummary[Action ID],tbl_ES_EligibilitySummary[Exposure Eligibility],"")="Eligible",_xlfn.XLOOKUP(_xlfn.XLOOKUP(tbl_Summary_Numerical[[#This Row],[ActionID]],tbl_ES_Assessment[ActionID],tbl_ES_Assessment[Effectiveness on Exposure],""),'Summary Matrix'!$B$61:$B$64,'Summary Matrix'!$C$61:$C$64,""),""),"") | J71: =IFERROR(IF(_xlfn.XLOOKUP(tbl_Summary_Numerical[[#This Row],[ActionID]],tbl_H_EligibilitySummary[Action ID],tbl_H_EligibilitySummary[Vulnerability Eligibility],"")="Eligible",_xlfn.XLOOKUP(_xlfn.XLOOKUP(tbl_Summary_Numerical[[#This Row],[ActionID]],tbl_H_Assessment[ActionID],tbl_H_Assessment[Effectiveness on Vulnerability],""),'Summary Matrix'!$B$61:$B$64,'Summary Matrix'!$C$61:$C$64,""),""),"") | K71: =IFERROR(IF(_xlfn.XLOOKUP(tbl_Summary_Numerical[[#This Row],[ActionID]],tbl_H_EligibilitySummary[Action ID],tbl_H_EligibilitySummary[Exposure Eligibility],"")="Eligible",_xlfn.XLOOKUP(_xlfn.XLOOKUP(tbl_Summary_Numerical[[#This Row],[ActionID]],tbl_H_Assessment[ActionID],tbl_H_Assessment[Effectiveness on Exposure],""),'Summary Matrix'!$B$61:$B$64,'Summary Matrix'!$C$61:$C$64,""),""),"") | L71: =IFERROR(IF(_xlfn.XLOOKUP(tbl_Summary_Numerical[[#This Row],[ActionID]],tbl_GS_EligibilitySummary[Action ID],tbl_GS_EligibilitySummary[Vulnerability Eligibility],"")="Eligible",_xlfn.XLOOKUP(_xlfn.XLOOKUP(tbl_Summary_Numerical[[#This Row],[ActionID]],tbl_GS_Assessment[ActionID],tbl_GS_Assessment[Effectiveness on Vulnerability],""),'Summary Matrix'!$B$61:$B$64,'Summary Matrix'!$C$61:$C$64,""),""),"") | M71: =IFERROR(IF(_xlfn.XLOOKUP(tbl_Summary_Numerical[[#This Row],[ActionID]],tbl_GS_EligibilitySummary[Action ID],tbl_GS_EligibilitySummary[Exposure Eligibility],"")="Eligible",_xlfn.XLOOKUP(_xlfn.XLOOKUP(tbl_Summary_Numerical[[#This Row],[ActionID]],tbl_GS_Assessment[ActionID],tbl_GS_Assessment[Effectiveness on Exposure],""),'Summary Matrix'!$B$61:$B$64,'Summary Matrix'!$C$61:$C$64,""),""),"") | N71: =IFERROR(IF(_xlfn.XLOOKUP(tbl_Summary_Numerical[[#This Row],[ActionID]],tbl_B_EligibilitySummary[Action ID],tbl_B_EligibilitySummary[Vulnerability Eligibility],"")="Eligible",_xlfn.XLOOKUP(_xlfn.XLOOKUP(tbl_Summary_Numerical[[#This Row],[ActionID]],tbl_B_Assessment[ActionID],tbl_B_Assessment[Effectiveness on Vulnerability],""),'Summary Matrix'!$B$61:$B$64,'Summary Matrix'!$C$61:$C$64,""),""),"") | O71: =IFERROR(IF(_xlfn.XLOOKUP(tbl_Summary_Numerical[[#This Row],[ActionID]],tbl_B_EligibilitySummary[Action ID],tbl_B_EligibilitySummary[Exposure Eligibility],"")="Eligible",_xlfn.XLOOKUP(_xlfn.XLOOKUP(tbl_Summary_Numerical[[#This Row],[ActionID]],tbl_B_Assessment[ActionID],tbl_B_Assessment[Effectiveness on Exposure],""),'Summary Matrix'!$B$61:$B$64,'Summary Matrix'!$C$61:$C$64,""),""),"")
B72: c40_0051 | C72: Provide public shading in heat hotspots | D72: =IFERROR(IF(_xlfn.XLOOKUP(tbl_Summary_Numerical[[#This Row],[ActionID]],tbl_WR_EligibilitySummary[Action ID],tbl_WR_EligibilitySummary[Vulnerability Eligibility],"")="Eligible",_xlfn.XLOOKUP(_xlfn.XLOOKUP(tbl_Summary_Numerical[[#This Row],[ActionID]],tbl_WR_Assessment[ActionID],tbl_WR_Assessment[Effectiveness on Vulnerability],""),'Summary Matrix'!$B$61:$B$64,'Summary Matrix'!$C$61:$C$64,""),""),"") | E72: =IFERROR(IF(_xlfn.XLOOKUP(tbl_Summary_Numerical[[#This Row],[ActionID]],tbl_WR_EligibilitySummary[Action ID],tbl_WR_EligibilitySummary[Exposure Eligibility],"")="Eligible",_xlfn.XLOOKUP(_xlfn.XLOOKUP(tbl_Summary_Numerical[[#This Row],[ActionID]],tbl_WR_Assessment[ActionID],tbl_WR_Assessment[Effectiveness on Exposure],""),'Summary Matrix'!$B$61:$B$64,'Summary Matrix'!$C$61:$C$64,""),""),"") | F72: =IFERROR(IF(_xlfn.XLOOKUP(tbl_Summary_Numerical[[#This Row],[ActionID]],tbl_FS_EligibilitySummary[Action ID],tbl_FS_EligibilitySummary[Vulnerability Eligibility],"")="Eligible",_xlfn.XLOOKUP(_xlfn.XLOOKUP(tbl_Summary_Numerical[[#This Row],[ActionID]],tbl_FS_Assessment[ActionID],tbl_FS_Assessment[Effectiveness on Vulnerability],""),'Summary Matrix'!$B$61:$B$64,'Summary Matrix'!$C$61:$C$64,""),""),"") | G72: =IFERROR(IF(_xlfn.XLOOKUP(tbl_Summary_Numerical[[#This Row],[ActionID]],tbl_FS_EligibilitySummary[Action ID],tbl_FS_EligibilitySummary[Exposure Eligibility],"")="Eligible",_xlfn.XLOOKUP(_xlfn.XLOOKUP(tbl_Summary_Numerical[[#This Row],[ActionID]],tbl_FS_Assessment[ActionID],tbl_FS_Assessment[Effectiveness on Exposure],""),'Summary Matrix'!$B$61:$B$64,'Summary Matrix'!$C$61:$C$64,""),""),"") | H72: =IFERROR(IF(_xlfn.XLOOKUP(tbl_Summary_Numerical[[#This Row],[ActionID]],tbl_ES_EligibilitySummary[Action ID],tbl_ES_EligibilitySummary[Vulnerability Eligibility],"")="Eligible",_xlfn.XLOOKUP(_xlfn.XLOOKUP(tbl_Summary_Numerical[[#This Row],[ActionID]],tbl_ES_Assessment[ActionID],tbl_ES_Assessment[Effectiveness on Vulnerability],""),'Summary Matrix'!$B$61:$B$64,'Summary Matrix'!$C$61:$C$64,""),""),"") | I72: =IFERROR(IF(_xlfn.XLOOKUP(tbl_Summary_Numerical[[#This Row],[ActionID]],tbl_ES_EligibilitySummary[Action ID],tbl_ES_EligibilitySummary[Exposure Eligibility],"")="Eligible",_xlfn.XLOOKUP(_xlfn.XLOOKUP(tbl_Summary_Numerical[[#This Row],[ActionID]],tbl_ES_Assessment[ActionID],tbl_ES_Assessment[Effectiveness on Exposure],""),'Summary Matrix'!$B$61:$B$64,'Summary Matrix'!$C$61:$C$64,""),""),"") | J72: =IFERROR(IF(_xlfn.XLOOKUP(tbl_Summary_Numerical[[#This Row],[ActionID]],tbl_H_EligibilitySummary[Action ID],tbl_H_EligibilitySummary[Vulnerability Eligibility],"")="Eligible",_xlfn.XLOOKUP(_xlfn.XLOOKUP(tbl_Summary_Numerical[[#This Row],[ActionID]],tbl_H_Assessment[ActionID],tbl_H_Assessment[Effectiveness on Vulnerability],""),'Summary Matrix'!$B$61:$B$64,'Summary Matrix'!$C$61:$C$64,""),""),"") | K72: =IFERROR(IF(_xlfn.XLOOKUP(tbl_Summary_Numerical[[#This Row],[ActionID]],tbl_H_EligibilitySummary[Action ID],tbl_H_EligibilitySummary[Exposure Eligibility],"")="Eligible",_xlfn.XLOOKUP(_xlfn.XLOOKUP(tbl_Summary_Numerical[[#This Row],[ActionID]],tbl_H_Assessment[ActionID],tbl_H_Assessment[Effectiveness on Exposure],""),'Summary Matrix'!$B$61:$B$64,'Summary Matrix'!$C$61:$C$64,""),""),"") | L72: =IFERROR(IF(_xlfn.XLOOKUP(tbl_Summary_Numerical[[#This Row],[ActionID]],tbl_GS_EligibilitySummary[Action ID],tbl_GS_EligibilitySummary[Vulnerability Eligibility],"")="Eligible",_xlfn.XLOOKUP(_xlfn.XLOOKUP(tbl_Summary_Numerical[[#This Row],[ActionID]],tbl_GS_Assessment[ActionID],tbl_GS_Assessment[Effectiveness on Vulnerability],""),'Summary Matrix'!$B$61:$B$64,'Summary Matrix'!$C$61:$C$64,""),""),"") | M72: =IFERROR(IF(_xlfn.XLOOKUP(tbl_Summary_Numerical[[#This Row],[ActionID]],tbl_GS_EligibilitySummary[Action ID],tbl_GS_EligibilitySummary[Exposure Eligibility],"")="Eligible",_xlfn.XLOOKUP(_xlfn.XLOOKUP(tbl_Summary_Numerical[[#This Row],[ActionID]],tbl_GS_Assessment[ActionID],tbl_GS_Assessment[Effectiveness on Exposure],""),'Summary Matrix'!$B$61:$B$64,'Summary Matrix'!$C$61:$C$64,""),""),"") | N72: =IFERROR(IF(_xlfn.XLOOKUP(tbl_Summary_Numerical[[#This Row],[ActionID]],tbl_B_EligibilitySummary[Action ID],tbl_B_EligibilitySummary[Vulnerability Eligibility],"")="Eligible",_xlfn.XLOOKUP(_xlfn.XLOOKUP(tbl_Summary_Numerical[[#This Row],[ActionID]],tbl_B_Assessment[ActionID],tbl_B_Assessment[Effectiveness on Vulnerability],""),'Summary Matrix'!$B$61:$B$64,'Summary Matrix'!$C$61:$C$64,""),""),"") | O72: =IFERROR(IF(_xlfn.XLOOKUP(tbl_Summary_Numerical[[#This Row],[ActionID]],tbl_B_EligibilitySummary[Action ID],tbl_B_EligibilitySummary[Exposure Eligibility],"")="Eligible",_xlfn.XLOOKUP(_xlfn.XLOOKUP(tbl_Summary_Numerical[[#This Row],[ActionID]],tbl_B_Assessment[ActionID],tbl_B_Assessment[Effectiveness on Exposure],""),'Summary Matrix'!$B$61:$B$64,'Summary Matrix'!$C$61:$C$64,""),""),"")
B73: c40_0052 | C73: Deploy cool pavements and cool roofs on heat‑exposed streets and buildings | D73: =IFERROR(IF(_xlfn.XLOOKUP(tbl_Summary_Numerical[[#This Row],[ActionID]],tbl_WR_EligibilitySummary[Action ID],tbl_WR_EligibilitySummary[Vulnerability Eligibility],"")="Eligible",_xlfn.XLOOKUP(_xlfn.XLOOKUP(tbl_Summary_Numerical[[#This Row],[ActionID]],tbl_WR_Assessment[ActionID],tbl_WR_Assessment[Effectiveness on Vulnerability],""),'Summary Matrix'!$B$61:$B$64,'Summary Matrix'!$C$61:$C$64,""),""),"") | E73: =IFERROR(IF(_xlfn.XLOOKUP(tbl_Summary_Numerical[[#This Row],[ActionID]],tbl_WR_EligibilitySummary[Action ID],tbl_WR_EligibilitySummary[Exposure Eligibility],"")="Eligible",_xlfn.XLOOKUP(_xlfn.XLOOKUP(tbl_Summary_Numerical[[#This Row],[ActionID]],tbl_WR_Assessment[ActionID],tbl_WR_Assessment[Effectiveness on Exposure],""),'Summary Matrix'!$B$61:$B$64,'Summary Matrix'!$C$61:$C$64,""),""),"") | F73: =IFERROR(IF(_xlfn.XLOOKUP(tbl_Summary_Numerical[[#This Row],[ActionID]],tbl_FS_EligibilitySummary[Action ID],tbl_FS_EligibilitySummary[Vulnerability Eligibility],"")="Eligible",_xlfn.XLOOKUP(_xlfn.XLOOKUP(tbl_Summary_Numerical[[#This Row],[ActionID]],tbl_FS_Assessment[ActionID],tbl_FS_Assessment[Effectiveness on Vulnerability],""),'Summary Matrix'!$B$61:$B$64,'Summary Matrix'!$C$61:$C$64,""),""),"") | G73: =IFERROR(IF(_xlfn.XLOOKUP(tbl_Summary_Numerical[[#This Row],[ActionID]],tbl_FS_EligibilitySummary[Action ID],tbl_FS_EligibilitySummary[Exposure Eligibility],"")="Eligible",_xlfn.XLOOKUP(_xlfn.XLOOKUP(tbl_Summary_Numerical[[#This Row],[ActionID]],tbl_FS_Assessment[ActionID],tbl_FS_Assessment[Effectiveness on Exposure],""),'Summary Matrix'!$B$61:$B$64,'Summary Matrix'!$C$61:$C$64,""),""),"") | H73: =IFERROR(IF(_xlfn.XLOOKUP(tbl_Summary_Numerical[[#This Row],[ActionID]],tbl_ES_EligibilitySummary[Action ID],tbl_ES_EligibilitySummary[Vulnerability Eligibility],"")="Eligible",_xlfn.XLOOKUP(_xlfn.XLOOKUP(tbl_Summary_Numerical[[#This Row],[ActionID]],tbl_ES_Assessment[ActionID],tbl_ES_Assessment[Effectiveness on Vulnerability],""),'Summary Matrix'!$B$61:$B$64,'Summary Matrix'!$C$61:$C$64,""),""),"") | I73: =IFERROR(IF(_xlfn.XLOOKUP(tbl_Summary_Numerical[[#This Row],[ActionID]],tbl_ES_EligibilitySummary[Action ID],tbl_ES_EligibilitySummary[Exposure Eligibility],"")="Eligible",_xlfn.XLOOKUP(_xlfn.XLOOKUP(tbl_Summary_Numerical[[#This Row],[ActionID]],tbl_ES_Assessment[ActionID],tbl_ES_Assessment[Effectiveness on Exposure],""),'Summary Matrix'!$B$61:$B$64,'Summary Matrix'!$C$61:$C$64,""),""),"") | J73: =IFERROR(IF(_xlfn.XLOOKUP(tbl_Summary_Numerical[[#This Row],[ActionID]],tbl_H_EligibilitySummary[Action ID],tbl_H_EligibilitySummary[Vulnerability Eligibility],"")="Eligible",_xlfn.XLOOKUP(_xlfn.XLOOKUP(tbl_Summary_Numerical[[#This Row],[ActionID]],tbl_H_Assessment[ActionID],tbl_H_Assessment[Effectiveness on Vulnerability],""),'Summary Matrix'!$B$61:$B$64,'Summary Matrix'!$C$61:$C$64,""),""),"") | K73: =IFERROR(IF(_xlfn.XLOOKUP(tbl_Summary_Numerical[[#This Row],[ActionID]],tbl_H_EligibilitySummary[Action ID],tbl_H_EligibilitySummary[Exposure Eligibility],"")="Eligible",_xlfn.XLOOKUP(_xlfn.XLOOKUP(tbl_Summary_Numerical[[#This Row],[ActionID]],tbl_H_Assessment[ActionID],tbl_H_Assessment[Effectiveness on Exposure],""),'Summary Matrix'!$B$61:$B$64,'Summary Matrix'!$C$61:$C$64,""),""),"") | L73: =IFERROR(IF(_xlfn.XLOOKUP(tbl_Summary_Numerical[[#This Row],[ActionID]],tbl_GS_EligibilitySummary[Action ID],tbl_GS_EligibilitySummary[Vulnerability Eligibility],"")="Eligible",_xlfn.XLOOKUP(_xlfn.XLOOKUP(tbl_Summary_Numerical[[#This Row],[ActionID]],tbl_GS_Assessment[ActionID],tbl_GS_Assessment[Effectiveness on Vulnerability],""),'Summary Matrix'!$B$61:$B$64,'Summary Matrix'!$C$61:$C$64,""),""),"") | M73: =IFERROR(IF(_xlfn.XLOOKUP(tbl_Summary_Numerical[[#This Row],[ActionID]],tbl_GS_EligibilitySummary[Action ID],tbl_GS_EligibilitySummary[Exposure Eligibility],"")="Eligible",_xlfn.XLOOKUP(_xlfn.XLOOKUP(tbl_Summary_Numerical[[#This Row],[ActionID]],tbl_GS_Assessment[ActionID],tbl_GS_Assessment[Effectiveness on Exposure],""),'Summary Matrix'!$B$61:$B$64,'Summary Matrix'!$C$61:$C$64,""),""),"") | N73: =IFERROR(IF(_xlfn.XLOOKUP(tbl_Summary_Numerical[[#This Row],[ActionID]],tbl_B_EligibilitySummary[Action ID],tbl_B_EligibilitySummary[Vulnerability Eligibility],"")="Eligible",_xlfn.XLOOKUP(_xlfn.XLOOKUP(tbl_Summary_Numerical[[#This Row],[ActionID]],tbl_B_Assessment[ActionID],tbl_B_Assessment[Effectiveness on Vulnerability],""),'Summary Matrix'!$B$61:$B$64,'Summary Matrix'!$C$61:$C$64,""),""),"") | O73: =IFERROR(IF(_xlfn.XLOOKUP(tbl_Summary_Numerical[[#This Row],[ActionID]],tbl_B_EligibilitySummary[Action ID],tbl_B_EligibilitySummary[Exposure Eligibility],"")="Eligible",_xlfn.XLOOKUP(_xlfn.XLOOKUP(tbl_Summary_Numerical[[#This Row],[ActionID]],tbl_B_Assessment[ActionID],tbl_B_Assessment[Effectiveness on Exposure],""),'Summary Matrix'!$B$61:$B$64,'Summary Matrix'!$C$61:$C$64,""),""),"")
B74: c40_0053 | C74: Promote water-saving technologies and practices | D74: =IFERROR(IF(_xlfn.XLOOKUP(tbl_Summary_Numerical[[#This Row],[ActionID]],tbl_WR_EligibilitySummary[Action ID],tbl_WR_EligibilitySummary[Vulnerability Eligibility],"")="Eligible",_xlfn.XLOOKUP(_xlfn.XLOOKUP(tbl_Summary_Numerical[[#This Row],[ActionID]],tbl_WR_Assessment[ActionID],tbl_WR_Assessment[Effectiveness on Vulnerability],""),'Summary Matrix'!$B$61:$B$64,'Summary Matrix'!$C$61:$C$64,""),""),"") -> -0.5 | E74: =IFERROR(IF(_xlfn.XLOOKUP(tbl_Summary_Numerical[[#This Row],[ActionID]],tbl_WR_EligibilitySummary[Action ID],tbl_WR_EligibilitySummary[Exposure Eligibility],"")="Eligible",_xlfn.XLOOKUP(_xlfn.XLOOKUP(tbl_Summary_Numerical[[#This Row],[ActionID]],tbl_WR_Assessment[ActionID],tbl_WR_Assessment[Effectiveness on Exposure],""),'Summary Matrix'!$B$61:$B$64,'Summary Matrix'!$C$61:$C$64,""),""),"") | F74: =IFERROR(IF(_xlfn.XLOOKUP(tbl_Summary_Numerical[[#This Row],[ActionID]],tbl_FS_EligibilitySummary[Action ID],tbl_FS_EligibilitySummary[Vulnerability Eligibility],"")="Eligible",_xlfn.XLOOKUP(_xlfn.XLOOKUP(tbl_Summary_Numerical[[#This Row],[ActionID]],tbl_FS_Assessment[ActionID],tbl_FS_Assessment[Effectiveness on Vulnerability],""),'Summary Matrix'!$B$61:$B$64,'Summary Matrix'!$C$61:$C$64,""),""),"") | G74: =IFERROR(IF(_xlfn.XLOOKUP(tbl_Summary_Numerical[[#This Row],[ActionID]],tbl_FS_EligibilitySummary[Action ID],tbl_FS_EligibilitySummary[Exposure Eligibility],"")="Eligible",_xlfn.XLOOKUP(_xlfn.XLOOKUP(tbl_Summary_Numerical[[#This Row],[ActionID]],tbl_FS_Assessment[ActionID],tbl_FS_Assessment[Effectiveness on Exposure],""),'Summary Matrix'!$B$61:$B$64,'Summary Matrix'!$C$61:$C$64,""),""),"") | H74: =IFERROR(IF(_xlfn.XLOOKUP(tbl_Summary_Numerical[[#This Row],[ActionID]],tbl_ES_EligibilitySummary[Action ID],tbl_ES_EligibilitySummary[Vulnerability Eligibility],"")="Eligible",_xlfn.XLOOKUP(_xlfn.XLOOKUP(tbl_Summary_Numerical[[#This Row],[ActionID]],tbl_ES_Assessment[ActionID],tbl_ES_Assessment[Effectiveness on Vulnerability],""),'Summary Matrix'!$B$61:$B$64,'Summary Matrix'!$C$61:$C$64,""),""),"") | I74: =IFERROR(IF(_xlfn.XLOOKUP(tbl_Summary_Numerical[[#This Row],[ActionID]],tbl_ES_EligibilitySummary[Action ID],tbl_ES_EligibilitySummary[Exposure Eligibility],"")="Eligible",_xlfn.XLOOKUP(_xlfn.XLOOKUP(tbl_Summary_Numerical[[#This Row],[ActionID]],tbl_ES_Assessment[ActionID],tbl_ES_Assessment[Effectiveness on Exposure],""),'Summary Matrix'!$B$61:$B$64,'Summary Matrix'!$C$61:$C$64,""),""),"") | J74: =IFERROR(IF(_xlfn.XLOOKUP(tbl_Summary_Numerical[[#This Row],[ActionID]],tbl_H_EligibilitySummary[Action ID],tbl_H_EligibilitySummary[Vulnerability Eligibility],"")="Eligible",_xlfn.XLOOKUP(_xlfn.XLOOKUP(tbl_Summary_Numerical[[#This Row],[ActionID]],tbl_H_Assessment[ActionID],tbl_H_Assessment[Effectiveness on Vulnerability],""),'Summary Matrix'!$B$61:$B$64,'Summary Matrix'!$C$61:$C$64,""),""),"") | K74: =IFERROR(IF(_xlfn.XLOOKUP(tbl_Summary_Numerical[[#This Row],[ActionID]],tbl_H_EligibilitySummary[Action ID],tbl_H_EligibilitySummary[Exposure Eligibility],"")="Eligible",_xlfn.XLOOKUP(_xlfn.XLOOKUP(tbl_Summary_Numerical[[#This Row],[ActionID]],tbl_H_Assessment[ActionID],tbl_H_Assessment[Effectiveness on Exposure],""),'Summary Matrix'!$B$61:$B$64,'Summary Matrix'!$C$61:$C$64,""),""),"") | L74: =IFERROR(IF(_xlfn.XLOOKUP(tbl_Summary_Numerical[[#This Row],[ActionID]],tbl_GS_EligibilitySummary[Action ID],tbl_GS_EligibilitySummary[Vulnerability Eligibility],"")="Eligible",_xlfn.XLOOKUP(_xlfn.XLOOKUP(tbl_Summary_Numerical[[#This Row],[ActionID]],tbl_GS_Assessment[ActionID],tbl_GS_Assessment[Effectiveness on Vulnerability],""),'Summary Matrix'!$B$61:$B$64,'Summary Matrix'!$C$61:$C$64,""),""),"") | M74: =IFERROR(IF(_xlfn.XLOOKUP(tbl_Summary_Numerical[[#This Row],[ActionID]],tbl_GS_EligibilitySummary[Action ID],tbl_GS_EligibilitySummary[Exposure Eligibility],"")="Eligible",_xlfn.XLOOKUP(_xlfn.XLOOKUP(tbl_Summary_Numerical[[#This Row],[ActionID]],tbl_GS_Assessment[ActionID],tbl_GS_Assessment[Effectiveness on Exposure],""),'Summary Matrix'!$B$61:$B$64,'Summary Matrix'!$C$61:$C$64,""),""),"") | N74: =IFERROR(IF(_xlfn.XLOOKUP(tbl_Summary_Numerical[[#This Row],[ActionID]],tbl_B_EligibilitySummary[Action ID],tbl_B_EligibilitySummary[Vulnerability Eligibility],"")="Eligible",_xlfn.XLOOKUP(_xlfn.XLOOKUP(tbl_Summary_Numerical[[#This Row],[ActionID]],tbl_B_Assessment[ActionID],tbl_B_Assessment[Effectiveness on Vulnerability],""),'Summary Matrix'!$B$61:$B$64,'Summary Matrix'!$C$61:$C$64,""),""),"") | O74: =IFERROR(IF(_xlfn.XLOOKUP(tbl_Summary_Numerical[[#This Row],[ActionID]],tbl_B_EligibilitySummary[Action ID],tbl_B_EligibilitySummary[Exposure Eligibility],"")="Eligible",_xlfn.XLOOKUP(_xlfn.XLOOKUP(tbl_Summary_Numerical[[#This Row],[ActionID]],tbl_B_Assessment[ActionID],tbl_B_Assessment[Effectiveness on Exposure],""),'Summary Matrix'!$B$61:$B$64,'Summary Matrix'!$C$61:$C$64,""),""),"")
B75: c40_0056 | C75: Improve Watershed Protection and Management | D75: =IFERROR(IF(_xlfn.XLOOKUP(tbl_Summary_Numerical[[#This Row],[ActionID]],tbl_WR_EligibilitySummary[Action ID],tbl_WR_EligibilitySummary[Vulnerability Eligibility],"")="Eligible",_xlfn.XLOOKUP(_xlfn.XLOOKUP(tbl_Summary_Numerical[[#This Row],[ActionID]],tbl_WR_Assessment[ActionID],tbl_WR_Assessment[Effectiveness on Vulnerability],""),'Summary Matrix'!$B$61:$B$64,'Summary Matrix'!$C$61:$C$64,""),""),"") -> -1 | E75: =IFERROR(IF(_xlfn.XLOOKUP(tbl_Summary_Numerical[[#This Row],[ActionID]],tbl_WR_EligibilitySummary[Action ID],tbl_WR_EligibilitySummary[Exposure Eligibility],"")="Eligible",_xlfn.XLOOKUP(_xlfn.XLOOKUP(tbl_Summary_Numerical[[#This Row],[ActionID]],tbl_WR_Assessment[ActionID],tbl_WR_Assessment[Effectiveness on Exposure],""),'Summary Matrix'!$B$61:$B$64,'Summary Matrix'!$C$61:$C$64,""),""),"") | F75: =IFERROR(IF(_xlfn.XLOOKUP(tbl_Summary_Numerical[[#This Row],[ActionID]],tbl_FS_EligibilitySummary[Action ID],tbl_FS_EligibilitySummary[Vulnerability Eligibility],"")="Eligible",_xlfn.XLOOKUP(_xlfn.XLOOKUP(tbl_Summary_Numerical[[#This Row],[ActionID]],tbl_FS_Assessment[ActionID],tbl_FS_Assessment[Effectiveness on Vulnerability],""),'Summary Matrix'!$B$61:$B$64,'Summary Matrix'!$C$61:$C$64,""),""),"") | G75: =IFERROR(IF(_xlfn.XLOOKUP(tbl_Summary_Numerical[[#This Row],[ActionID]],tbl_FS_EligibilitySummary[Action ID],tbl_FS_EligibilitySummary[Exposure Eligibility],"")="Eligible",_xlfn.XLOOKUP(_xlfn.XLOOKUP(tbl_Summary_Numerical[[#This Row],[ActionID]],tbl_FS_Assessment[ActionID],tbl_FS_Assessment[Effectiveness on Exposure],""),'Summary Matrix'!$B$61:$B$64,'Summary Matrix'!$C$61:$C$64,""),""),"") | H75: =IFERROR(IF(_xlfn.XLOOKUP(tbl_Summary_Numerical[[#This Row],[ActionID]],tbl_ES_EligibilitySummary[Action ID],tbl_ES_EligibilitySummary[Vulnerability Eligibility],"")="Eligible",_xlfn.XLOOKUP(_xlfn.XLOOKUP(tbl_Summary_Numerical[[#This Row],[ActionID]],tbl_ES_Assessment[ActionID],tbl_ES_Assessment[Effectiveness on Vulnerability],""),'Summary Matrix'!$B$61:$B$64,'Summary Matrix'!$C$61:$C$64,""),""),"") | I75: =IFERROR(IF(_xlfn.XLOOKUP(tbl_Summary_Numerical[[#This Row],[ActionID]],tbl_ES_EligibilitySummary[Action ID],tbl_ES_EligibilitySummary[Exposure Eligibility],"")="Eligible",_xlfn.XLOOKUP(_xlfn.XLOOKUP(tbl_Summary_Numerical[[#This Row],[ActionID]],tbl_ES_Assessment[ActionID],tbl_ES_Assessment[Effectiveness on Exposure],""),'Summary Matrix'!$B$61:$B$64,'Summary Matrix'!$C$61:$C$64,""),""),"") | J75: =IFERROR(IF(_xlfn.XLOOKUP(tbl_Summary_Numerical[[#This Row],[ActionID]],tbl_H_EligibilitySummary[Action ID],tbl_H_EligibilitySummary[Vulnerability Eligibility],"")="Eligible",_xlfn.XLOOKUP(_xlfn.XLOOKUP(tbl_Summary_Numerical[[#This Row],[ActionID]],tbl_H_Assessment[ActionID],tbl_H_Assessment[Effectiveness on Vulnerability],""),'Summary Matrix'!$B$61:$B$64,'Summary Matrix'!$C$61:$C$64,""),""),"") | K75: =IFERROR(IF(_xlfn.XLOOKUP(tbl_Summary_Numerical[[#This Row],[ActionID]],tbl_H_EligibilitySummary[Action ID],tbl_H_EligibilitySummary[Exposure Eligibility],"")="Eligible",_xlfn.XLOOKUP(_xlfn.XLOOKUP(tbl_Summary_Numerical[[#This Row],[ActionID]],tbl_H_Assessment[ActionID],tbl_H_Assessment[Effectiveness on Exposure],""),'Summary Matrix'!$B$61:$B$64,'Summary Matrix'!$C$61:$C$64,""),""),"") | L75: =IFERROR(IF(_xlfn.XLOOKUP(tbl_Summary_Numerical[[#This Row],[ActionID]],tbl_GS_EligibilitySummary[Action ID],tbl_GS_EligibilitySummary[Vulnerability Eligibility],"")="Eligible",_xlfn.XLOOKUP(_xlfn.XLOOKUP(tbl_Summary_Numerical[[#This Row],[ActionID]],tbl_GS_Assessment[ActionID],tbl_GS_Assessment[Effectiveness on Vulnerability],""),'Summary Matrix'!$B$61:$B$64,'Summary Matrix'!$C$61:$C$64,""),""),"") | M75: =IFERROR(IF(_xlfn.XLOOKUP(tbl_Summary_Numerical[[#This Row],[ActionID]],tbl_GS_EligibilitySummary[Action ID],tbl_GS_EligibilitySummary[Exposure Eligibility],"")="Eligible",_xlfn.XLOOKUP(_xlfn.XLOOKUP(tbl_Summary_Numerical[[#This Row],[ActionID]],tbl_GS_Assessment[ActionID],tbl_GS_Assessment[Effectiveness on Exposure],""),'Summary Matrix'!$B$61:$B$64,'Summary Matrix'!$C$61:$C$64,""),""),"") | N75: =IFERROR(IF(_xlfn.XLOOKUP(tbl_Summary_Numerical[[#This Row],[ActionID]],tbl_B_EligibilitySummary[Action ID],tbl_B_EligibilitySummary[Vulnerability Eligibility],"")="Eligible",_xlfn.XLOOKUP(_xlfn.XLOOKUP(tbl_Summary_Numerical[[#This Row],[ActionID]],tbl_B_Assessment[ActionID],tbl_B_Assessment[Effectiveness on Vulnerability],""),'Summary Matrix'!$B$61:$B$64,'Summary Matrix'!$C$61:$C$64,""),""),"") | O75: =IFERROR(IF(_xlfn.XLOOKUP(tbl_Summary_Numerical[[#This Row],[ActionID]],tbl_B_EligibilitySummary[Action ID],tbl_B_EligibilitySummary[Exposure Eligibility],"")="Eligible",_xlfn.XLOOKUP(_xlfn.XLOOKUP(tbl_Summary_Numerical[[#This Row],[ActionID]],tbl_B_Assessment[ActionID],tbl_B_Assessment[Effectiveness on Exposure],""),'Summary Matrix'!$B$61:$B$64,'Summary Matrix'!$C$61:$C$64,""),""),"")
B76: c40_0062 | C76: Reform water tariffs to support efficiency and equity | D76: =IFERROR(IF(_xlfn.XLOOKUP(tbl_Summary_Numerical[[#This Row],[ActionID]],tbl_WR_EligibilitySummary[Action ID],tbl_WR_EligibilitySummary[Vulnerability Eligibility],"")="Eligible",_xlfn.XLOOKUP(_xlfn.XLOOKUP(tbl_Summary_Numerical[[#This Row],[ActionID]],tbl_WR_Assessment[ActionID],tbl_WR_Assessment[Effectiveness on Vulnerability],""),'Summary Matrix'!$B$61:$B$64,'Summary Matrix'!$C$61:$C$64,""),""),"") -> -0.5 | E76: =IFERROR(IF(_xlfn.XLOOKUP(tbl_Summary_Numerical[[#This Row],[ActionID]],tbl_WR_EligibilitySummary[Action ID],tbl_WR_EligibilitySummary[Exposure Eligibility],"")="Eligible",_xlfn.XLOOKUP(_xlfn.XLOOKUP(tbl_Summary_Numerical[[#This Row],[ActionID]],tbl_WR_Assessment[ActionID],tbl_WR_Assessment[Effectiveness on Exposure],""),'Summary Matrix'!$B$61:$B$64,'Summary Matrix'!$C$61:$C$64,""),""),"") | F76: =IFERROR(IF(_xlfn.XLOOKUP(tbl_Summary_Numerical[[#This Row],[ActionID]],tbl_FS_EligibilitySummary[Action ID],tbl_FS_EligibilitySummary[Vulnerability Eligibility],"")="Eligible",_xlfn.XLOOKUP(_xlfn.XLOOKUP(tbl_Summary_Numerical[[#This Row],[ActionID]],tbl_FS_Assessment[ActionID],tbl_FS_Assessment[Effectiveness on Vulnerability],""),'Summary Matrix'!$B$61:$B$64,'Summary Matrix'!$C$61:$C$64,""),""),"") | G76: =IFERROR(IF(_xlfn.XLOOKUP(tbl_Summary_Numerical[[#This Row],[ActionID]],tbl_FS_EligibilitySummary[Action ID],tbl_FS_EligibilitySummary[Exposure Eligibility],"")="Eligible",_xlfn.XLOOKUP(_xlfn.XLOOKUP(tbl_Summary_Numerical[[#This Row],[ActionID]],tbl_FS_Assessment[ActionID],tbl_FS_Assessment[Effectiveness on Exposure],""),'Summary Matrix'!$B$61:$B$64,'Summary Matrix'!$C$61:$C$64,""),""),"") | H76: =IFERROR(IF(_xlfn.XLOOKUP(tbl_Summary_Numerical[[#This Row],[ActionID]],tbl_ES_EligibilitySummary[Action ID],tbl_ES_EligibilitySummary[Vulnerability Eligibility],"")="Eligible",_xlfn.XLOOKUP(_xlfn.XLOOKUP(tbl_Summary_Numerical[[#This Row],[ActionID]],tbl_ES_Assessment[ActionID],tbl_ES_Assessment[Effectiveness on Vulnerability],""),'Summary Matrix'!$B$61:$B$64,'Summary Matrix'!$C$61:$C$64,""),""),"") | I76: =IFERROR(IF(_xlfn.XLOOKUP(tbl_Summary_Numerical[[#This Row],[ActionID]],tbl_ES_EligibilitySummary[Action ID],tbl_ES_EligibilitySummary[Exposure Eligibility],"")="Eligible",_xlfn.XLOOKUP(_xlfn.XLOOKUP(tbl_Summary_Numerical[[#This Row],[ActionID]],tbl_ES_Assessment[ActionID],tbl_ES_Assessment[Effectiveness on Exposure],""),'Summary Matrix'!$B$61:$B$64,'Summary Matrix'!$C$61:$C$64,""),""),"") | J76: =IFERROR(IF(_xlfn.XLOOKUP(tbl_Summary_Numerical[[#This Row],[ActionID]],tbl_H_EligibilitySummary[Action ID],tbl_H_EligibilitySummary[Vulnerability Eligibility],"")="Eligible",_xlfn.XLOOKUP(_xlfn.XLOOKUP(tbl_Summary_Numerical[[#This Row],[ActionID]],tbl_H_Assessment[ActionID],tbl_H_Assessment[Effectiveness on Vulnerability],""),'Summary Matrix'!$B$61:$B$64,'Summary Matrix'!$C$61:$C$64,""),""),"") | K76: =IFERROR(IF(_xlfn.XLOOKUP(tbl_Summary_Numerical[[#This Row],[ActionID]],tbl_H_EligibilitySummary[Action ID],tbl_H_EligibilitySummary[Exposure Eligibility],"")="Eligible",_xlfn.XLOOKUP(_xlfn.XLOOKUP(tbl_Summary_Numerical[[#This Row],[ActionID]],tbl_H_Assessment[ActionID],tbl_H_Assessment[Effectiveness on Exposure],""),'Summary Matrix'!$B$61:$B$64,'Summary Matrix'!$C$61:$C$64,""),""),"") | L76: =IFERROR(IF(_xlfn.XLOOKUP(tbl_Summary_Numerical[[#This Row],[ActionID]],tbl_GS_EligibilitySummary[Action ID],tbl_GS_EligibilitySummary[Vulnerability Eligibility],"")="Eligible",_xlfn.XLOOKUP(_xlfn.XLOOKUP(tbl_Summary_Numerical[[#This Row],[ActionID]],tbl_GS_Assessment[ActionID],tbl_GS_Assessment[Effectiveness on Vulnerability],""),'Summary Matrix'!$B$61:$B$64,'Summary Matrix'!$C$61:$C$64,""),""),"") | M76: =IFERROR(IF(_xlfn.XLOOKUP(tbl_Summary_Numerical[[#This Row],[ActionID]],tbl_GS_EligibilitySummary[Action ID],tbl_GS_EligibilitySummary[Exposure Eligibility],"")="Eligible",_xlfn.XLOOKUP(_xlfn.XLOOKUP(tbl_Summary_Numerical[[#This Row],[ActionID]],tbl_GS_Assessment[ActionID],tbl_GS_Assessment[Effectiveness on Exposure],""),'Summary Matrix'!$B$61:$B$64,'Summary Matrix'!$C$61:$C$64,""),""),"") | N76: =IFERROR(IF(_xlfn.XLOOKUP(tbl_Summary_Numerical[[#This Row],[ActionID]],tbl_B_EligibilitySummary[Action ID],tbl_B_EligibilitySummary[Vulnerability Eligibility],"")="Eligible",_xlfn.XLOOKUP(_xlfn.XLOOKUP(tbl_Summary_Numerical[[#This Row],[ActionID]],tbl_B_Assessment[ActionID],tbl_B_Assessment[Effectiveness on Vulnerability],""),'Summary Matrix'!$B$61:$B$64,'Summary Matrix'!$C$61:$C$64,""),""),"") | O76: =IFERROR(IF(_xlfn.XLOOKUP(tbl_Summary_Numerical[[#This Row],[ActionID]],tbl_B_EligibilitySummary[Action ID],tbl_B_EligibilitySummary[Exposure Eligibility],"")="Eligible",_xlfn.XLOOKUP(_xlfn.XLOOKUP(tbl_Summary_Numerical[[#This Row],[ActionID]],tbl_B_Assessment[ActionID],tbl_B_Assessment[Effectiveness on Exposure],""),'Summary Matrix'!$B$61:$B$64,'Summary Matrix'!$C$61:$C$64,""),""),"")
B77: icare_0144 | C77: Establish a financial support program for extreme weather events | D77: =IFERROR(IF(_xlfn.XLOOKUP(tbl_Summary_Numerical[[#This Row],[ActionID]],tbl_WR_EligibilitySummary[Action ID],tbl_WR_EligibilitySummary[Vulnerability Eligibility],"")="Eligible",_xlfn.XLOOKUP(_xlfn.XLOOKUP(tbl_Summary_Numerical[[#This Row],[ActionID]],tbl_WR_Assessment[ActionID],tbl_WR_Assessment[Effectiveness on Vulnerability],""),'Summary Matrix'!$B$61:$B$64,'Summary Matrix'!$C$61:$C$64,""),""),"") | E77: =IFERROR(IF(_xlfn.XLOOKUP(tbl_Summary_Numerical[[#This Row],[ActionID]],tbl_WR_EligibilitySummary[Action ID],tbl_WR_EligibilitySummary[Exposure Eligibility],"")="Eligible",_xlfn.XLOOKUP(_xlfn.XLOOKUP(tbl_Summary_Numerical[[#This Row],[ActionID]],tbl_WR_Assessment[ActionID],tbl_WR_Assessment[Effectiveness on Exposure],""),'Summary Matrix'!$B$61:$B$64,'Summary Matrix'!$C$61:$C$64,""),""),"") | F77: =IFERROR(IF(_xlfn.XLOOKUP(tbl_Summary_Numerical[[#This Row],[ActionID]],tbl_FS_EligibilitySummary[Action ID],tbl_FS_EligibilitySummary[Vulnerability Eligibility],"")="Eligible",_xlfn.XLOOKUP(_xlfn.XLOOKUP(tbl_Summary_Numerical[[#This Row],[ActionID]],tbl_FS_Assessment[ActionID],tbl_FS_Assessment[Effectiveness on Vulnerability],""),'Summary Matrix'!$B$61:$B$64,'Summary Matrix'!$C$61:$C$64,""),""),"") | G77: =IFERROR(IF(_xlfn.XLOOKUP(tbl_Summary_Numerical[[#This Row],[ActionID]],tbl_FS_EligibilitySummary[Action ID],tbl_FS_EligibilitySummary[Exposure Eligibility],"")="Eligible",_xlfn.XLOOKUP(_xlfn.XLOOKUP(tbl_Summary_Numerical[[#This Row],[ActionID]],tbl_FS_Assessment[ActionID],tbl_FS_Assessment[Effectiveness on Exposure],""),'Summary Matrix'!$B$61:$B$64,'Summary Matrix'!$C$61:$C$64,""),""),"") | H77: =IFERROR(IF(_xlfn.XLOOKUP(tbl_Summary_Numerical[[#This Row],[ActionID]],tbl_ES_EligibilitySummary[Action ID],tbl_ES_EligibilitySummary[Vulnerability Eligibility],"")="Eligible",_xlfn.XLOOKUP(_xlfn.XLOOKUP(tbl_Summary_Numerical[[#This Row],[ActionID]],tbl_ES_Assessment[ActionID],tbl_ES_Assessment[Effectiveness on Vulnerability],""),'Summary Matrix'!$B$61:$B$64,'Summary Matrix'!$C$61:$C$64,""),""),"") | I77: =IFERROR(IF(_xlfn.XLOOKUP(tbl_Summary_Numerical[[#This Row],[ActionID]],tbl_ES_EligibilitySummary[Action ID],tbl_ES_EligibilitySummary[Exposure Eligibility],"")="Eligible",_xlfn.XLOOKUP(_xlfn.XLOOKUP(tbl_Summary_Numerical[[#This Row],[ActionID]],tbl_ES_Assessment[ActionID],tbl_ES_Assessment[Effectiveness on Exposure],""),'Summary Matrix'!$B$61:$B$64,'Summary Matrix'!$C$61:$C$64,""),""),"") | J77: =IFERROR(IF(_xlfn.XLOOKUP(tbl_Summary_Numerical[[#This Row],[ActionID]],tbl_H_EligibilitySummary[Action ID],tbl_H_EligibilitySummary[Vulnerability Eligibility],"")="Eligible",_xlfn.XLOOKUP(_xlfn.XLOOKUP(tbl_Summary_Numerical[[#This Row],[ActionID]],tbl_H_Assessment[ActionID],tbl_H_Assessment[Effectiveness on Vulnerability],""),'Summary Matrix'!$B$61:$B$64,'Summary Matrix'!$C$61:$C$64,""),""),"") | K77: =IFERROR(IF(_xlfn.XLOOKUP(tbl_Summary_Numerical[[#This Row],[ActionID]],tbl_H_EligibilitySummary[Action ID],tbl_H_EligibilitySummary[Exposure Eligibility],"")="Eligible",_xlfn.XLOOKUP(_xlfn.XLOOKUP(tbl_Summary_Numerical[[#This Row],[ActionID]],tbl_H_Assessment[ActionID],tbl_H_Assessment[Effectiveness on Exposure],""),'Summary Matrix'!$B$61:$B$64,'Summary Matrix'!$C$61:$C$64,""),""),"") | L77: =IFERROR(IF(_xlfn.XLOOKUP(tbl_Summary_Numerical[[#This Row],[ActionID]],tbl_GS_EligibilitySummary[Action ID],tbl_GS_EligibilitySummary[Vulnerability Eligibility],"")="Eligible",_xlfn.XLOOKUP(_xlfn.XLOOKUP(tbl_Summary_Numerical[[#This Row],[ActionID]],tbl_GS_Assessment[ActionID],tbl_GS_Assessment[Effectiveness on Vulnerability],""),'Summary Matrix'!$B$61:$B$64,'Summary Matrix'!$C$61:$C$64,""),""),"") | M77: =IFERROR(IF(_xlfn.XLOOKUP(tbl_Summary_Numerical[[#This Row],[ActionID]],tbl_GS_EligibilitySummary[Action ID],tbl_GS_EligibilitySummary[Exposure Eligibility],"")="Eligible",_xlfn.XLOOKUP(_xlfn.XLOOKUP(tbl_Summary_Numerical[[#This Row],[ActionID]],tbl_GS_Assessment[ActionID],tbl_GS_Assessment[Effectiveness on Exposure],""),'Summary Matrix'!$B$61:$B$64,'Summary Matrix'!$C$61:$C$64,""),""),"") | N77: =IFERROR(IF(_xlfn.XLOOKUP(tbl_Summary_Numerical[[#This Row],[ActionID]],tbl_B_EligibilitySummary[Action ID],tbl_B_EligibilitySummary[Vulnerability Eligibility],"")="Eligible",_xlfn.XLOOKUP(_xlfn.XLOOKUP(tbl_Summary_Numerical[[#This Row],[ActionID]],tbl_B_Assessment[ActionID],tbl_B_Assessment[Effectiveness on Vulnerability],""),'Summary Matrix'!$B$61:$B$64,'Summary Matrix'!$C$61:$C$64,""),""),"") | O77: =IFERROR(IF(_xlfn.XLOOKUP(tbl_Summary_Numerical[[#This Row],[ActionID]],tbl_B_EligibilitySummary[Action ID],tbl_B_EligibilitySummary[Exposure Eligibility],"")="Eligible",_xlfn.XLOOKUP(_xlfn.XLOOKUP(tbl_Summary_Numerical[[#This Row],[ActionID]],tbl_B_Assessment[ActionID],tbl_B_Assessment[Effectiveness on Exposure],""),'Summary Matrix'!$B$61:$B$64,'Summary Matrix'!$C$61:$C$64,""),""),"")
B78: icare_0145 | C78: Strengthen the healthcare system to respond effectively to extreme events | D78: =IFERROR(IF(_xlfn.XLOOKUP(tbl_Summary_Numerical[[#This Row],[ActionID]],tbl_WR_EligibilitySummary[Action ID],tbl_WR_EligibilitySummary[Vulnerability Eligibility],"")="Eligible",_xlfn.XLOOKUP(_xlfn.XLOOKUP(tbl_Summary_Numerical[[#This Row],[ActionID]],tbl_WR_Assessment[ActionID],tbl_WR_Assessment[Effectiveness on Vulnerability],""),'Summary Matrix'!$B$61:$B$64,'Summary Matrix'!$C$61:$C$64,""),""),"") | E78: =IFERROR(IF(_xlfn.XLOOKUP(tbl_Summary_Numerical[[#This Row],[ActionID]],tbl_WR_EligibilitySummary[Action ID],tbl_WR_EligibilitySummary[Exposure Eligibility],"")="Eligible",_xlfn.XLOOKUP(_xlfn.XLOOKUP(tbl_Summary_Numerical[[#This Row],[ActionID]],tbl_WR_Assessment[ActionID],tbl_WR_Assessment[Effectiveness on Exposure],""),'Summary Matrix'!$B$61:$B$64,'Summary Matrix'!$C$61:$C$64,""),""),"") | F78: =IFERROR(IF(_xlfn.XLOOKUP(tbl_Summary_Numerical[[#This Row],[ActionID]],tbl_FS_EligibilitySummary[Action ID],tbl_FS_EligibilitySummary[Vulnerability Eligibility],"")="Eligible",_xlfn.XLOOKUP(_xlfn.XLOOKUP(tbl_Summary_Numerical[[#This Row],[ActionID]],tbl_FS_Assessment[ActionID],tbl_FS_Assessment[Effectiveness on Vulnerability],""),'Summary Matrix'!$B$61:$B$64,'Summary Matrix'!$C$61:$C$64,""),""),"") | G78: =IFERROR(IF(_xlfn.XLOOKUP(tbl_Summary_Numerical[[#This Row],[ActionID]],tbl_FS_EligibilitySummary[Action ID],tbl_FS_EligibilitySummary[Exposure Eligibility],"")="Eligible",_xlfn.XLOOKUP(_xlfn.XLOOKUP(tbl_Summary_Numerical[[#This Row],[ActionID]],tbl_FS_Assessment[ActionID],tbl_FS_Assessment[Effectiveness on Exposure],""),'Summary Matrix'!$B$61:$B$64,'Summary Matrix'!$C$61:$C$64,""),""),"") | H78: =IFERROR(IF(_xlfn.XLOOKUP(tbl_Summary_Numerical[[#This Row],[ActionID]],tbl_ES_EligibilitySummary[Action ID],tbl_ES_EligibilitySummary[Vulnerability Eligibility],"")="Eligible",_xlfn.XLOOKUP(_xlfn.XLOOKUP(tbl_Summary_Numerical[[#This Row],[ActionID]],tbl_ES_Assessment[ActionID],tbl_ES_Assessment[Effectiveness on Vulnerability],""),'Summary Matrix'!$B$61:$B$64,'Summary Matrix'!$C$61:$C$64,""),""),"") | I78: =IFERROR(IF(_xlfn.XLOOKUP(tbl_Summary_Numerical[[#This Row],[ActionID]],tbl_ES_EligibilitySummary[Action ID],tbl_ES_EligibilitySummary[Exposure Eligibility],"")="Eligible",_xlfn.XLOOKUP(_xlfn.XLOOKUP(tbl_Summary_Numerical[[#This Row],[ActionID]],tbl_ES_Assessment[ActionID],tbl_ES_Assessment[Effectiveness on Exposure],""),'Summary Matrix'!$B$61:$B$64,'Summary Matrix'!$C$61:$C$64,""),""),"") | J78: =IFERROR(IF(_xlfn.XLOOKUP(tbl_Summary_Numerical[[#This Row],[ActionID]],tbl_H_EligibilitySummary[Action ID],tbl_H_EligibilitySummary[Vulnerability Eligibility],"")="Eligible",_xlfn.XLOOKUP(_xlfn.XLOOKUP(tbl_Summary_Numerical[[#This Row],[ActionID]],tbl_H_Assessment[ActionID],tbl_H_Assessment[Effectiveness on Vulnerability],""),'Summary Matrix'!$B$61:$B$64,'Summary Matrix'!$C$61:$C$64,""),""),"") | K78: =IFERROR(IF(_xlfn.XLOOKUP(tbl_Summary_Numerical[[#This Row],[ActionID]],tbl_H_EligibilitySummary[Action ID],tbl_H_EligibilitySummary[Exposure Eligibility],"")="Eligible",_xlfn.XLOOKUP(_xlfn.XLOOKUP(tbl_Summary_Numerical[[#This Row],[ActionID]],tbl_H_Assessment[ActionID],tbl_H_Assessment[Effectiveness on Exposure],""),'Summary Matrix'!$B$61:$B$64,'Summary Matrix'!$C$61:$C$64,""),""),"") | L78: =IFERROR(IF(_xlfn.XLOOKUP(tbl_Summary_Numerical[[#This Row],[ActionID]],tbl_GS_EligibilitySummary[Action ID],tbl_GS_EligibilitySummary[Vulnerability Eligibility],"")="Eligible",_xlfn.XLOOKUP(_xlfn.XLOOKUP(tbl_Summary_Numerical[[#This Row],[ActionID]],tbl_GS_Assessment[ActionID],tbl_GS_Assessment[Effectiveness on Vulnerability],""),'Summary Matrix'!$B$61:$B$64,'Summary Matrix'!$C$61:$C$64,""),""),"") | M78: =IFERROR(IF(_xlfn.XLOOKUP(tbl_Summary_Numerical[[#This Row],[ActionID]],tbl_GS_EligibilitySummary[Action ID],tbl_GS_EligibilitySummary[Exposure Eligibility],"")="Eligible",_xlfn.XLOOKUP(_xlfn.XLOOKUP(tbl_Summary_Numerical[[#This Row],[ActionID]],tbl_GS_Assessment[ActionID],tbl_GS_Assessment[Effectiveness on Exposure],""),'Summary Matrix'!$B$61:$B$64,'Summary Matrix'!$C$61:$C$64,""),""),"") | N78: =IFERROR(IF(_xlfn.XLOOKUP(tbl_Summary_Numerical[[#This Row],[ActionID]],tbl_B_EligibilitySummary[Action ID],tbl_B_EligibilitySummary[Vulnerability Eligibility],"")="Eligible",_xlfn.XLOOKUP(_xlfn.XLOOKUP(tbl_Summary_Numerical[[#This Row],[ActionID]],tbl_B_Assessment[ActionID],tbl_B_Assessment[Effectiveness on Vulnerability],""),'Summary Matrix'!$B$61:$B$64,'Summary Matrix'!$C$61:$C$64,""),""),"") | O78: =IFERROR(IF(_xlfn.XLOOKUP(tbl_Summary_Numerical[[#This Row],[ActionID]],tbl_B_EligibilitySummary[Action ID],tbl_B_EligibilitySummary[Exposure Eligibility],"")="Eligible",_xlfn.XLOOKUP(_xlfn.XLOOKUP(tbl_Summary_Numerical[[#This Row],[ActionID]],tbl_B_Assessment[ActionID],tbl_B_Assessment[Effectiveness on Exposure],""),'Summary Matrix'!$B$61:$B$64,'Summary Matrix'!$C$61:$C$64,""),""),"")
B79: icare_0154 | C79: Clean and unclog drainage channels and install eco-barriers | D79: =IFERROR(IF(_xlfn.XLOOKUP(tbl_Summary_Numerical[[#This Row],[ActionID]],tbl_WR_EligibilitySummary[Action ID],tbl_WR_EligibilitySummary[Vulnerability Eligibility],"")="Eligible",_xlfn.XLOOKUP(_xlfn.XLOOKUP(tbl_Summary_Numerical[[#This Row],[ActionID]],tbl_WR_Assessment[ActionID],tbl_WR_Assessment[Effectiveness on Vulnerability],""),'Summary Matrix'!$B$61:$B$64,'Summary Matrix'!$C$61:$C$64,""),""),"") | E79: =IFERROR(IF(_xlfn.XLOOKUP(tbl_Summary_Numerical[[#This Row],[ActionID]],tbl_WR_EligibilitySummary[Action ID],tbl_WR_EligibilitySummary[Exposure Eligibility],"")="Eligible",_xlfn.XLOOKUP(_xlfn.XLOOKUP(tbl_Summary_Numerical[[#This Row],[ActionID]],tbl_WR_Assessment[ActionID],tbl_WR_Assessment[Effectiveness on Exposure],""),'Summary Matrix'!$B$61:$B$64,'Summary Matrix'!$C$61:$C$64,""),""),"") | F79: =IFERROR(IF(_xlfn.XLOOKUP(tbl_Summary_Numerical[[#This Row],[ActionID]],tbl_FS_EligibilitySummary[Action ID],tbl_FS_EligibilitySummary[Vulnerability Eligibility],"")="Eligible",_xlfn.XLOOKUP(_xlfn.XLOOKUP(tbl_Summary_Numerical[[#This Row],[ActionID]],tbl_FS_Assessment[ActionID],tbl_FS_Assessment[Effectiveness on Vulnerability],""),'Summary Matrix'!$B$61:$B$64,'Summary Matrix'!$C$61:$C$64,""),""),"") | G79: =IFERROR(IF(_xlfn.XLOOKUP(tbl_Summary_Numerical[[#This Row],[ActionID]],tbl_FS_EligibilitySummary[Action ID],tbl_FS_EligibilitySummary[Exposure Eligibility],"")="Eligible",_xlfn.XLOOKUP(_xlfn.XLOOKUP(tbl_Summary_Numerical[[#This Row],[ActionID]],tbl_FS_Assessment[ActionID],tbl_FS_Assessment[Effectiveness on Exposure],""),'Summary Matrix'!$B$61:$B$64,'Summary Matrix'!$C$61:$C$64,""),""),"") | H79: =IFERROR(IF(_xlfn.XLOOKUP(tbl_Summary_Numerical[[#This Row],[ActionID]],tbl_ES_EligibilitySummary[Action ID],tbl_ES_EligibilitySummary[Vulnerability Eligibility],"")="Eligible",_xlfn.XLOOKUP(_xlfn.XLOOKUP(tbl_Summary_Numerical[[#This Row],[ActionID]],tbl_ES_Assessment[ActionID],tbl_ES_Assessment[Effectiveness on Vulnerability],""),'Summary Matrix'!$B$61:$B$64,'Summary Matrix'!$C$61:$C$64,""),""),"") | I79: =IFERROR(IF(_xlfn.XLOOKUP(tbl_Summary_Numerical[[#This Row],[ActionID]],tbl_ES_EligibilitySummary[Action ID],tbl_ES_EligibilitySummary[Exposure Eligibility],"")="Eligible",_xlfn.XLOOKUP(_xlfn.XLOOKUP(tbl_Summary_Numerical[[#This Row],[ActionID]],tbl_ES_Assessment[ActionID],tbl_ES_Assessment[Effectiveness on Exposure],""),'Summary Matrix'!$B$61:$B$64,'Summary Matrix'!$C$61:$C$64,""),""),"") | J79: =IFERROR(IF(_xlfn.XLOOKUP(tbl_Summary_Numerical[[#This Row],[ActionID]],tbl_H_EligibilitySummary[Action ID],tbl_H_EligibilitySummary[Vulnerability Eligibility],"")="Eligible",_xlfn.XLOOKUP(_xlfn.XLOOKUP(tbl_Summary_Numerical[[#This Row],[ActionID]],tbl_H_Assessment[ActionID],tbl_H_Assessment[Effectiveness on Vulnerability],""),'Summary Matrix'!$B$61:$B$64,'Summary Matrix'!$C$61:$C$64,""),""),"") | K79: =IFERROR(IF(_xlfn.XLOOKUP(tbl_Summary_Numerical[[#This Row],[ActionID]],tbl_H_EligibilitySummary[Action ID],tbl_H_EligibilitySummary[Exposure Eligibility],"")="Eligible",_xlfn.XLOOKUP(_xlfn.XLOOKUP(tbl_Summary_Numerical[[#This Row],[ActionID]],tbl_H_Assessment[ActionID],tbl_H_Assessment[Effectiveness on Exposure],""),'Summary Matrix'!$B$61:$B$64,'Summary Matrix'!$C$61:$C$64,""),""),"") | L79: =IFERROR(IF(_xlfn.XLOOKUP(tbl_Summary_Numerical[[#This Row],[ActionID]],tbl_GS_EligibilitySummary[Action ID],tbl_GS_EligibilitySummary[Vulnerability Eligibility],"")="Eligible",_xlfn.XLOOKUP(_xlfn.XLOOKUP(tbl_Summary_Numerical[[#This Row],[ActionID]],tbl_GS_Assessment[ActionID],tbl_GS_Assessment[Effectiveness on Vulnerability],""),'Summary Matrix'!$B$61:$B$64,'Summary Matrix'!$C$61:$C$64,""),""),"") | M79: =IFERROR(IF(_xlfn.XLOOKUP(tbl_Summary_Numerical[[#This Row],[ActionID]],tbl_GS_EligibilitySummary[Action ID],tbl_GS_EligibilitySummary[Exposure Eligibility],"")="Eligible",_xlfn.XLOOKUP(_xlfn.XLOOKUP(tbl_Summary_Numerical[[#This Row],[ActionID]],tbl_GS_Assessment[ActionID],tbl_GS_Assessment[Effectiveness on Exposure],""),'Summary Matrix'!$B$61:$B$64,'Summary Matrix'!$C$61:$C$64,""),""),"") | N79: =IFERROR(IF(_xlfn.XLOOKUP(tbl_Summary_Numerical[[#This Row],[ActionID]],tbl_B_EligibilitySummary[Action ID],tbl_B_EligibilitySummary[Vulnerability Eligibility],"")="Eligible",_xlfn.XLOOKUP(_xlfn.XLOOKUP(tbl_Summary_Numerical[[#This Row],[ActionID]],tbl_B_Assessment[ActionID],tbl_B_Assessment[Effectiveness on Vulnerability],""),'Summary Matrix'!$B$61:$B$64,'Summary Matrix'!$C$61:$C$64,""),""),"") | O79: =IFERROR(IF(_xlfn.XLOOKUP(tbl_Summary_Numerical[[#This Row],[ActionID]],tbl_B_EligibilitySummary[Action ID],tbl_B_EligibilitySummary[Exposure Eligibility],"")="Eligible",_xlfn.XLOOKUP(_xlfn.XLOOKUP(tbl_Summary_Numerical[[#This Row],[ActionID]],tbl_B_Assessment[ActionID],tbl_B_Assessment[Effectiveness on Exposure],""),'Summary Matrix'!$B$61:$B$64,'Summary Matrix'!$C$61:$C$64,""),""),"")
B80: icare_0156 | C80: Improve Implementation of urban gardens | D80: =IFERROR(IF(_xlfn.XLOOKUP(tbl_Summary_Numerical[[#This Row],[ActionID]],tbl_WR_EligibilitySummary[Action ID],tbl_WR_EligibilitySummary[Vulnerability Eligibility],"")="Eligible",_xlfn.XLOOKUP(_xlfn.XLOOKUP(tbl_Summary_Numerical[[#This Row],[ActionID]],tbl_WR_Assessment[ActionID],tbl_WR_Assessment[Effectiveness on Vulnerability],""),'Summary Matrix'!$B$61:$B$64,'Summary Matrix'!$C$61:$C$64,""),""),"") | E80: =IFERROR(IF(_xlfn.XLOOKUP(tbl_Summary_Numerical[[#This Row],[ActionID]],tbl_WR_EligibilitySummary[Action ID],tbl_WR_EligibilitySummary[Exposure Eligibility],"")="Eligible",_xlfn.XLOOKUP(_xlfn.XLOOKUP(tbl_Summary_Numerical[[#This Row],[ActionID]],tbl_WR_Assessment[ActionID],tbl_WR_Assessment[Effectiveness on Exposure],""),'Summary Matrix'!$B$61:$B$64,'Summary Matrix'!$C$61:$C$64,""),""),"") | F80: =IFERROR(IF(_xlfn.XLOOKUP(tbl_Summary_Numerical[[#This Row],[ActionID]],tbl_FS_EligibilitySummary[Action ID],tbl_FS_EligibilitySummary[Vulnerability Eligibility],"")="Eligible",_xlfn.XLOOKUP(_xlfn.XLOOKUP(tbl_Summary_Numerical[[#This Row],[ActionID]],tbl_FS_Assessment[ActionID],tbl_FS_Assessment[Effectiveness on Vulnerability],""),'Summary Matrix'!$B$61:$B$64,'Summary Matrix'!$C$61:$C$64,""),""),"") | G80: =IFERROR(IF(_xlfn.XLOOKUP(tbl_Summary_Numerical[[#This Row],[ActionID]],tbl_FS_EligibilitySummary[Action ID],tbl_FS_EligibilitySummary[Exposure Eligibility],"")="Eligible",_xlfn.XLOOKUP(_xlfn.XLOOKUP(tbl_Summary_Numerical[[#This Row],[ActionID]],tbl_FS_Assessment[ActionID],tbl_FS_Assessment[Effectiveness on Exposure],""),'Summary Matrix'!$B$61:$B$64,'Summary Matrix'!$C$61:$C$64,""),""),"") | H80: =IFERROR(IF(_xlfn.XLOOKUP(tbl_Summary_Numerical[[#This Row],[ActionID]],tbl_ES_EligibilitySummary[Action ID],tbl_ES_EligibilitySummary[Vulnerability Eligibility],"")="Eligible",_xlfn.XLOOKUP(_xlfn.XLOOKUP(tbl_Summary_Numerical[[#This Row],[ActionID]],tbl_ES_Assessment[ActionID],tbl_ES_Assessment[Effectiveness on Vulnerability],""),'Summary Matrix'!$B$61:$B$64,'Summary Matrix'!$C$61:$C$64,""),""),"") | I80: =IFERROR(IF(_xlfn.XLOOKUP(tbl_Summary_Numerical[[#This Row],[ActionID]],tbl_ES_EligibilitySummary[Action ID],tbl_ES_EligibilitySummary[Exposure Eligibility],"")="Eligible",_xlfn.XLOOKUP(_xlfn.XLOOKUP(tbl_Summary_Numerical[[#This Row],[ActionID]],tbl_ES_Assessment[ActionID],tbl_ES_Assessment[Effectiveness on Exposure],""),'Summary Matrix'!$B$61:$B$64,'Summary Matrix'!$C$61:$C$64,""),""),"") | J80: =IFERROR(IF(_xlfn.XLOOKUP(tbl_Summary_Numerical[[#This Row],[ActionID]],tbl_H_EligibilitySummary[Action ID],tbl_H_EligibilitySummary[Vulnerability Eligibility],"")="Eligible",_xlfn.XLOOKUP(_xlfn.XLOOKUP(tbl_Summary_Numerical[[#This Row],[ActionID]],tbl_H_Assessment[ActionID],tbl_H_Assessment[Effectiveness on Vulnerability],""),'Summary Matrix'!$B$61:$B$64,'Summary Matrix'!$C$61:$C$64,""),""),"") | K80: =IFERROR(IF(_xlfn.XLOOKUP(tbl_Summary_Numerical[[#This Row],[ActionID]],tbl_H_EligibilitySummary[Action ID],tbl_H_EligibilitySummary[Exposure Eligibility],"")="Eligible",_xlfn.XLOOKUP(_xlfn.XLOOKUP(tbl_Summary_Numerical[[#This Row],[ActionID]],tbl_H_Assessment[ActionID],tbl_H_Assessment[Effectiveness on Exposure],""),'Summary Matrix'!$B$61:$B$64,'Summary Matrix'!$C$61:$C$64,""),""),"") | L80: =IFERROR(IF(_xlfn.XLOOKUP(tbl_Summary_Numerical[[#This Row],[ActionID]],tbl_GS_EligibilitySummary[Action ID],tbl_GS_EligibilitySummary[Vulnerability Eligibility],"")="Eligible",_xlfn.XLOOKUP(_xlfn.XLOOKUP(tbl_Summary_Numerical[[#This Row],[ActionID]],tbl_GS_Assessment[ActionID],tbl_GS_Assessment[Effectiveness on Vulnerability],""),'Summary Matrix'!$B$61:$B$64,'Summary Matrix'!$C$61:$C$64,""),""),"") | M80: =IFERROR(IF(_xlfn.XLOOKUP(tbl_Summary_Numerical[[#This Row],[ActionID]],tbl_GS_EligibilitySummary[Action ID],tbl_GS_EligibilitySummary[Exposure Eligibility],"")="Eligible",_xlfn.XLOOKUP(_xlfn.XLOOKUP(tbl_Summary_Numerical[[#This Row],[ActionID]],tbl_GS_Assessment[ActionID],tbl_GS_Assessment[Effectiveness on Exposure],""),'Summary Matrix'!$B$61:$B$64,'Summary Matrix'!$C$61:$C$64,""),""),"") | N80: =IFERROR(IF(_xlfn.XLOOKUP(tbl_Summary_Numerical[[#This Row],[ActionID]],tbl_B_EligibilitySummary[Action ID],tbl_B_EligibilitySummary[Vulnerability Eligibility],"")="Eligible",_xlfn.XLOOKUP(_xlfn.XLOOKUP(tbl_Summary_Numerical[[#This Row],[ActionID]],tbl_B_Assessment[ActionID],tbl_B_Assessment[Effectiveness on Vulnerability],""),'Summary Matrix'!$B$61:$B$64,'Summary Matrix'!$C$61:$C$64,""),""),"") | O80: =IFERROR(IF(_xlfn.XLOOKUP(tbl_Summary_Numerical[[#This Row],[ActionID]],tbl_B_EligibilitySummary[Action ID],tbl_B_EligibilitySummary[Exposure Eligibility],"")="Eligible",_xlfn.XLOOKUP(_xlfn.XLOOKUP(tbl_Summary_Numerical[[#This Row],[ActionID]],tbl_B_Assessment[ActionID],tbl_B_Assessment[Effectiveness on Exposure],""),'Summary Matrix'!$B$61:$B$64,'Summary Matrix'!$C$61:$C$64,""),""),"")
... B121: ipcc_0104 | C121: Plan and support permanent climate‑related migration | D121: =IFERROR(IF(_xlfn.XLOOKUP(tbl_Summary_Numerical[[#This Row],[ActionID]],tbl_WR_EligibilitySummary[Action ID],tbl_WR_EligibilitySummary[Vulnerability Eligibility],"")="Eligible",_xlfn.XLOOKUP(_xlfn.XLOOKUP(tbl_Summary_Numerical[[#This Row],[ActionID]],tbl_WR_Assessment[ActionID],tbl_WR_Assessment[Effectiveness on Vulnerability],""),'Summary Matrix'!$B$61:$B$64,'Summary Matrix'!$C$61:$C$64,""),""),"") | E121: =IFERROR(IF(_xlfn.XLOOKUP(tbl_Summary_Numerical[[#This Row],[ActionID]],tbl_WR_EligibilitySummary[Action ID],tbl_WR_EligibilitySummary[Exposure Eligibility],"")="Eligible",_xlfn.XLOOKUP(_xlfn.XLOOKUP(tbl_Summary_Numerical[[#This Row],[ActionID]],tbl_WR_Assessment[ActionID],tbl_WR_Assessment[Effectiveness on Exposure],""),'Summary Matrix'!$B$61:$B$64,'Summary Matrix'!$C$61:$C$64,""),""),"") | F121: =IFERROR(IF(_xlfn.XLOOKUP(tbl_Summary_Numerical[[#This Row],[ActionID]],tbl_FS_EligibilitySummary[Action ID],tbl_FS_EligibilitySummary[Vulnerability Eligibility],"")="Eligible",_xlfn.XLOOKUP(_xlfn.XLOOKUP(tbl_Summary_Numerical[[#This Row],[ActionID]],tbl_FS_Assessment[ActionID],tbl_FS_Assessment[Effectiveness on Vulnerability],""),'Summary Matrix'!$B$61:$B$64,'Summary Matrix'!$C$61:$C$64,""),""),"") | G121: =IFERROR(IF(_xlfn.XLOOKUP(tbl_Summary_Numerical[[#This Row],[ActionID]],tbl_FS_EligibilitySummary[Action ID],tbl_FS_EligibilitySummary[Exposure Eligibility],"")="Eligible",_xlfn.XLOOKUP(_xlfn.XLOOKUP(tbl_Summary_Numerical[[#This Row],[ActionID]],tbl_FS_Assessment[ActionID],tbl_FS_Assessment[Effectiveness on Exposure],""),'Summary Matrix'!$B$61:$B$64,'Summary Matrix'!$C$61:$C$64,""),""),"") | H121: =IFERROR(IF(_xlfn.XLOOKUP(tbl_Summary_Numerical[[#This Row],[ActionID]],tbl_ES_EligibilitySummary[Action ID],tbl_ES_EligibilitySummary[Vulnerability Eligibility],"")="Eligible",_xlfn.XLOOKUP(_xlfn.XLOOKUP(tbl_Summary_Numerical[[#This Row],[ActionID]],tbl_ES_Assessment[ActionID],tbl_ES_Assessment[Effectiveness on Vulnerability],""),'Summary Matrix'!$B$61:$B$64,'Summary Matrix'!$C$61:$C$64,""),""),"") | I121: =IFERROR(IF(_xlfn.XLOOKUP(tbl_Summary_Numerical[[#This Row],[ActionID]],tbl_ES_EligibilitySummary[Action ID],tbl_ES_EligibilitySummary[Exposure Eligibility],"")="Eligible",_xlfn.XLOOKUP(_xlfn.XLOOKUP(tbl_Summary_Numerical[[#This Row],[ActionID]],tbl_ES_Assessment[ActionID],tbl_ES_Assessment[Effectiveness on Exposure],""),'Summary Matrix'!$B$61:$B$64,'Summary Matrix'!$C$61:$C$64,""),""),"") | J121: =IFERROR(IF(_xlfn.XLOOKUP(tbl_Summary_Numerical[[#This Row],[ActionID]],tbl_H_EligibilitySummary[Action ID],tbl_H_EligibilitySummary[Vulnerability Eligibility],"")="Eligible",_xlfn.XLOOKUP(_xlfn.XLOOKUP(tbl_Summary_Numerical[[#This Row],[ActionID]],tbl_H_Assessment[ActionID],tbl_H_Assessment[Effectiveness on Vulnerability],""),'Summary Matrix'!$B$61:$B$64,'Summary Matrix'!$C$61:$C$64,""),""),"") | K121: =IFERROR(IF(_xlfn.XLOOKUP(tbl_Summary_Numerical[[#This Row],[ActionID]],tbl_H_EligibilitySummary[Action ID],tbl_H_EligibilitySummary[Exposure Eligibility],"")="Eligible",_xlfn.XLOOKUP(_xlfn.XLOOKUP(tbl_Summary_Numerical[[#This Row],[ActionID]],tbl_H_Assessment[ActionID],tbl_H_Assessment[Effectiveness on Exposure],""),'Summary Matrix'!$B$61:$B$64,'Summary Matrix'!$C$61:$C$64,""),""),"") | L121: =IFERROR(IF(_xlfn.XLOOKUP(tbl_Summary_Numerical[[#This Row],[ActionID]],tbl_GS_EligibilitySummary[Action ID],tbl_GS_EligibilitySummary[Vulnerability Eligibility],"")="Eligible",_xlfn.XLOOKUP(_xlfn.XLOOKUP(tbl_Summary_Numerical[[#This Row],[ActionID]],tbl_GS_Assessment[ActionID],tbl_GS_Assessment[Effectiveness on Vulnerability],""),'Summary Matrix'!$B$61:$B$64,'Summary Matrix'!$C$61:$C$64,""),""),"") | M121: =IFERROR(IF(_xlfn.XLOOKUP(tbl_Summary_Numerical[[#This Row],[ActionID]],tbl_GS_EligibilitySummary[Action ID],tbl_GS_EligibilitySummary[Exposure Eligibility],"")="Eligible",_xlfn.XLOOKUP(_xlfn.XLOOKUP(tbl_Summary_Numerical[[#This Row],[ActionID]],tbl_GS_Assessment[ActionID],tbl_GS_Assessment[Effectiveness on Exposure],""),'Summary Matrix'!$B$61:$B$64,'Summary Matrix'!$C$61:$C$64,""),""),"") | N121: =IFERROR(IF(_xlfn.XLOOKUP(tbl_Summary_Numerical[[#This Row],[ActionID]],tbl_B_EligibilitySummary[Action ID],tbl_B_EligibilitySummary[Vulnerability Eligibility],"")="Eligible",_xlfn.XLOOKUP(_xlfn.XLOOKUP(tbl_Summary_Numerical[[#This Row],[ActionID]],tbl_B_Assessment[ActionID],tbl_B_Assessment[Effectiveness on Vulnerability],""),'Summary Matrix'!$B$61:$B$64,'Summary Matrix'!$C$61:$C$64,""),""),"") | O121: =IFERROR(IF(_xlfn.XLOOKUP(tbl_Summary_Numerical[[#This Row],[ActionID]],tbl_B_EligibilitySummary[Action ID],tbl_B_EligibilitySummary[Exposure Eligibility],"")="Eligible",_xlfn.XLOOKUP(_xlfn.XLOOKUP(tbl_Summary_Numerical[[#This Row],[ActionID]],tbl_B_Assessment[ActionID],tbl_B_Assessment[Effectiveness on Exposure],""),'Summary Matrix'!$B$61:$B$64,'Summary Matrix'!$C$61:$C$64,""),""),"")

Sheet Water Resources x actions
B2: Water Resources x actions
B3: Sector workflow for constructing the approved indicator framework, validating PDF evidence sources, assessing direct sector eligibility and evaluating cumulative effectiveness evidence.
B4: Red text identifies prompts to run with AI; all resulting assessments require evidence checks and human review.
B6: WATER RESOURCES ELIGIBILITY AND EFFECTIVENESS SUMMARY
B7: Record Type | C7: Action ID | D7: Action Name | E7: Vulnerability Eligibility | F7: Vulnerability Evidence Count | G7: Vulnerability Effectiveness | H7: Exposure Eligibility | I7: Exposure Evidence Count | J7: Exposure Effectiveness | K7: ReviewStatus
B8: {=IF(ROW()-ROW(tbl_WR_EligibilitySummary[#Headers])<=ROWS(tbl_WR_Assessment[ActionID]),"Existing action","Additional action")} -> Existing action | C8: {=IF(ROW()-ROW(tbl_WR_EligibilitySummary[#Headers])<=ROWS(tbl_WR_Assessment[ActionID]),INDEX(tbl_WR_Assessment[ActionID],ROW()-ROW(tbl_WR_EligibilitySummary[#Headers])),INDEX(tbl_WR_AdditionalActions[AdditionalActionID],ROW()-ROW(tbl_WR_EligibilitySummary[#Headers])-ROWS(tbl_WR_Assessment[ActionID])))} -> c40_0046 | D8: {=IF(ROW()-ROW(tbl_WR_EligibilitySummary[#Headers])<=ROWS(tbl_WR_Assessment[ActionID]),INDEX(tbl_WR_Assessment[ActionName],ROW()-ROW(tbl_WR_EligibilitySummary[#Headers])),INDEX(tbl_WR_AdditionalActions[ActionName],ROW()-ROW(tbl_WR_EligibilitySummary[#Headers])-ROWS(tbl_WR_Assessment[ActionID])))} -> Strengthen coastal protection infrastructure | E8: {=IF(ROW()-ROW(tbl_WR_EligibilitySummary[#Headers])<=ROWS(tbl_WR_Assessment[ActionID]),INDEX(tbl_WR_Assessment[Vulnerability Eligibility],ROW()-ROW(tbl_WR_EligibilitySummary[#Headers])),INDEX(tbl_WR_AdditionalActions[Vulnerability Eligibility],ROW()-ROW(tbl_WR_EligibilitySummary[#Headers])-ROWS(tbl_WR_Assessment[ActionID])))} -> Not eligible | F8: {=IF(ROW()-ROW(tbl_WR_EligibilitySummary[#Headers])<=ROWS(tbl_WR_Assessment[ActionID]),IF(INDEX(tbl_WR_Assessment[Vulnerability Evidence Count],ROW()-ROW(tbl_WR_EligibilitySummary[#Headers]))=0,"",INDEX(tbl_WR_Assessment[Vulnerability Evidence Count],ROW()-ROW(tbl_WR_EligibilitySummary[#Headers]))),IF(INDEX(tbl_WR_AdditionalActions[Vulnerability Evidence Count],ROW()-ROW(tbl_WR_EligibilitySummary[#Headers])-ROWS(tbl_WR_Assessment[ActionID]))=0,"",INDEX(tbl_WR_AdditionalActions[Vulnerability Evidence Count],ROW()-ROW(tbl_WR_EligibilitySummary[#Headers])-ROWS(tbl_WR_Assessment[ActionID]))))} | G8: {=IF(tbl_WR_EligibilitySummary[[#This Row],[Vulnerability Eligibility]]="Eligible",IF(ROW()-ROW(tbl_WR_EligibilitySummary[#Headers])<=ROWS(tbl_WR_Assessment[ActionID]),INDEX(tbl_WR_Assessment[Effectiveness on Vulnerability],ROW()-ROW(tbl_WR_EligibilitySummary[#Headers])),INDEX(tbl_WR_AdditionalActions[Effectiveness on Vulnerability],ROW()-ROW(tbl_WR_EligibilitySummary[#Headers])-ROWS(tbl_WR_Assessment[ActionID]))),IF(tbl_WR_EligibilitySummary[[#This Row],[Vulnerability Eligibility]]="Review required","Review required",IF(tbl_WR_EligibilitySummary[[#This Row],[Vulnerability Eligibility]]="Not eligible","N/A","")))} -> N/A | H8: {=IF(ROW()-ROW(tbl_WR_EligibilitySummary[#Headers])<=ROWS(tbl_WR_Assessment[ActionID]),INDEX(tbl_WR_Assessment[Exposure Eligibility],ROW()-ROW(tbl_WR_EligibilitySummary[#Headers])),INDEX(tbl_WR_AdditionalActions[Exposure Eligibility],ROW()-ROW(tbl_WR_EligibilitySummary[#Headers])-ROWS(tbl_WR_Assessment[ActionID])))} -> Not eligible | I8: {=IF(ROW()-ROW(tbl_WR_EligibilitySummary[#Headers])<=ROWS(tbl_WR_Assessment[ActionID]),IF(INDEX(tbl_WR_Assessment[Exposure Evidence Count],ROW()-ROW(tbl_WR_EligibilitySummary[#Headers]))=0,"",INDEX(tbl_WR_Assessment[Exposure Evidence Count],ROW()-ROW(tbl_WR_EligibilitySummary[#Headers]))),IF(INDEX(tbl_WR_AdditionalActions[Exposure Evidence Count],ROW()-ROW(tbl_WR_EligibilitySummary[#Headers])-ROWS(tbl_WR_Assessment[ActionID]))=0,"",INDEX(tbl_WR_AdditionalActions[Exposure Evidence Count],ROW()-ROW(tbl_WR_EligibilitySummary[#Headers])-ROWS(tbl_WR_Assessment[ActionID]))))} | J8: {=IF(tbl_WR_EligibilitySummary[[#This Row],[Exposure Eligibility]]="Eligible",IF(ROW()-ROW(tbl_WR_EligibilitySummary[#Headers])<=ROWS(tbl_WR_Assessment[ActionID]),INDEX(tbl_WR_Assessment[Effectiveness on Exposure],ROW()-ROW(tbl_WR_EligibilitySummary[#Headers])),INDEX(tbl_WR_AdditionalActions[Effectiveness on Exposure],ROW()-ROW(tbl_WR_EligibilitySummary[#Headers])-ROWS(tbl_WR_Assessment[ActionID]))),IF(tbl_WR_EligibilitySummary[[#This Row],[Exposure Eligibility]]="Review required","Review required",IF(tbl_WR_EligibilitySummary[[#This Row],[Exposure Eligibility]]="Not eligible","N/A","")))} -> N/A | K8: {=IF(ROW()-ROW(tbl_WR_EligibilitySummary[#Headers])<=ROWS(tbl_WR_Assessment[ActionID]),INDEX(tbl_WR_Assessment[ReviewStatus],ROW()-ROW(tbl_WR_EligibilitySummary[#Headers])),INDEX(tbl_WR_AdditionalActions[ReviewStatus],ROW()-ROW(tbl_WR_EligibilitySummary[#Headers])-ROWS(tbl_WR_Assessment[ActionID])))} -> Not assessed
B9: {=IF(ROW()-ROW(tbl_WR_EligibilitySummary[#Headers])<=ROWS(tbl_WR_Assessment[ActionID]),"Existing action","Additional action")} -> Existing action | C9: {=IF(ROW()-ROW(tbl_WR_EligibilitySummary[#Headers])<=ROWS(tbl_WR_Assessment[ActionID]),INDEX(tbl_WR_Assessment[ActionID],ROW()-ROW(tbl_WR_EligibilitySummary[#Headers])),INDEX(tbl_WR_AdditionalActions[AdditionalActionID],ROW()-ROW(tbl_WR_EligibilitySummary[#Headers])-ROWS(tbl_WR_Assessment[ActionID])))} -> c40_0048 | D9: {=IF(ROW()-ROW(tbl_WR_EligibilitySummary[#Headers])<=ROWS(tbl_WR_Assessment[ActionID]),INDEX(tbl_WR_Assessment[ActionName],ROW()-ROW(tbl_WR_EligibilitySummary[#Headers])),INDEX(tbl_WR_AdditionalActions[ActionName],ROW()-ROW(tbl_WR_EligibilitySummary[#Headers])-ROWS(tbl_WR_Assessment[ActionID])))} -> Upgrade urban drainage systems | E9: {=IF(ROW()-ROW(tbl_WR_EligibilitySummary[#Headers])<=ROWS(tbl_WR_Assessment[ActionID]),INDEX(tbl_WR_Assessment[Vulnerability Eligibility],ROW()-ROW(tbl_WR_EligibilitySummary[#Headers])),INDEX(tbl_WR_AdditionalActions[Vulnerability Eligibility],ROW()-ROW(tbl_WR_EligibilitySummary[#Headers])-ROWS(tbl_WR_Assessment[ActionID])))} -> Not eligible | F9: {=IF(ROW()-ROW(tbl_WR_EligibilitySummary[#Headers])<=ROWS(tbl_WR_Assessment[ActionID]),IF(INDEX(tbl_WR_Assessment[Vulnerability Evidence Count],ROW()-ROW(tbl_WR_EligibilitySummary[#Headers]))=0,"",INDEX(tbl_WR_Assessment[Vulnerability Evidence Count],ROW()-ROW(tbl_WR_EligibilitySummary[#Headers]))),IF(INDEX(tbl_WR_AdditionalActions[Vulnerability Evidence Count],ROW()-ROW(tbl_WR_EligibilitySummary[#Headers])-ROWS(tbl_WR_Assessment[ActionID]))=0,"",INDEX(tbl_WR_AdditionalActions[Vulnerability Evidence Count],ROW()-ROW(tbl_WR_EligibilitySummary[#Headers])-ROWS(tbl_WR_Assessment[ActionID]))))} -> 1 | G9: {=IF(tbl_WR_EligibilitySummary[[#This Row],[Vulnerability Eligibility]]="Eligible",IF(ROW()-ROW(tbl_WR_EligibilitySummary[#Headers])<=ROWS(tbl_WR_Assessment[ActionID]),INDEX(tbl_WR_Assessment[Effectiveness on Vulnerability],ROW()-ROW(tbl_WR_EligibilitySummary[#Headers])),INDEX(tbl_WR_AdditionalActions[Effectiveness on Vulnerability],ROW()-ROW(tbl_WR_EligibilitySummary[#Headers])-ROWS(tbl_WR_Assessment[ActionID]))),IF(tbl_WR_EligibilitySummary[[#This Row],[Vulnerability Eligibility]]="Review required","Review required",IF(tbl_WR_EligibilitySummary[[#This Row],[Vulnerability Eligibility]]="Not eligible","N/A","")))} -> N/A | H9: {=IF(ROW()-ROW(tbl_WR_EligibilitySummary[#Headers])<=ROWS(tbl_WR_Assessment[ActionID]),INDEX(tbl_WR_Assessment[Exposure Eligibility],ROW()-ROW(tbl_WR_EligibilitySummary[#Headers])),INDEX(tbl_WR_AdditionalActions[Exposure Eligibility],ROW()-ROW(tbl_WR_EligibilitySummary[#Headers])-ROWS(tbl_WR_Assessment[ActionID])))} -> Not eligible | I9: {=IF(ROW()-ROW(tbl_WR_EligibilitySummary[#Headers])<=ROWS(tbl_WR_Assessment[ActionID]),IF(INDEX(tbl_WR_Assessment[Exposure Evidence Count],ROW()-ROW(tbl_WR_EligibilitySummary[#Headers]))=0,"",INDEX(tbl_WR_Assessment[Exposure Evidence Count],ROW()-ROW(tbl_WR_EligibilitySummary[#Headers]))),IF(INDEX(tbl_WR_AdditionalActions[Exposure Evidence Count],ROW()-ROW(tbl_WR_EligibilitySummary[#Headers])-ROWS(tbl_WR_Assessment[ActionID]))=0,"",INDEX(tbl_WR_AdditionalActions[Exposure Evidence Count],ROW()-ROW(tbl_WR_EligibilitySummary[#Headers])-ROWS(tbl_WR_Assessment[ActionID]))))} | J9: {=IF(tbl_WR_EligibilitySummary[[#This Row],[Exposure Eligibility]]="Eligible",IF(ROW()-ROW(tbl_WR_EligibilitySummary[#Headers])<=ROWS(tbl_WR_Assessment[ActionID]),INDEX(tbl_WR_Assessment[Effectiveness on Exposure],ROW()-ROW(tbl_WR_EligibilitySummary[#Headers])),INDEX(tbl_WR_AdditionalActions[Effectiveness on Exposure],ROW()-ROW(tbl_WR_EligibilitySummary[#Headers])-ROWS(tbl_WR_Assessment[ActionID]))),IF(tbl_WR_EligibilitySummary[[#This Row],[Exposure Eligibility]]="Review required","Review required",IF(tbl_WR_EligibilitySummary[[#This Row],[Exposure Eligibility]]="Not eligible","N/A","")))} -> N/A | K9: {=IF(ROW()-ROW(tbl_WR_EligibilitySummary[#Headers])<=ROWS(tbl_WR_Assessment[ActionID]),INDEX(tbl_WR_Assessment[ReviewStatus],ROW()-ROW(tbl_WR_EligibilitySummary[#Headers])),INDEX(tbl_WR_AdditionalActions[ReviewStatus],ROW()-ROW(tbl_WR_EligibilitySummary[#Headers])-ROWS(tbl_WR_Assessment[ActionID])))} -> Eligibility corrected
B10: {=IF(ROW()-ROW(tbl_WR_EligibilitySummary[#Headers])<=ROWS(tbl_WR_Assessment[ActionID]),"Existing action","Additional action")} -> Existing action | C10: {=IF(ROW()-ROW(tbl_WR_EligibilitySummary[#Headers])<=ROWS(tbl_WR_Assessment[ActionID]),INDEX(tbl_WR_Assessment[ActionID],ROW()-ROW(tbl_WR_EligibilitySummary[#Headers])),INDEX(tbl_WR_AdditionalActions[AdditionalActionID],ROW()-ROW(tbl_WR_EligibilitySummary[#Headers])-ROWS(tbl_WR_Assessment[ActionID])))} -> c40_0049 | D10: {=IF(ROW()-ROW(tbl_WR_EligibilitySummary[#Headers])<=ROWS(tbl_WR_Assessment[ActionID]),INDEX(tbl_WR_Assessment[ActionName],ROW()-ROW(tbl_WR_EligibilitySummary[#Headers])),INDEX(tbl_WR_AdditionalActions[ActionName],ROW()-ROW(tbl_WR_EligibilitySummary[#Headers])-ROWS(tbl_WR_Assessment[ActionID])))} -> Build and maintain shelters for critical climate hazards | E10: {=IF(ROW()-ROW(tbl_WR_EligibilitySummary[#Headers])<=ROWS(tbl_WR_Assessment[ActionID]),INDEX(tbl_WR_Assessment[Vulnerability Eligibility],ROW()-ROW(tbl_WR_EligibilitySummary[#Headers])),INDEX(tbl_WR_AdditionalActions[Vulnerability Eligibility],ROW()-ROW(tbl_WR_EligibilitySummary[#Headers])-ROWS(tbl_WR_Assessment[ActionID])))} -> Not eligible | F10: {=IF(ROW()-ROW(tbl_WR_EligibilitySummary[#Headers])<=ROWS(tbl_WR_Assessment[ActionID]),IF(INDEX(tbl_WR_Assessment[Vulnerability Evidence Count],ROW()-ROW(tbl_WR_EligibilitySummary[#Headers]))=0,"",INDEX(tbl_WR_Assessment[Vulnerability Evidence Count],ROW()-ROW(tbl_WR_EligibilitySummary[#Headers]))),IF(INDEX(tbl_WR_AdditionalActions[Vulnerability Evidence Count],ROW()-ROW(tbl_WR_EligibilitySummary[#Headers])-ROWS(tbl_WR_Assessment[ActionID]))=0,"",INDEX(tbl_WR_AdditionalActions[Vulnerability Evidence Count],ROW()-ROW(tbl_WR_EligibilitySummary[#Headers])-ROWS(tbl_WR_Assessment[ActionID]))))} | G10: {=IF(tbl_WR_EligibilitySummary[[#This Row],[Vulnerability Eligibility]]="Eligible",IF(ROW()-ROW(tbl_WR_EligibilitySummary[#Headers])<=ROWS(tbl_WR_Assessment[ActionID]),INDEX(tbl_WR_Assessment[Effectiveness on Vulnerability],ROW()-ROW(tbl_WR_EligibilitySummary[#Headers])),INDEX(tbl_WR_AdditionalActions[Effectiveness on Vulnerability],ROW()-ROW(tbl_WR_EligibilitySummary[#Headers])-ROWS(tbl_WR_Assessment[ActionID]))),IF(tbl_WR_EligibilitySummary[[#This Row],[Vulnerability Eligibility]]="Review required","Review required",IF(tbl_WR_EligibilitySummary[[#This Row],[Vulnerability Eligibility]]="Not eligible","N/A","")))} -> N/A | H10: {=IF(ROW()-ROW(tbl_WR_EligibilitySummary[#Headers])<=ROWS(tbl_WR_Assessment[ActionID]),INDEX(tbl_WR_Assessment[Exposure Eligibility],ROW()-ROW(tbl_WR_EligibilitySummary[#Headers])),INDEX(tbl_WR_AdditionalActions[Exposure Eligibility],ROW()-ROW(tbl_WR_EligibilitySummary[#Headers])-ROWS(tbl_WR_Assessment[ActionID])))} -> Not eligible | I10: {=IF(ROW()-ROW(tbl_WR_EligibilitySummary[#Headers])<=ROWS(tbl_WR_Assessment[ActionID]),IF(INDEX(tbl_WR_Assessment[Exposure Evidence Count],ROW()-ROW(tbl_WR_EligibilitySummary[#Headers]))=0,"",INDEX(tbl_WR_Assessment[Exposure Evidence Count],ROW()-ROW(tbl_WR_EligibilitySummary[#Headers]))),IF(INDEX(tbl_WR_AdditionalActions[Exposure Evidence Count],ROW()-ROW(tbl_WR_EligibilitySummary[#Headers])-ROWS(tbl_WR_Assessment[ActionID]))=0,"",INDEX(tbl_WR_AdditionalActions[Exposure Evidence Count],ROW()-ROW(tbl_WR_EligibilitySummary[#Headers])-ROWS(tbl_WR_Assessment[ActionID]))))} | J10: {=IF(tbl_WR_EligibilitySummary[[#This Row],[Exposure Eligibility]]="Eligible",IF(ROW()-ROW(tbl_WR_EligibilitySummary[#Headers])<=ROWS(tbl_WR_Assessment[ActionID]),INDEX(tbl_WR_Assessment[Effectiveness on Exposure],ROW()-ROW(tbl_WR_EligibilitySummary[#Headers])),INDEX(tbl_WR_AdditionalActions[Effectiveness on Exposure],ROW()-ROW(tbl_WR_EligibilitySummary[#Headers])-ROWS(tbl_WR_Assessment[ActionID]))),IF(tbl_WR_EligibilitySummary[[#This Row],[Exposure Eligibility]]="Review required","Review required",IF(tbl_WR_EligibilitySummary[[#This Row],[Exposure Eligibility]]="Not eligible","N/A","")))} -> N/A | K10: {=IF(ROW()-ROW(tbl_WR_EligibilitySummary[#Headers])<=ROWS(tbl_WR_Assessment[ActionID]),INDEX(tbl_WR_Assessment[ReviewStatus],ROW()-ROW(tbl_WR_EligibilitySummary[#Headers])),INDEX(tbl_WR_AdditionalActions[ReviewStatus],ROW()-ROW(tbl_WR_EligibilitySummary[#Headers])-ROWS(tbl_WR_Assessment[ActionID])))} -> Not assessed
B11: {=IF(ROW()-ROW(tbl_WR_EligibilitySummary[#Headers])<=ROWS(tbl_WR_Assessment[ActionID]),"Existing action","Additional action")} -> Existing action | C11: {=IF(ROW()-ROW(tbl_WR_EligibilitySummary[#Headers])<=ROWS(tbl_WR_Assessment[ActionID]),INDEX(tbl_WR_Assessment[ActionID],ROW()-ROW(tbl_WR_EligibilitySummary[#Headers])),INDEX(tbl_WR_AdditionalActions[AdditionalActionID],ROW()-ROW(tbl_WR_EligibilitySummary[#Headers])-ROWS(tbl_WR_Assessment[ActionID])))} -> c40_0051 | D11: {=IF(ROW()-ROW(tbl_WR_EligibilitySummary[#Headers])<=ROWS(tbl_WR_Assessment[ActionID]),INDEX(tbl_WR_Assessment[ActionName],ROW()-ROW(tbl_WR_EligibilitySummary[#Headers])),INDEX(tbl_WR_AdditionalActions[ActionName],ROW()-ROW(tbl_WR_EligibilitySummary[#Headers])-ROWS(tbl_WR_Assessment[ActionID])))} -> Provide public shading in heat hotspots | E11: {=IF(ROW()-ROW(tbl_WR_EligibilitySummary[#Headers])<=ROWS(tbl_WR_Assessment[ActionID]),INDEX(tbl_WR_Assessment[Vulnerability Eligibility],ROW()-ROW(tbl_WR_EligibilitySummary[#Headers])),INDEX(tbl_WR_AdditionalActions[Vulnerability Eligibility],ROW()-ROW(tbl_WR_EligibilitySummary[#Headers])-ROWS(tbl_WR_Assessment[ActionID])))} -> Not eligible | F11: {=IF(ROW()-ROW(tbl_WR_EligibilitySummary[#Headers])<=ROWS(tbl_WR_Assessment[ActionID]),IF(INDEX(tbl_WR_Assessment[Vulnerability Evidence Count],ROW()-ROW(tbl_WR_EligibilitySummary[#Headers]))=0,"",INDEX(tbl_WR_Assessment[Vulnerability Evidence Count],ROW()-ROW(tbl_WR_EligibilitySummary[#Headers]))),IF(INDEX(tbl_WR_AdditionalActions[Vulnerability Evidence Count],ROW()-ROW(tbl_WR_EligibilitySummary[#Headers])-ROWS(tbl_WR_Assessment[ActionID]))=0,"",INDEX(tbl_WR_AdditionalActions[Vulnerability Evidence Count],ROW()-ROW(tbl_WR_EligibilitySummary[#Headers])-ROWS(tbl_WR_Assessment[ActionID]))))} | G11: {=IF(tbl_WR_EligibilitySummary[[#This Row],[Vulnerability Eligibility]]="Eligible",IF(ROW()-ROW(tbl_WR_EligibilitySummary[#Headers])<=ROWS(tbl_WR_Assessment[ActionID]),INDEX(tbl_WR_Assessment[Effectiveness on Vulnerability],ROW()-ROW(tbl_WR_EligibilitySummary[#Headers])),INDEX(tbl_WR_AdditionalActions[Effectiveness on Vulnerability],ROW()-ROW(tbl_WR_EligibilitySummary[#Headers])-ROWS(tbl_WR_Assessment[ActionID]))),IF(tbl_WR_EligibilitySummary[[#This Row],[Vulnerability Eligibility]]="Review required","Review required",IF(tbl_WR_EligibilitySummary[[#This Row],[Vulnerability Eligibility]]="Not eligible","N/A","")))} -> N/A | H11: {=IF(ROW()-ROW(tbl_WR_EligibilitySummary[#Headers])<=ROWS(tbl_WR_Assessment[ActionID]),INDEX(tbl_WR_Assessment[Exposure Eligibility],ROW()-ROW(tbl_WR_EligibilitySummary[#Headers])),INDEX(tbl_WR_AdditionalActions[Exposure Eligibility],ROW()-ROW(tbl_WR_EligibilitySummary[#Headers])-ROWS(tbl_WR_Assessment[ActionID])))} -> Not eligible | I11: {=IF(ROW()-ROW(tbl_WR_EligibilitySummary[#Headers])<=ROWS(tbl_WR_Assessment[ActionID]),IF(INDEX(tbl_WR_Assessment[Exposure Evidence Count],ROW()-ROW(tbl_WR_EligibilitySummary[#Headers]))=0,"",INDEX(tbl_WR_Assessment[Exposure Evidence Count],ROW()-ROW(tbl_WR_EligibilitySummary[#Headers]))),IF(INDEX(tbl_WR_AdditionalActions[Exposure Evidence Count],ROW()-ROW(tbl_WR_EligibilitySummary[#Headers])-ROWS(tbl_WR_Assessment[ActionID]))=0,"",INDEX(tbl_WR_AdditionalActions[Exposure Evidence Count],ROW()-ROW(tbl_WR_EligibilitySummary[#Headers])-ROWS(tbl_WR_Assessment[ActionID]))))} | J11: {=IF(tbl_WR_EligibilitySummary[[#This Row],[Exposure Eligibility]]="Eligible",IF(ROW()-ROW(tbl_WR_EligibilitySummary[#Headers])<=ROWS(tbl_WR_Assessment[ActionID]),INDEX(tbl_WR_Assessment[Effectiveness on Exposure],ROW()-ROW(tbl_WR_EligibilitySummary[#Headers])),INDEX(tbl_WR_AdditionalActions[Effectiveness on Exposure],ROW()-ROW(tbl_WR_EligibilitySummary[#Headers])-ROWS(tbl_WR_Assessment[ActionID]))),IF(tbl_WR_EligibilitySummary[[#This Row],[Exposure Eligibility]]="Review required","Review required",IF(tbl_WR_EligibilitySummary[[#This Row],[Exposure Eligibility]]="Not eligible","N/A","")))} -> N/A | K11: {=IF(ROW()-ROW(tbl_WR_EligibilitySummary[#Headers])<=ROWS(tbl_WR_Assessment[ActionID]),INDEX(tbl_WR_Assessment[ReviewStatus],ROW()-ROW(tbl_WR_EligibilitySummary[#Headers])),INDEX(tbl_WR_AdditionalActions[ReviewStatus],ROW()-ROW(tbl_WR_EligibilitySummary[#Headers])-ROWS(tbl_WR_Assessment[ActionID])))} -> Not assessed
B12: {=IF(ROW()-ROW(tbl_WR_EligibilitySummary[#Headers])<=ROWS(tbl_WR_Assessment[ActionID]),"Existing action","Additional action")} -> Existing action | C12: {=IF(ROW()-ROW(tbl_WR_EligibilitySummary[#Headers])<=ROWS(tbl_WR_Assessment[ActionID]),INDEX(tbl_WR_Assessment[ActionID],ROW()-ROW(tbl_WR_EligibilitySummary[#Headers])),INDEX(tbl_WR_AdditionalActions[AdditionalActionID],ROW()-ROW(tbl_WR_EligibilitySummary[#Headers])-ROWS(tbl_WR_Assessment[ActionID])))} -> c40_0052 | D12: {=IF(ROW()-ROW(tbl_WR_EligibilitySummary[#Headers])<=ROWS(tbl_WR_Assessment[ActionID]),INDEX(tbl_WR_Assessment[ActionName],ROW()-ROW(tbl_WR_EligibilitySummary[#Headers])),INDEX(tbl_WR_AdditionalActions[ActionName],ROW()-ROW(tbl_WR_EligibilitySummary[#Headers])-ROWS(tbl_WR_Assessment[ActionID])))} -> Deploy cool pavements and cool roofs on heat‑exposed streets and buildings | E12: {=IF(ROW()-ROW(tbl_WR_EligibilitySummary[#Headers])<=ROWS(tbl_WR_Assessment[ActionID]),INDEX(tbl_WR_Assessment[Vulnerability Eligibility],ROW()-ROW(tbl_WR_EligibilitySummary[#Headers])),INDEX(tbl_WR_AdditionalActions[Vulnerability Eligibility],ROW()-ROW(tbl_WR_EligibilitySummary[#Headers])-ROWS(tbl_WR_Assessment[ActionID])))} -> Not eligible | F12: {=IF(ROW()-ROW(tbl_WR_EligibilitySummary[#Headers])<=ROWS(tbl_WR_Assessment[ActionID]),IF(INDEX(tbl_WR_Assessment[Vulnerability Evidence Count],ROW()-ROW(tbl_WR_EligibilitySummary[#Headers]))=0,"",INDEX(tbl_WR_Assessment[Vulnerability Evidence Count],ROW()-ROW(tbl_WR_EligibilitySummary[#Headers]))),IF(INDEX(tbl_WR_AdditionalActions[Vulnerability Evidence Count],ROW()-ROW(tbl_WR_EligibilitySummary[#Headers])-ROWS(tbl_WR_Assessment[ActionID]))=0,"",INDEX(tbl_WR_AdditionalActions[Vulnerability Evidence Count],ROW()-ROW(tbl_WR_EligibilitySummary[#Headers])-ROWS(tbl_WR_Assessment[ActionID]))))} | G12: {=IF(tbl_WR_EligibilitySummary[[#This Row],[Vulnerability Eligibility]]="Eligible",IF(ROW()-ROW(tbl_WR_EligibilitySummary[#Headers])<=ROWS(tbl_WR_Assessment[ActionID]),INDEX(tbl_WR_Assessment[Effectiveness on Vulnerability],ROW()-ROW(tbl_WR_EligibilitySummary[#Headers])),INDEX(tbl_WR_AdditionalActions[Effectiveness on Vulnerability],ROW()-ROW(tbl_WR_EligibilitySummary[#Headers])-ROWS(tbl_WR_Assessment[ActionID]))),IF(tbl_WR_EligibilitySummary[[#This Row],[Vulnerability Eligibility]]="Review required","Review required",IF(tbl_WR_EligibilitySummary[[#This Row],[Vulnerability Eligibility]]="Not eligible","N/A","")))} -> N/A | H12: {=IF(ROW()-ROW(tbl_WR_EligibilitySummary[#Headers])<=ROWS(tbl_WR_Assessment[ActionID]),INDEX(tbl_WR_Assessment[Exposure Eligibility],ROW()-ROW(tbl_WR_EligibilitySummary[#Headers])),INDEX(tbl_WR_AdditionalActions[Exposure Eligibility],ROW()-ROW(tbl_WR_EligibilitySummary[#Headers])-ROWS(tbl_WR_Assessment[ActionID])))} -> Not eligible | I12: {=IF(ROW()-ROW(tbl_WR_EligibilitySummary[#Headers])<=ROWS(tbl_WR_Assessment[ActionID]),IF(INDEX(tbl_WR_Assessment[Exposure Evidence Count],ROW()-ROW(tbl_WR_EligibilitySummary[#Headers]))=0,"",INDEX(tbl_WR_Assessment[Exposure Evidence Count],ROW()-ROW(tbl_WR_EligibilitySummary[#Headers]))),IF(INDEX(tbl_WR_AdditionalActions[Exposure Evidence Count],ROW()-ROW(tbl_WR_EligibilitySummary[#Headers])-ROWS(tbl_WR_Assessment[ActionID]))=0,"",INDEX(tbl_WR_AdditionalActions[Exposure Evidence Count],ROW()-ROW(tbl_WR_EligibilitySummary[#Headers])-ROWS(tbl_WR_Assessment[ActionID]))))} | J12: {=IF(tbl_WR_EligibilitySummary[[#This Row],[Exposure Eligibility]]="Eligible",IF(ROW()-ROW(tbl_WR_EligibilitySummary[#Headers])<=ROWS(tbl_WR_Assessment[ActionID]),INDEX(tbl_WR_Assessment[Effectiveness on Exposure],ROW()-ROW(tbl_WR_EligibilitySummary[#Headers])),INDEX(tbl_WR_AdditionalActions[Effectiveness on Exposure],ROW()-ROW(tbl_WR_EligibilitySummary[#Headers])-ROWS(tbl_WR_Assessment[ActionID]))),IF(tbl_WR_EligibilitySummary[[#This Row],[Exposure Eligibility]]="Review required","Review required",IF(tbl_WR_EligibilitySummary[[#This Row],[Exposure Eligibility]]="Not eligible","N/A","")))} -> N/A | K12: {=IF(ROW()-ROW(tbl_WR_EligibilitySummary[#Headers])<=ROWS(tbl_WR_Assessment[ActionID]),INDEX(tbl_WR_Assessment[ReviewStatus],ROW()-ROW(tbl_WR_EligibilitySummary[#Headers])),INDEX(tbl_WR_AdditionalActions[ReviewStatus],ROW()-ROW(tbl_WR_EligibilitySummary[#Headers])-ROWS(tbl_WR_Assessment[ActionID])))} -> Not assessed
B13: {=IF(ROW()-ROW(tbl_WR_EligibilitySummary[#Headers])<=ROWS(tbl_WR_Assessment[ActionID]),"Existing action","Additional action")} -> Existing action | C13: {=IF(ROW()-ROW(tbl_WR_EligibilitySummary[#Headers])<=ROWS(tbl_WR_Assessment[ActionID]),INDEX(tbl_WR_Assessment[ActionID],ROW()-ROW(tbl_WR_EligibilitySummary[#Headers])),INDEX(tbl_WR_AdditionalActions[AdditionalActionID],ROW()-ROW(tbl_WR_EligibilitySummary[#Headers])-ROWS(tbl_WR_Assessment[ActionID])))} -> c40_0053 | D13: {=IF(ROW()-ROW(tbl_WR_EligibilitySummary[#Headers])<=ROWS(tbl_WR_Assessment[ActionID]),INDEX(tbl_WR_Assessment[ActionName],ROW()-ROW(tbl_WR_EligibilitySummary[#Headers])),INDEX(tbl_WR_AdditionalActions[ActionName],ROW()-ROW(tbl_WR_EligibilitySummary[#Headers])-ROWS(tbl_WR_Assessment[ActionID])))} -> Promote water-saving technologies and practices | E13: {=IF(ROW()-ROW(tbl_WR_EligibilitySummary[#Headers])<=ROWS(tbl_WR_Assessment[ActionID]),INDEX(tbl_WR_Assessment[Vulnerability Eligibility],ROW()-ROW(tbl_WR_EligibilitySummary[#Headers])),INDEX(tbl_WR_AdditionalActions[Vulnerability Eligibility],ROW()-ROW(tbl_WR_EligibilitySummary[#Headers])-ROWS(tbl_WR_Assessment[ActionID])))} -> Eligible | F13: {=IF(ROW()-ROW(tbl_WR_EligibilitySummary[#Headers])<=ROWS(tbl_WR_Assessment[ActionID]),IF(INDEX(tbl_WR_Assessment[Vulnerability Evidence Count],ROW()-ROW(tbl_WR_EligibilitySummary[#Headers]))=0,"",INDEX(tbl_WR_Assessment[Vulnerability Evidence Count],ROW()-ROW(tbl_WR_EligibilitySummary[#Headers]))),IF(INDEX(tbl_WR_AdditionalActions[Vulnerability Evidence Count],ROW()-ROW(tbl_WR_EligibilitySummary[#Headers])-ROWS(tbl_WR_Assessment[ActionID]))=0,"",INDEX(tbl_WR_AdditionalActions[Vulnerability Evidence Count],ROW()-ROW(tbl_WR_EligibilitySummary[#Headers])-ROWS(tbl_WR_Assessment[ActionID]))))} -> 3 | G13: {=IF(tbl_WR_EligibilitySummary[[#This Row],[Vulnerability Eligibility]]="Eligible",IF(ROW()-ROW(tbl_WR_EligibilitySummary[#Headers])<=ROWS(tbl_WR_Assessment[ActionID]),INDEX(tbl_WR_Assessment[Effectiveness on Vulnerability],ROW()-ROW(tbl_WR_EligibilitySummary[#Headers])),INDEX(tbl_WR_AdditionalActions[Effectiveness on Vulnerability],ROW()-ROW(tbl_WR_EligibilitySummary[#Headers])-ROWS(tbl_WR_Assessment[ActionID]))),IF(tbl_WR_EligibilitySummary[[#This Row],[Vulnerability Eligibility]]="Review required","Review required",IF(tbl_WR_EligibilitySummary[[#This Row],[Vulnerability Eligibility]]="Not eligible","N/A","")))} -> Medium effectiveness | H13: {=IF(ROW()-ROW(tbl_WR_EligibilitySummary[#Headers])<=ROWS(tbl_WR_Assessment[ActionID]),INDEX(tbl_WR_Assessment[Exposure Eligibility],ROW()-ROW(tbl_WR_EligibilitySummary[#Headers])),INDEX(tbl_WR_AdditionalActions[Exposure Eligibility],ROW()-ROW(tbl_WR_EligibilitySummary[#Headers])-ROWS(tbl_WR_Assessment[ActionID])))} -> Not eligible | I13: {=IF(ROW()-ROW(tbl_WR_EligibilitySummary[#Headers])<=ROWS(tbl_WR_Assessment[ActionID]),IF(INDEX(tbl_WR_Assessment[Exposure Evidence Count],ROW()-ROW(tbl_WR_EligibilitySummary[#Headers]))=0,"",INDEX(tbl_WR_Assessment[Exposure Evidence Count],ROW()-ROW(tbl_WR_EligibilitySummary[#Headers]))),IF(INDEX(tbl_WR_AdditionalActions[Exposure Evidence Count],ROW()-ROW(tbl_WR_EligibilitySummary[#Headers])-ROWS(tbl_WR_Assessment[ActionID]))=0,"",INDEX(tbl_WR_AdditionalActions[Exposure Evidence Count],ROW()-ROW(tbl_WR_EligibilitySummary[#Headers])-ROWS(tbl_WR_Assessment[ActionID]))))} | J13: {=IF(tbl_WR_EligibilitySummary[[#This Row],[Exposure Eligibility]]="Eligible",IF(ROW()-ROW(tbl_WR_EligibilitySummary[#Headers])<=ROWS(tbl_WR_Assessment[ActionID]),INDEX(tbl_WR_Assessment[Effectiveness on Exposure],ROW()-ROW(tbl_WR_EligibilitySummary[#Headers])),INDEX(tbl_WR_AdditionalActions[Effectiveness on Exposure],ROW()-ROW(tbl_WR_EligibilitySummary[#Headers])-ROWS(tbl_WR_Assessment[ActionID]))),IF(tbl_WR_EligibilitySummary[[#This Row],[Exposure Eligibility]]="Review required","Review required",IF(tbl_WR_EligibilitySummary[[#This Row],[Exposure Eligibility]]="Not eligible","N/A","")))} -> N/A | K13: {=IF(ROW()-ROW(tbl_WR_EligibilitySummary[#Headers])<=ROWS(tbl_WR_Assessment[ActionID]),INDEX(tbl_WR_Assessment[ReviewStatus],ROW()-ROW(tbl_WR_EligibilitySummary[#Headers])),INDEX(tbl_WR_AdditionalActions[ReviewStatus],ROW()-ROW(tbl_WR_EligibilitySummary[#Headers])-ROWS(tbl_WR_Assessment[ActionID])))} -> Evidence added
B14: {=IF(ROW()-ROW(tbl_WR_EligibilitySummary[#Headers])<=ROWS(tbl_WR_Assessment[ActionID]),"Existing action","Additional action")} -> Existing action | C14: {=IF(ROW()-ROW(tbl_WR_EligibilitySummary[#Headers])<=ROWS(tbl_WR_Assessment[ActionID]),INDEX(tbl_WR_Assessment[ActionID],ROW()-ROW(tbl_WR_EligibilitySummary[#Headers])),INDEX(tbl_WR_AdditionalActions[AdditionalActionID],ROW()-ROW(tbl_WR_EligibilitySummary[#Headers])-ROWS(tbl_WR_Assessment[ActionID])))} -> c40_0056 | D14: {=IF(ROW()-ROW(tbl_WR_EligibilitySummary[#Headers])<=ROWS(tbl_WR_Assessment[ActionID]),INDEX(tbl_WR_Assessment[ActionName],ROW()-ROW(tbl_WR_EligibilitySummary[#Headers])),INDEX(tbl_WR_AdditionalActions[ActionName],ROW()-ROW(tbl_WR_EligibilitySummary[#Headers])-ROWS(tbl_WR_Assessment[ActionID])))} -> Improve Watershed Protection and Management | E14: {=IF(ROW()-ROW(tbl_WR_EligibilitySummary[#Headers])<=ROWS(tbl_WR_Assessment[ActionID]),INDEX(tbl_WR_Assessment[Vulnerability Eligibility],ROW()-ROW(tbl_WR_EligibilitySummary[#Headers])),INDEX(tbl_WR_AdditionalActions[Vulnerability Eligibility],ROW()-ROW(tbl_WR_EligibilitySummary[#Headers])-ROWS(tbl_WR_Assessment[ActionID])))} -> Eligible | F14: {=IF(ROW()-ROW(tbl_WR_EligibilitySummary[#Headers])<=ROWS(tbl_WR_Assessment[ActionID]),IF(INDEX(tbl_WR_Assessment[Vulnerability Evidence Count],ROW()-ROW(tbl_WR_EligibilitySummary[#Headers]))=0,"",INDEX(tbl_WR_Assessment[Vulnerability Evidence Count],ROW()-ROW(tbl_WR_EligibilitySummary[#Headers]))),IF(INDEX(tbl_WR_AdditionalActions[Vulnerability Evidence Count],ROW()-ROW(tbl_WR_EligibilitySummary[#Headers])-ROWS(tbl_WR_Assessment[ActionID]))=0,"",INDEX(tbl_WR_AdditionalActions[Vulnerability Evidence Count],ROW()-ROW(tbl_WR_EligibilitySummary[#Headers])-ROWS(tbl_WR_Assessment[ActionID]))))} -> 3 | G14: {=IF(tbl_WR_EligibilitySummary[[#This Row],[Vulnerability Eligibility]]="Eligible",IF(ROW()-ROW(tbl_WR_EligibilitySummary[#Headers])<=ROWS(tbl_WR_Assessment[ActionID]),INDEX(tbl_WR_Assessment[Effectiveness on Vulnerability],ROW()-ROW(tbl_WR_EligibilitySummary[#Headers])),INDEX(tbl_WR_AdditionalActions[Effectiveness on Vulnerability],ROW()-ROW(tbl_WR_EligibilitySummary[#Headers])-ROWS(tbl_WR_Assessment[ActionID]))),IF(tbl_WR_EligibilitySummary[[#This Row],[Vulnerability Eligibility]]="Review required","Review required",IF(tbl_WR_EligibilitySummary[[#This Row],[Vulnerability Eligibility]]="Not eligible","N/A","")))} -> High effectiveness | H14: {=IF(ROW()-ROW(tbl_WR_EligibilitySummary[#Headers])<=ROWS(tbl_WR_Assessment[ActionID]),INDEX(tbl_WR_Assessment[Exposure Eligibility],ROW()-ROW(tbl_WR_EligibilitySummary[#Headers])),INDEX(tbl_WR_AdditionalActions[Exposure Eligibility],ROW()-ROW(tbl_WR_EligibilitySummary[#Headers])-ROWS(tbl_WR_Assessment[ActionID])))} -> Not eligible | I14: {=IF(ROW()-ROW(tbl_WR_EligibilitySummary[#Headers])<=ROWS(tbl_WR_Assessment[ActionID]),IF(INDEX(tbl_WR_Assessment[Exposure Evidence Count],ROW()-ROW(tbl_WR_EligibilitySummary[#Headers]))=0,"",INDEX(tbl_WR_Assessment[Exposure Evidence Count],ROW()-ROW(tbl_WR_EligibilitySummary[#Headers]))),IF(INDEX(tbl_WR_AdditionalActions[Exposure Evidence Count],ROW()-ROW(tbl_WR_EligibilitySummary[#Headers])-ROWS(tbl_WR_Assessment[ActionID]))=0,"",INDEX(tbl_WR_AdditionalActions[Exposure Evidence Count],ROW()-ROW(tbl_WR_EligibilitySummary[#Headers])-ROWS(tbl_WR_Assessment[ActionID]))))} | J14: {=IF(tbl_WR_EligibilitySummary[[#This Row],[Exposure Eligibility]]="Eligible",IF(ROW()-ROW(tbl_WR_EligibilitySummary[#Headers])<=ROWS(tbl_WR_Assessment[ActionID]),INDEX(tbl_WR_Assessment[Effectiveness on Exposure],ROW()-ROW(tbl_WR_EligibilitySummary[#Headers])),INDEX(tbl_WR_AdditionalActions[Effectiveness on Exposure],ROW()-ROW(tbl_WR_EligibilitySummary[#Headers])-ROWS(tbl_WR_Assessment[ActionID]))),IF(tbl_WR_EligibilitySummary[[#This Row],[Exposure Eligibility]]="Review required","Review required",IF(tbl_WR_EligibilitySummary[[#This Row],[Exposure Eligibility]]="Not eligible","N/A","")))} -> N/A | K14: {=IF(ROW()-ROW(tbl_WR_EligibilitySummary[#Headers])<=ROWS(tbl_WR_Assessment[ActionID]),INDEX(tbl_WR_Assessment[ReviewStatus],ROW()-ROW(tbl_WR_EligibilitySummary[#Headers])),INDEX(tbl_WR_AdditionalActions[ReviewStatus],ROW()-ROW(tbl_WR_EligibilitySummary[#Headers])-ROWS(tbl_WR_Assessment[ActionID])))} -> Evidence added
B15: {=IF(ROW()-ROW(tbl_WR_EligibilitySummary[#Headers])<=ROWS(tbl_WR_Assessment[ActionID]),"Existing action","Additional action")} -> Existing action | C15: {=IF(ROW()-ROW(tbl_WR_EligibilitySummary[#Headers])<=ROWS(tbl_WR_Assessment[ActionID]),INDEX(tbl_WR_Assessment[ActionID],ROW()-ROW(tbl_WR_EligibilitySummary[#Headers])),INDEX(tbl_WR_AdditionalActions[AdditionalActionID],ROW()-ROW(tbl_WR_EligibilitySummary[#Headers])-ROWS(tbl_WR_Assessment[ActionID])))} -> c40_0062 | D15: {=IF(ROW()-ROW(tbl_WR_EligibilitySummary[#Headers])<=ROWS(tbl_WR_Assessment[ActionID]),INDEX(tbl_WR_Assessment[ActionName],ROW()-ROW(tbl_WR_EligibilitySummary[#Headers])),INDEX(tbl_WR_AdditionalActions[ActionName],ROW()-ROW(tbl_WR_EligibilitySummary[#Headers])-ROWS(tbl_WR_Assessment[ActionID])))} -> Reform water tariffs to support efficiency and equity | E15: {=IF(ROW()-ROW(tbl_WR_EligibilitySummary[#Headers])<=ROWS(tbl_WR_Assessment[ActionID]),INDEX(tbl_WR_Assessment[Vulnerability Eligibility],ROW()-ROW(tbl_WR_EligibilitySummary[#Headers])),INDEX(tbl_WR_AdditionalActions[Vulnerability Eligibility],ROW()-ROW(tbl_WR_EligibilitySummary[#Headers])-ROWS(tbl_WR_Assessment[ActionID])))} -> Eligible | F15: {=IF(ROW()-ROW(tbl_WR_EligibilitySummary[#Headers])<=ROWS(tbl_WR_Assessment[ActionID]),IF(INDEX(tbl_WR_Assessment[Vulnerability Evidence Count],ROW()-ROW(tbl_WR_EligibilitySummary[#Headers]))=0,"",INDEX(tbl_WR_Assessment[Vulnerability Evidence Count],ROW()-ROW(tbl_WR_EligibilitySummary[#Headers]))),IF(INDEX(tbl_WR_AdditionalActions[Vulnerability Evidence Count],ROW()-ROW(tbl_WR_EligibilitySummary[#Headers])-ROWS(tbl_WR_Assessment[ActionID]))=0,"",INDEX(tbl_WR_AdditionalActions[Vulnerability Evidence Count],ROW()-ROW(tbl_WR_EligibilitySummary[#Headers])-ROWS(tbl_WR_Assessment[ActionID]))))} -> 3 | G15: {=IF(tbl_WR_EligibilitySummary[[#This Row],[Vulnerability Eligibility]]="Eligible",IF(ROW()-ROW(tbl_WR_EligibilitySummary[#Headers])<=ROWS(tbl_WR_Assessment[ActionID]),INDEX(tbl_WR_Assessment[Effectiveness on Vulnerability],ROW()-ROW(tbl_WR_EligibilitySummary[#Headers])),INDEX(tbl_WR_AdditionalActions[Effectiveness on Vulnerability],ROW()-ROW(tbl_WR_EligibilitySummary[#Headers])-ROWS(tbl_WR_Assessment[ActionID]))),IF(tbl_WR_EligibilitySummary[[#This Row],[Vulnerability Eligibility]]="Review required","Review required",IF(tbl_WR_EligibilitySummary[[#This Row],[Vulnerability Eligibility]]="Not eligible","N/A","")))} -> Medium effectiveness | H15: {=IF(ROW()-ROW(tbl_WR_EligibilitySummary[#Headers])<=ROWS(tbl_WR_Assessment[ActionID]),INDEX(tbl_WR_Assessment[Exposure Eligibility],ROW()-ROW(tbl_WR_EligibilitySummary[#Headers])),INDEX(tbl_WR_AdditionalActions[Exposure Eligibility],ROW()-ROW(tbl_WR_EligibilitySummary[#Headers])-ROWS(tbl_WR_Assessment[ActionID])))} -> Not eligible | I15: {=IF(ROW()-ROW(tbl_WR_EligibilitySummary[#Headers])<=ROWS(tbl_WR_Assessment[ActionID]),IF(INDEX(tbl_WR_Assessment[Exposure Evidence Count],ROW()-ROW(tbl_WR_EligibilitySummary[#Headers]))=0,"",INDEX(tbl_WR_Assessment[Exposure Evidence Count],ROW()-ROW(tbl_WR_EligibilitySummary[#Headers]))),IF(INDEX(tbl_WR_AdditionalActions[Exposure Evidence Count],ROW()-ROW(tbl_WR_EligibilitySummary[#Headers])-ROWS(tbl_WR_Assessment[ActionID]))=0,"",INDEX(tbl_WR_AdditionalActions[Exposure Evidence Count],ROW()-ROW(tbl_WR_EligibilitySummary[#Headers])-ROWS(tbl_WR_Assessment[ActionID]))))} | J15: {=IF(tbl_WR_EligibilitySummary[[#This Row],[Exposure Eligibility]]="Eligible",IF(ROW()-ROW(tbl_WR_EligibilitySummary[#Headers])<=ROWS(tbl_WR_Assessment[ActionID]),INDEX(tbl_WR_Assessment[Effectiveness on Exposure],ROW()-ROW(tbl_WR_EligibilitySummary[#Headers])),INDEX(tbl_WR_AdditionalActions[Effectiveness on Exposure],ROW()-ROW(tbl_WR_EligibilitySummary[#Headers])-ROWS(tbl_WR_Assessment[ActionID]))),IF(tbl_WR_EligibilitySummary[[#This Row],[Exposure Eligibility]]="Review required","Review required",IF(tbl_WR_EligibilitySummary[[#This Row],[Exposure Eligibility]]="Not eligible","N/A","")))} -> N/A | K15: {=IF(ROW()-ROW(tbl_WR_EligibilitySummary[#Headers])<=ROWS(tbl_WR_Assessment[ActionID]),INDEX(tbl_WR_Assessment[ReviewStatus],ROW()-ROW(tbl_WR_EligibilitySummary[#Headers])),INDEX(tbl_WR_AdditionalActions[ReviewStatus],ROW()-ROW(tbl_WR_EligibilitySummary[#Headers])-ROWS(tbl_WR_Assessment[ActionID])))} -> Evidence added
B16: {=IF(ROW()-ROW(tbl_WR_EligibilitySummary[#Headers])<=ROWS(tbl_WR_Assessment[ActionID]),"Existing action","Additional action")} -> Existing action | C16: {=IF(ROW()-ROW(tbl_WR_EligibilitySummary[#Headers])<=ROWS(tbl_WR_Assessment[ActionID]),INDEX(tbl_WR_Assessment[ActionID],ROW()-ROW(tbl_WR_EligibilitySummary[#Headers])),INDEX(tbl_WR_AdditionalActions[AdditionalActionID],ROW()-ROW(tbl_WR_EligibilitySummary[#Headers])-ROWS(tbl_WR_Assessment[ActionID])))} -> icare_0144 | D16: {=IF(ROW()-ROW(tbl_WR_EligibilitySummary[#Headers])<=ROWS(tbl_WR_Assessment[ActionID]),INDEX(tbl_WR_Assessment[ActionName],ROW()-ROW(tbl_WR_EligibilitySummary[#Headers])),INDEX(tbl_WR_AdditionalActions[ActionName],ROW()-ROW(tbl_WR_EligibilitySummary[#Headers])-ROWS(tbl_WR_Assessment[ActionID])))} -> Establish a financial support program for extreme weather events | E16: {=IF(ROW()-ROW(tbl_WR_EligibilitySummary[#Headers])<=ROWS(tbl_WR_Assessment[ActionID]),INDEX(tbl_WR_Assessment[Vulnerability Eligibility],ROW()-ROW(tbl_WR_EligibilitySummary[#Headers])),INDEX(tbl_WR_AdditionalActions[Vulnerability Eligibility],ROW()-ROW(tbl_WR_EligibilitySummary[#Headers])-ROWS(tbl_WR_Assessment[ActionID])))} -> Not eligible | F16: {=IF(ROW()-ROW(tbl_WR_EligibilitySummary[#Headers])<=ROWS(tbl_WR_Assessment[ActionID]),IF(INDEX(tbl_WR_Assessment[Vulnerability Evidence Count],ROW()-ROW(tbl_WR_EligibilitySummary[#Headers]))=0,"",INDEX(tbl_WR_Assessment[Vulnerability Evidence Count],ROW()-ROW(tbl_WR_EligibilitySummary[#Headers]))),IF(INDEX(tbl_WR_AdditionalActions[Vulnerability Evidence Count],ROW()-ROW(tbl_WR_EligibilitySummary[#Headers])-ROWS(tbl_WR_Assessment[ActionID]))=0,"",INDEX(tbl_WR_AdditionalActions[Vulnerability Evidence Count],ROW()-ROW(tbl_WR_EligibilitySummary[#Headers])-ROWS(tbl_WR_Assessment[ActionID]))))} | G16: {=IF(tbl_WR_EligibilitySummary[[#This Row],[Vulnerability Eligibility]]="Eligible",IF(ROW()-ROW(tbl_WR_EligibilitySummary[#Headers])<=ROWS(tbl_WR_Assessment[ActionID]),INDEX(tbl_WR_Assessment[Effectiveness on Vulnerability],ROW()-ROW(tbl_WR_EligibilitySummary[#Headers])),INDEX(tbl_WR_AdditionalActions[Effectiveness on Vulnerability],ROW()-ROW(tbl_WR_EligibilitySummary[#Headers])-ROWS(tbl_WR_Assessment[ActionID]))),IF(tbl_WR_EligibilitySummary[[#This Row],[Vulnerability Eligibility]]="Review required","Review required",IF(tbl_WR_EligibilitySummary[[#This Row],[Vulnerability Eligibility]]="Not eligible","N/A","")))} -> N/A | H16: {=IF(ROW()-ROW(tbl_WR_EligibilitySummary[#Headers])<=ROWS(tbl_WR_Assessment[ActionID]),INDEX(tbl_WR_Assessment[Exposure Eligibility],ROW()-ROW(tbl_WR_EligibilitySummary[#Headers])),INDEX(tbl_WR_AdditionalActions[Exposure Eligibility],ROW()-ROW(tbl_WR_EligibilitySummary[#Headers])-ROWS(tbl_WR_Assessment[ActionID])))} -> Not eligible | I16: {=IF(ROW()-ROW(tbl_WR_EligibilitySummary[#Headers])<=ROWS(tbl_WR_Assessment[ActionID]),IF(INDEX(tbl_WR_Assessment[Exposure Evidence Count],ROW()-ROW(tbl_WR_EligibilitySummary[#Headers]))=0,"",INDEX(tbl_WR_Assessment[Exposure Evidence Count],ROW()-ROW(tbl_WR_EligibilitySummary[#Headers]))),IF(INDEX(tbl_WR_AdditionalActions[Exposure Evidence Count],ROW()-ROW(tbl_WR_EligibilitySummary[#Headers])-ROWS(tbl_WR_Assessment[ActionID]))=0,"",INDEX(tbl_WR_AdditionalActions[Exposure Evidence Count],ROW()-ROW(tbl_WR_EligibilitySummary[#Headers])-ROWS(tbl_WR_Assessment[ActionID]))))} | J16: {=IF(tbl_WR_EligibilitySummary[[#This Row],[Exposure Eligibility]]="Eligible",IF(ROW()-ROW(tbl_WR_EligibilitySummary[#Headers])<=ROWS(tbl_WR_Assessment[ActionID]),INDEX(tbl_WR_Assessment[Effectiveness on Exposure],ROW()-ROW(tbl_WR_EligibilitySummary[#Headers])),INDEX(tbl_WR_AdditionalActions[Effectiveness on Exposure],ROW()-ROW(tbl_WR_EligibilitySummary[#Headers])-ROWS(tbl_WR_Assessment[ActionID]))),IF(tbl_WR_EligibilitySummary[[#This Row],[Exposure Eligibility]]="Review required","Review required",IF(tbl_WR_EligibilitySummary[[#This Row],[Exposure Eligibility]]="Not eligible","N/A","")))} -> N/A | K16: {=IF(ROW()-ROW(tbl_WR_EligibilitySummary[#Headers])<=ROWS(tbl_WR_Assessment[ActionID]),INDEX(tbl_WR_Assessment[ReviewStatus],ROW()-ROW(tbl_WR_EligibilitySummary[#Headers])),INDEX(tbl_WR_AdditionalActions[ReviewStatus],ROW()-ROW(tbl_WR_EligibilitySummary[#Headers])-ROWS(tbl_WR_Assessment[ActionID])))} -> Not assessed
B17: {=IF(ROW()-ROW(tbl_WR_EligibilitySummary[#Headers])<=ROWS(tbl_WR_Assessment[ActionID]),"Existing action","Additional action")} -> Existing action | C17: {=IF(ROW()-ROW(tbl_WR_EligibilitySummary[#Headers])<=ROWS(tbl_WR_Assessment[ActionID]),INDEX(tbl_WR_Assessment[ActionID],ROW()-ROW(tbl_WR_EligibilitySummary[#Headers])),INDEX(tbl_WR_AdditionalActions[AdditionalActionID],ROW()-ROW(tbl_WR_EligibilitySummary[#Headers])-ROWS(tbl_WR_Assessment[ActionID])))} -> icare_0145 | D17: {=IF(ROW()-ROW(tbl_WR_EligibilitySummary[#Headers])<=ROWS(tbl_WR_Assessment[ActionID]),INDEX(tbl_WR_Assessment[ActionName],ROW()-ROW(tbl_WR_EligibilitySummary[#Headers])),INDEX(tbl_WR_AdditionalActions[ActionName],ROW()-ROW(tbl_WR_EligibilitySummary[#Headers])-ROWS(tbl_WR_Assessment[ActionID])))} -> Strengthen the healthcare system to respond effectively to extreme events | E17: {=IF(ROW()-ROW(tbl_WR_EligibilitySummary[#Headers])<=ROWS(tbl_WR_Assessment[ActionID]),INDEX(tbl_WR_Assessment[Vulnerability Eligibility],ROW()-ROW(tbl_WR_EligibilitySummary[#Headers])),INDEX(tbl_WR_AdditionalActions[Vulnerability Eligibility],ROW()-ROW(tbl_WR_EligibilitySummary[#Headers])-ROWS(tbl_WR_Assessment[ActionID])))} -> Not eligible | F17: {=IF(ROW()-ROW(tbl_WR_EligibilitySummary[#Headers])<=ROWS(tbl_WR_Assessment[ActionID]),IF(INDEX(tbl_WR_Assessment[Vulnerability Evidence Count],ROW()-ROW(tbl_WR_EligibilitySummary[#Headers]))=0,"",INDEX(tbl_WR_Assessment[Vulnerability Evidence Count],ROW()-ROW(tbl_WR_EligibilitySummary[#Headers]))),IF(INDEX(tbl_WR_AdditionalActions[Vulnerability Evidence Count],ROW()-ROW(tbl_WR_EligibilitySummary[#Headers])-ROWS(tbl_WR_Assessment[ActionID]))=0,"",INDEX(tbl_WR_AdditionalActions[Vulnerability Evidence Count],ROW()-ROW(tbl_WR_EligibilitySummary[#Headers])-ROWS(tbl_WR_Assessment[ActionID]))))} | G17: {=IF(tbl_WR_EligibilitySummary[[#This Row],[Vulnerability Eligibility]]="Eligible",IF(ROW()-ROW(tbl_WR_EligibilitySummary[#Headers])<=ROWS(tbl_WR_Assessment[ActionID]),INDEX(tbl_WR_Assessment[Effectiveness on Vulnerability],ROW()-ROW(tbl_WR_EligibilitySummary[#Headers])),INDEX(tbl_WR_AdditionalActions[Effectiveness on Vulnerability],ROW()-ROW(tbl_WR_EligibilitySummary[#Headers])-ROWS(tbl_WR_Assessment[ActionID]))),IF(tbl_WR_EligibilitySummary[[#This Row],[Vulnerability Eligibility]]="Review required","Review required",IF(tbl_WR_EligibilitySummary[[#This Row],[Vulnerability Eligibility]]="Not eligible","N/A","")))} -> N/A | H17: {=IF(ROW()-ROW(tbl_WR_EligibilitySummary[#Headers])<=ROWS(tbl_WR_Assessment[ActionID]),INDEX(tbl_WR_Assessment[Exposure Eligibility],ROW()-ROW(tbl_WR_EligibilitySummary[#Headers])),INDEX(tbl_WR_AdditionalActions[Exposure Eligibility],ROW()-ROW(tbl_WR_EligibilitySummary[#Headers])-ROWS(tbl_WR_Assessment[ActionID])))} -> Not eligible | I17: {=IF(ROW()-ROW(tbl_WR_EligibilitySummary[#Headers])<=ROWS(tbl_WR_Assessment[ActionID]),IF(INDEX(tbl_WR_Assessment[Exposure Evidence Count],ROW()-ROW(tbl_WR_EligibilitySummary[#Headers]))=0,"",INDEX(tbl_WR_Assessment[Exposure Evidence Count],ROW()-ROW(tbl_WR_EligibilitySummary[#Headers]))),IF(INDEX(tbl_WR_AdditionalActions[Exposure Evidence Count],ROW()-ROW(tbl_WR_EligibilitySummary[#Headers])-ROWS(tbl_WR_Assessment[ActionID]))=0,"",INDEX(tbl_WR_AdditionalActions[Exposure Evidence Count],ROW()-ROW(tbl_WR_EligibilitySummary[#Headers])-ROWS(tbl_WR_Assessment[ActionID]))))} | J17: {=IF(tbl_WR_EligibilitySummary[[#This Row],[Exposure Eligibility]]="Eligible",IF(ROW()-ROW(tbl_WR_EligibilitySummary[#Headers])<=ROWS(tbl_WR_Assessment[ActionID]),INDEX(tbl_WR_Assessment[Effectiveness on Exposure],ROW()-ROW(tbl_WR_EligibilitySummary[#Headers])),INDEX(tbl_WR_AdditionalActions[Effectiveness on Exposure],ROW()-ROW(tbl_WR_EligibilitySummary[#Headers])-ROWS(tbl_WR_Assessment[ActionID]))),IF(tbl_WR_EligibilitySummary[[#This Row],[Exposure Eligibility]]="Review required","Review required",IF(tbl_WR_EligibilitySummary[[#This Row],[Exposure Eligibility]]="Not eligible","N/A","")))} -> N/A | K17: {=IF(ROW()-ROW(tbl_WR_EligibilitySummary[#Headers])<=ROWS(tbl_WR_Assessment[ActionID]),INDEX(tbl_WR_Assessment[ReviewStatus],ROW()-ROW(tbl_WR_EligibilitySummary[#Headers])),INDEX(tbl_WR_AdditionalActions[ReviewStatus],ROW()-ROW(tbl_WR_EligibilitySummary[#Headers])-ROWS(tbl_WR_Assessment[ActionID])))} -> Not assessed
B18: {=IF(ROW()-ROW(tbl_WR_EligibilitySummary[#Headers])<=ROWS(tbl_WR_Assessment[ActionID]),"Existing action","Additional action")} -> Existing action | C18: {=IF(ROW()-ROW(tbl_WR_EligibilitySummary[#Headers])<=ROWS(tbl_WR_Assessment[ActionID]),INDEX(tbl_WR_Assessment[ActionID],ROW()-ROW(tbl_WR_EligibilitySummary[#Headers])),INDEX(tbl_WR_AdditionalActions[AdditionalActionID],ROW()-ROW(tbl_WR_EligibilitySummary[#Headers])-ROWS(tbl_WR_Assessment[ActionID])))} -> icare_0154 | D18: {=IF(ROW()-ROW(tbl_WR_EligibilitySummary[#Headers])<=ROWS(tbl_WR_Assessment[ActionID]),INDEX(tbl_WR_Assessment[ActionName],ROW()-ROW(tbl_WR_EligibilitySummary[#Headers])),INDEX(tbl_WR_AdditionalActions[ActionName],ROW()-ROW(tbl_WR_EligibilitySummary[#Headers])-ROWS(tbl_WR_Assessment[ActionID])))} -> Clean and unclog drainage channels and install eco-barriers | E18: {=IF(ROW()-ROW(tbl_WR_EligibilitySummary[#Headers])<=ROWS(tbl_WR_Assessment[ActionID]),INDEX(tbl_WR_Assessment[Vulnerability Eligibility],ROW()-ROW(tbl_WR_EligibilitySummary[#Headers])),INDEX(tbl_WR_AdditionalActions[Vulnerability Eligibility],ROW()-ROW(tbl_WR_EligibilitySummary[#Headers])-ROWS(tbl_WR_Assessment[ActionID])))} -> Not eligible | F18: {=IF(ROW()-ROW(tbl_WR_EligibilitySummary[#Headers])<=ROWS(tbl_WR_Assessment[ActionID]),IF(INDEX(tbl_WR_Assessment[Vulnerability Evidence Count],ROW()-ROW(tbl_WR_EligibilitySummary[#Headers]))=0,"",INDEX(tbl_WR_Assessment[Vulnerability Evidence Count],ROW()-ROW(tbl_WR_EligibilitySummary[#Headers]))),IF(INDEX(tbl_WR_AdditionalActions[Vulnerability Evidence Count],ROW()-ROW(tbl_WR_EligibilitySummary[#Headers])-ROWS(tbl_WR_Assessment[ActionID]))=0,"",INDEX(tbl_WR_AdditionalActions[Vulnerability Evidence Count],ROW()-ROW(tbl_WR_EligibilitySummary[#Headers])-ROWS(tbl_WR_Assessment[ActionID]))))} | G18: {=IF(tbl_WR_EligibilitySummary[[#This Row],[Vulnerability Eligibility]]="Eligible",IF(ROW()-ROW(tbl_WR_EligibilitySummary[#Headers])<=ROWS(tbl_WR_Assessment[ActionID]),INDEX(tbl_WR_Assessment[Effectiveness on Vulnerability],ROW()-ROW(tbl_WR_EligibilitySummary[#Headers])),INDEX(tbl_WR_AdditionalActions[Effectiveness on Vulnerability],ROW()-ROW(tbl_WR_EligibilitySummary[#Headers])-ROWS(tbl_WR_Assessment[ActionID]))),IF(tbl_WR_EligibilitySummary[[#This Row],[Vulnerability Eligibility]]="Review required","Review required",IF(tbl_WR_EligibilitySummary[[#This Row],[Vulnerability Eligibility]]="Not eligible","N/A","")))} -> N/A | H18: {=IF(ROW()-ROW(tbl_WR_EligibilitySummary[#Headers])<=ROWS(tbl_WR_Assessment[ActionID]),INDEX(tbl_WR_Assessment[Exposure Eligibility],ROW()-ROW(tbl_WR_EligibilitySummary[#Headers])),INDEX(tbl_WR_AdditionalActions[Exposure Eligibility],ROW()-ROW(tbl_WR_EligibilitySummary[#Headers])-ROWS(tbl_WR_Assessment[ActionID])))} -> Not eligible | I18: {=IF(ROW()-ROW(tbl_WR_EligibilitySummary[#Headers])<=ROWS(tbl_WR_Assessment[ActionID]),IF(INDEX(tbl_WR_Assessment[Exposure Evidence Count],ROW()-ROW(tbl_WR_EligibilitySummary[#Headers]))=0,"",INDEX(tbl_WR_Assessment[Exposure Evidence Count],ROW()-ROW(tbl_WR_EligibilitySummary[#Headers]))),IF(INDEX(tbl_WR_AdditionalActions[Exposure Evidence Count],ROW()-ROW(tbl_WR_EligibilitySummary[#Headers])-ROWS(tbl_WR_Assessment[ActionID]))=0,"",INDEX(tbl_WR_AdditionalActions[Exposure Evidence Count],ROW()-ROW(tbl_WR_EligibilitySummary[#Headers])-ROWS(tbl_WR_Assessment[ActionID]))))} | J18: {=IF(tbl_WR_EligibilitySummary[[#This Row],[Exposure Eligibility]]="Eligible",IF(ROW()-ROW(tbl_WR_EligibilitySummary[#Headers])<=ROWS(tbl_WR_Assessment[ActionID]),INDEX(tbl_WR_Assessment[Effectiveness on Exposure],ROW()-ROW(tbl_WR_EligibilitySummary[#Headers])),INDEX(tbl_WR_AdditionalActions[Effectiveness on Exposure],ROW()-ROW(tbl_WR_EligibilitySummary[#Headers])-ROWS(tbl_WR_Assessment[ActionID]))),IF(tbl_WR_EligibilitySummary[[#This Row],[Exposure Eligibility]]="Review required","Review required",IF(tbl_WR_EligibilitySummary[[#This Row],[Exposure Eligibility]]="Not eligible","N/A","")))} -> N/A | K18: {=IF(ROW()-ROW(tbl_WR_EligibilitySummary[#Headers])<=ROWS(tbl_WR_Assessment[ActionID]),INDEX(tbl_WR_Assessment[ReviewStatus],ROW()-ROW(tbl_WR_EligibilitySummary[#Headers])),INDEX(tbl_WR_AdditionalActions[ReviewStatus],ROW()-ROW(tbl_WR_EligibilitySummary[#Headers])-ROWS(tbl_WR_Assessment[ActionID])))} -> Not assessed
B19: {=IF(ROW()-ROW(tbl_WR_EligibilitySummary[#Headers])<=ROWS(tbl_WR_Assessment[ActionID]),"Existing action","Additional action")} -> Existing action | C19: {=IF(ROW()-ROW(tbl_WR_EligibilitySummary[#Headers])<=ROWS(tbl_WR_Assessment[ActionID]),INDEX(tbl_WR_Assessment[ActionID],ROW()-ROW(tbl_WR_EligibilitySummary[#Headers])),INDEX(tbl_WR_AdditionalActions[AdditionalActionID],ROW()-ROW(tbl_WR_EligibilitySummary[#Headers])-ROWS(tbl_WR_Assessment[ActionID])))} -> icare_0156 | D19: {=IF(ROW()-ROW(tbl_WR_EligibilitySummary[#Headers])<=ROWS(tbl_WR_Assessment[ActionID]),INDEX(tbl_WR_Assessment[ActionName],ROW()-ROW(tbl_WR_EligibilitySummary[#Headers])),INDEX(tbl_WR_AdditionalActions[ActionName],ROW()-ROW(tbl_WR_EligibilitySummary[#Headers])-ROWS(tbl_WR_Assessment[ActionID])))} -> Improve Implementation of urban gardens | E19: {=IF(ROW()-ROW(tbl_WR_EligibilitySummary[#Headers])<=ROWS(tbl_WR_Assessment[ActionID]),INDEX(tbl_WR_Assessment[Vulnerability Eligibility],ROW()-ROW(tbl_WR_EligibilitySummary[#Headers])),INDEX(tbl_WR_AdditionalActions[Vulnerability Eligibility],ROW()-ROW(tbl_WR_EligibilitySummary[#Headers])-ROWS(tbl_WR_Assessment[ActionID])))} -> Not eligible | F19: {=IF(ROW()-ROW(tbl_WR_EligibilitySummary[#Headers])<=ROWS(tbl_WR_Assessment[ActionID]),IF(INDEX(tbl_WR_Assessment[Vulnerability Evidence Count],ROW()-ROW(tbl_WR_EligibilitySummary[#Headers]))=0,"",INDEX(tbl_WR_Assessment[Vulnerability Evidence Count],ROW()-ROW(tbl_WR_EligibilitySummary[#Headers]))),IF(INDEX(tbl_WR_AdditionalActions[Vulnerability Evidence Count],ROW()-ROW(tbl_WR_EligibilitySummary[#Headers])-ROWS(tbl_WR_Assessment[ActionID]))=0,"",INDEX(tbl_WR_AdditionalActions[Vulnerability Evidence Count],ROW()-ROW(tbl_WR_EligibilitySummary[#Headers])-ROWS(tbl_WR_Assessment[ActionID]))))} | G19: {=IF(tbl_WR_EligibilitySummary[[#This Row],[Vulnerability Eligibility]]="Eligible",IF(ROW()-ROW(tbl_WR_EligibilitySummary[#Headers])<=ROWS(tbl_WR_Assessment[ActionID]),INDEX(tbl_WR_Assessment[Effectiveness on Vulnerability],ROW()-ROW(tbl_WR_EligibilitySummary[#Headers])),INDEX(tbl_WR_AdditionalActions[Effectiveness on Vulnerability],ROW()-ROW(tbl_WR_EligibilitySummary[#Headers])-ROWS(tbl_WR_Assessment[ActionID]))),IF(tbl_WR_EligibilitySummary[[#This Row],[Vulnerability Eligibility]]="Review required","Review required",IF(tbl_WR_EligibilitySummary[[#This Row],[Vulnerability Eligibility]]="Not eligible","N/A","")))} -> N/A | H19: {=IF(ROW()-ROW(tbl_WR_EligibilitySummary[#Headers])<=ROWS(tbl_WR_Assessment[ActionID]),INDEX(tbl_WR_Assessment[Exposure Eligibility],ROW()-ROW(tbl_WR_EligibilitySummary[#Headers])),INDEX(tbl_WR_AdditionalActions[Exposure Eligibility],ROW()-ROW(tbl_WR_EligibilitySummary[#Headers])-ROWS(tbl_WR_Assessment[ActionID])))} -> Not eligible | I19: {=IF(ROW()-ROW(tbl_WR_EligibilitySummary[#Headers])<=ROWS(tbl_WR_Assessment[ActionID]),IF(INDEX(tbl_WR_Assessment[Exposure Evidence Count],ROW()-ROW(tbl_WR_EligibilitySummary[#Headers]))=0,"",INDEX(tbl_WR_Assessment[Exposure Evidence Count],ROW()-ROW(tbl_WR_EligibilitySummary[#Headers]))),IF(INDEX(tbl_WR_AdditionalActions[Exposure Evidence Count],ROW()-ROW(tbl_WR_EligibilitySummary[#Headers])-ROWS(tbl_WR_Assessment[ActionID]))=0,"",INDEX(tbl_WR_AdditionalActions[Exposure Evidence Count],ROW()-ROW(tbl_WR_EligibilitySummary[#Headers])-ROWS(tbl_WR_Assessment[ActionID]))))} | J19: {=IF(tbl_WR_EligibilitySummary[[#This Row],[Exposure Eligibility]]="Eligible",IF(ROW()-ROW(tbl_WR_EligibilitySummary[#Headers])<=ROWS(tbl_WR_Assessment[ActionID]),INDEX(tbl_WR_Assessment[Effectiveness on Exposure],ROW()-ROW(tbl_WR_EligibilitySummary[#Headers])),INDEX(tbl_WR_AdditionalActions[Effectiveness on Exposure],ROW()-ROW(tbl_WR_EligibilitySummary[#Headers])-ROWS(tbl_WR_Assessment[ActionID]))),IF(tbl_WR_EligibilitySummary[[#This Row],[Exposure Eligibility]]="Review required","Review required",IF(tbl_WR_EligibilitySummary[[#This Row],[Exposure Eligibility]]="Not eligible","N/A","")))} -> N/A | K19: {=IF(ROW()-ROW(tbl_WR_EligibilitySummary[#Headers])<=ROWS(tbl_WR_Assessment[ActionID]),INDEX(tbl_WR_Assessment[ReviewStatus],ROW()-ROW(tbl_WR_EligibilitySummary[#Headers])),INDEX(tbl_WR_AdditionalActions[ReviewStatus],ROW()-ROW(tbl_WR_EligibilitySummary[#Headers])-ROWS(tbl_WR_Assessment[ActionID])))} -> Not assessed
... B62: {=IF(ROW()-ROW(tbl_WR_EligibilitySummary[#Headers])<=ROWS(tbl_WR_Assessment[ActionID]),"Existing action","Additional action")} -> Additional action | C62: {=IF(ROW()-ROW(tbl_WR_EligibilitySummary[#Headers])<=ROWS(tbl_WR_Assessment[ActionID]),INDEX(tbl_WR_Assessment[ActionID],ROW()-ROW(tbl_WR_EligibilitySummary[#Headers])),INDEX(tbl_WR_AdditionalActions[AdditionalActionID],ROW()-ROW(tbl_WR_EligibilitySummary[#Headers])-ROWS(tbl_WR_Assessment[ActionID])))} -> WR_ADD_0002 | D62: {=IF(ROW()-ROW(tbl_WR_EligibilitySummary[#Headers])<=ROWS(tbl_WR_Assessment[ActionID]),INDEX(tbl_WR_Assessment[ActionName],ROW()-ROW(tbl_WR_EligibilitySummary[#Headers])),INDEX(tbl_WR_AdditionalActions[ActionName],ROW()-ROW(tbl_WR_EligibilitySummary[#Headers])-ROWS(tbl_WR_Assessment[ActionID])))} -> Integrate climate risk into water infrastructure investment planning | E62: {=IF(ROW()-ROW(tbl_WR_EligibilitySummary[#Headers])<=ROWS(tbl_WR_Assessment[ActionID]),INDEX(tbl_WR_Assessment[Vulnerability Eligibility],ROW()-ROW(tbl_WR_EligibilitySummary[#Headers])),INDEX(tbl_WR_AdditionalActions[Vulnerability Eligibility],ROW()-ROW(tbl_WR_EligibilitySummary[#Headers])-ROWS(tbl_WR_Assessment[ActionID])))} -> Eligible | F62: {=IF(ROW()-ROW(tbl_WR_EligibilitySummary[#Headers])<=ROWS(tbl_WR_Assessment[ActionID]),IF(INDEX(tbl_WR_Assessment[Vulnerability Evidence Count],ROW()-ROW(tbl_WR_EligibilitySummary[#Headers]))=0,"",INDEX(tbl_WR_Assessment[Vulnerability Evidence Count],ROW()-ROW(tbl_WR_EligibilitySummary[#Headers]))),IF(INDEX(tbl_WR_AdditionalActions[Vulnerability Evidence Count],ROW()-ROW(tbl_WR_EligibilitySummary[#Headers])-ROWS(tbl_WR_Assessment[ActionID]))=0,"",INDEX(tbl_WR_AdditionalActions[Vulnerability Evidence Count],ROW()-ROW(tbl_WR_EligibilitySummary[#Headers])-ROWS(tbl_WR_Assessment[ActionID]))))} -> 1 | G62: {=IF(tbl_WR_EligibilitySummary[[#This Row],[Vulnerability Eligibility]]="Eligible",IF(ROW()-ROW(tbl_WR_EligibilitySummary[#Headers])<=ROWS(tbl_WR_Assessment[ActionID]),INDEX(tbl_WR_Assessment[Effectiveness on Vulnerability],ROW()-ROW(tbl_WR_EligibilitySummary[#Headers])),INDEX(tbl_WR_AdditionalActions[Effectiveness on Vulnerability],ROW()-ROW(tbl_WR_EligibilitySummary[#Headers])-ROWS(tbl_WR_Assessment[ActionID]))),IF(tbl_WR_EligibilitySummary[[#This Row],[Vulnerability Eligibility]]="Review required","Review required",IF(tbl_WR_EligibilitySummary[[#This Row],[Vulnerability Eligibility]]="Not eligible","N/A","")))} -> High effectiveness | H62: {=IF(ROW()-ROW(tbl_WR_EligibilitySummary[#Headers])<=ROWS(tbl_WR_Assessment[ActionID]),INDEX(tbl_WR_Assessment[Exposure Eligibility],ROW()-ROW(tbl_WR_EligibilitySummary[#Headers])),INDEX(tbl_WR_AdditionalActions[Exposure Eligibility],ROW()-ROW(tbl_WR_EligibilitySummary[#Headers])-ROWS(tbl_WR_Assessment[ActionID])))} -> Not eligible | I62: {=IF(ROW()-ROW(tbl_WR_EligibilitySummary[#Headers])<=ROWS(tbl_WR_Assessment[ActionID]),IF(INDEX(tbl_WR_Assessment[Exposure Evidence Count],ROW()-ROW(tbl_WR_EligibilitySummary[#Headers]))=0,"",INDEX(tbl_WR_Assessment[Exposure Evidence Count],ROW()-ROW(tbl_WR_EligibilitySummary[#Headers]))),IF(INDEX(tbl_WR_AdditionalActions[Exposure Evidence Count],ROW()-ROW(tbl_WR_EligibilitySummary[#Headers])-ROWS(tbl_WR_Assessment[ActionID]))=0,"",INDEX(tbl_WR_AdditionalActions[Exposure Evidence Count],ROW()-ROW(tbl_WR_EligibilitySummary[#Headers])-ROWS(tbl_WR_Assessment[ActionID]))))} | J62: {=IF(tbl_WR_EligibilitySummary[[#This Row],[Exposure Eligibility]]="Eligible",IF(ROW()-ROW(tbl_WR_EligibilitySummary[#Headers])<=ROWS(tbl_WR_Assessment[ActionID]),INDEX(tbl_WR_Assessment[Effectiveness on Exposure],ROW()-ROW(tbl_WR_EligibilitySummary[#Headers])),INDEX(tbl_WR_AdditionalActions[Effectiveness on Exposure],ROW()-ROW(tbl_WR_EligibilitySummary[#Headers])-ROWS(tbl_WR_Assessment[ActionID]))),IF(tbl_WR_EligibilitySummary[[#This Row],[Exposure Eligibility]]="Review required","Review required",IF(tbl_WR_EligibilitySummary[[#This Row],[Exposure Eligibility]]="Not eligible","N/A","")))} -> N/A | K62: {=IF(ROW()-ROW(tbl_WR_EligibilitySummary[#Headers])<=ROWS(tbl_WR_Assessment[ActionID]),INDEX(tbl_WR_Assessment[ReviewStatus],ROW()-ROW(tbl_WR_EligibilitySummary[#Headers])),INDEX(tbl_WR_AdditionalActions[ReviewStatus],ROW()-ROW(tbl_WR_EligibilitySummary[#Headers])-ROWS(tbl_WR_Assessment[ActionID])))} -> New action identified
B63: {=IF(ROW()-ROW(tbl_WR_EligibilitySummary[#Headers])<=ROWS(tbl_WR_Assessment[ActionID]),"Existing action","Additional action")} -> Additional action | C63: {=IF(ROW()-ROW(tbl_WR_EligibilitySummary[#Headers])<=ROWS(tbl_WR_Assessment[ActionID]),INDEX(tbl_WR_Assessment[ActionID],ROW()-ROW(tbl_WR_EligibilitySummary[#Headers])),INDEX(tbl_WR_AdditionalActions[AdditionalActionID],ROW()-ROW(tbl_WR_EligibilitySummary[#Headers])-ROWS(tbl_WR_Assessment[ActionID])))} -> WR_ADD_0003 | D63: {=IF(ROW()-ROW(tbl_WR_EligibilitySummary[#Headers])<=ROWS(tbl_WR_Assessment[ActionID]),INDEX(tbl_WR_Assessment[ActionName],ROW()-ROW(tbl_WR_EligibilitySummary[#Headers])),INDEX(tbl_WR_AdditionalActions[ActionName],ROW()-ROW(tbl_WR_EligibilitySummary[#Headers])-ROWS(tbl_WR_Assessment[ActionID])))} -> Use earmarked water tariffs to finance ecosystem services and climate adaptation | E63: {=IF(ROW()-ROW(tbl_WR_EligibilitySummary[#Headers])<=ROWS(tbl_WR_Assessment[ActionID]),INDEX(tbl_WR_Assessment[Vulnerability Eligibility],ROW()-ROW(tbl_WR_EligibilitySummary[#Headers])),INDEX(tbl_WR_AdditionalActions[Vulnerability Eligibility],ROW()-ROW(tbl_WR_EligibilitySummary[#Headers])-ROWS(tbl_WR_Assessment[ActionID])))} -> Eligible | F63: {=IF(ROW()-ROW(tbl_WR_EligibilitySummary[#Headers])<=ROWS(tbl_WR_Assessment[ActionID]),IF(INDEX(tbl_WR_Assessment[Vulnerability Evidence Count],ROW()-ROW(tbl_WR_EligibilitySummary[#Headers]))=0,"",INDEX(tbl_WR_Assessment[Vulnerability Evidence Count],ROW()-ROW(tbl_WR_EligibilitySummary[#Headers]))),IF(INDEX(tbl_WR_AdditionalActions[Vulnerability Evidence Count],ROW()-ROW(tbl_WR_EligibilitySummary[#Headers])-ROWS(tbl_WR_Assessment[ActionID]))=0,"",INDEX(tbl_WR_AdditionalActions[Vulnerability Evidence Count],ROW()-ROW(tbl_WR_EligibilitySummary[#Headers])-ROWS(tbl_WR_Assessment[ActionID]))))} -> 1 | G63: {=IF(tbl_WR_EligibilitySummary[[#This Row],[Vulnerability Eligibility]]="Eligible",IF(ROW()-ROW(tbl_WR_EligibilitySummary[#Headers])<=ROWS(tbl_WR_Assessment[ActionID]),INDEX(tbl_WR_Assessment[Effectiveness on Vulnerability],ROW()-ROW(tbl_WR_EligibilitySummary[#Headers])),INDEX(tbl_WR_AdditionalActions[Effectiveness on Vulnerability],ROW()-ROW(tbl_WR_EligibilitySummary[#Headers])-ROWS(tbl_WR_Assessment[ActionID]))),IF(tbl_WR_EligibilitySummary[[#This Row],[Vulnerability Eligibility]]="Review required","Review required",IF(tbl_WR_EligibilitySummary[[#This Row],[Vulnerability Eligibility]]="Not eligible","N/A","")))} -> Medium effectiveness | H63: {=IF(ROW()-ROW(tbl_WR_EligibilitySummary[#Headers])<=ROWS(tbl_WR_Assessment[ActionID]),INDEX(tbl_WR_Assessment[Exposure Eligibility],ROW()-ROW(tbl_WR_EligibilitySummary[#Headers])),INDEX(tbl_WR_AdditionalActions[Exposure Eligibility],ROW()-ROW(tbl_WR_EligibilitySummary[#Headers])-ROWS(tbl_WR_Assessment[ActionID])))} -> Not eligible | I63: {=IF(ROW()-ROW(tbl_WR_EligibilitySummary[#Headers])<=ROWS(tbl_WR_Assessment[ActionID]),IF(INDEX(tbl_WR_Assessment[Exposure Evidence Count],ROW()-ROW(tbl_WR_EligibilitySummary[#Headers]))=0,"",INDEX(tbl_WR_Assessment[Exposure Evidence Count],ROW()-ROW(tbl_WR_EligibilitySummary[#Headers]))),IF(INDEX(tbl_WR_AdditionalActions[Exposure Evidence Count],ROW()-ROW(tbl_WR_EligibilitySummary[#Headers])-ROWS(tbl_WR_Assessment[ActionID]))=0,"",INDEX(tbl_WR_AdditionalActions[Exposure Evidence Count],ROW()-ROW(tbl_WR_EligibilitySummary[#Headers])-ROWS(tbl_WR_Assessment[ActionID]))))} | J63: {=IF(tbl_WR_EligibilitySummary[[#This Row],[Exposure Eligibility]]="Eligible",IF(ROW()-ROW(tbl_WR_EligibilitySummary[#Headers])<=ROWS(tbl_WR_Assessment[ActionID]),INDEX(tbl_WR_Assessment[Effectiveness on Exposure],ROW()-ROW(tbl_WR_EligibilitySummary[#Headers])),INDEX(tbl_WR_AdditionalActions[Effectiveness on Exposure],ROW()-ROW(tbl_WR_EligibilitySummary[#Headers])-ROWS(tbl_WR_Assessment[ActionID]))),IF(tbl_WR_EligibilitySummary[[#This Row],[Exposure Eligibility]]="Review required","Review required",IF(tbl_WR_EligibilitySummary[[#This Row],[Exposure Eligibility]]="Not eligible","N/A","")))} -> N/A | K63: {=IF(ROW()-ROW(tbl_WR_EligibilitySummary[#Headers])<=ROWS(tbl_WR_Assessment[ActionID]),INDEX(tbl_WR_Assessment[ReviewStatus],ROW()-ROW(tbl_WR_EligibilitySummary[#Headers])),INDEX(tbl_WR_AdditionalActions[ReviewStatus],ROW()-ROW(tbl_WR_EligibilitySummary[#Headers])-ROWS(tbl_WR_Assessment[ActionID])))} -> New action identified | L63: Workflow overview
B66: Step 0 – Indicator Framework Construction
B67: Objective: | C67: Purpose: build the official Water Resources assessment framework. 1. Aggregate all approved Vulnerability indicators (Level 6) under the Vulnerability component (Level 3). 2. Aggregate all approved Exposure indicators (Level 6) under the Exposure component (Level 3). 3. Produce the approved indicator lists used throughout the subsequent assessment process. These lists constitute the official sector assessment framework. Indicators must be retrieved from the workbook source tables and must not be renamed, regrouped, reinterpreted or replaced.
B68: EXCEL COPILOT PROMPT TO RUN | C68: Review the Water Resources reference framework. Verify that the Vulnerability and Exposure indicator source tables contain the complete approved indicator records and that indicator records remain structured table entries rather than manual text strings. Verify that all indicator dropdowns and dynamic references are connected to the correct source tables. Verify specifically that: - C28 dynamically returns the Water Resources Vulnerability indicator library. - C33 dynamically returns the Water Resources Exposure indicator library. Identify missing indicators, duplicated indicators, broken dynamic references, hard-coded lists and inconsistent indicator names. Do not modify, classify, score, rename or replace indicators. Do not assess actions. Return only validation findings and recommended corrections.
B70: Vulnerability indicators: Level 6
B71: Sector | C71: Water resources
B72: Component (level 3) | C72: Vulnerability
B73: Indicators (level 6) | C73: {=_xlfn.TEXTJOIN(", ",TRUE,_xlfn.UNIQUE(_xlfn._xlws.FILTER(Table227[base_indicator_name],(Table227[sector_name]=$C$71)*(Table227[risk_component_name]=$C$72),"")))} -> Inefficiency in water production, Inefficiency in water distribution, Average per capita water consumption, Water balance for agriculture, Water balance for industry, Diseases due to inadequate sanitation, Water quality, Degraded and/or deforested areas, Areas with soils susceptible to erosion, Ecological flow for ecosystem uses, Dam and mining safety, Municipal basic sanitation plan, Level of activity in basin committees, Drought-related prevention actions, Alternatives to water supply, Investments in water resources, Investments in adaptation policies, Resilient cities program, Cisterns program: water for consumption, Nature reserve, Artificial reserve, Underground storage potential, Agricultural participation in GDP, Industrial participation in GDP, Income not affected by water prices, Income greater than two minimum wages
B75: Exposure indicators: Level 6
B76: Sector | C76: Water resources
B77: Component (level 3) | C77: Exposure
B78: Indicators (level 6) | C78: {=_xlfn.TEXTJOIN(", ",TRUE,_xlfn.UNIQUE(_xlfn._xlws.FILTER(Table227[base_indicator_name],(Table227[sector_name]=$C$76)*(Table227[risk_component_name]=$C$77),"")))} -> Population density, Urban users exposed, Exposed rural users, Exposed industrial users, Mining Users Exposed, Thermoelectricity users exposed, Animal husbandry users exposed, Irrigation users exposed
B80: Step 1 – Source Identification
B81: Process: | C81: Web AI research followed by Excel Copilot update
B82: Objective: | C82: Purpose: identify and validate the evidence base for the Water Resources assessment. Build a portfolio of exactly 5 Brazilian and 5 International sources. Each source must contain adaptation-related evidence, provide a verifiable PDF, describe implementation mechanisms or adaptation interventions, and include monitoring, evaluation or effectiveness information. This step may be repeated as needed. It performs no action–sector eligibility assessment and assigns no effectiveness level. Its sole output is a validated portfolio of PDF evidence sources.
B83: 1. CONTEXT ELEMENTS TO PASTE WITH WEB AI PROMPT | C83: ="Sector:"&CHAR(10)&"Water resources"&CHAR(10)&CHAR(10)&"Approved Vulnerability Indicators:"&CHAR(10)&$C$73&CHAR(10)&CHAR(10)&"Approved Exposure Indicators:"&CHAR(10)&$C$78&CHAR(10)&CHAR(10)&"Mandatory framework sources:"&CHAR(10)&"WR_SRC_001 | Brazil | AdaptaBrasil MCTI: Índices e Indicadores | MCTI | 2023"&CHAR(10)&CHAR(10)&"WR_SRC_002 | International | IPCC AR6 WGII: Chapter 4: Water | IPCC | 2022" -> Sector: Water resources Approved Vulnerability Indicators: Inefficiency in water production, Inefficiency in water distribution, Average per capita water consumption, Water balance for agriculture, Water balance for industry, Diseases due to inadequate sanitation, Water quality, Degraded and/or deforested areas, Areas with soils susceptible to erosion, Ecological flow for ecosystem uses, Dam and mining safety, Municipal basic sanitation plan, Level of activity in basin committees, Drought-related prevention actions, Alternatives to water supply, Investments in water resources, Investments in adaptation policies, Resilient cities program, Cisterns program: water for consumption, Nature reserve, Artificial reserve, Underground storage potential, Agricultural participation in GDP, Industrial participation in GDP, Income not affected by water prices, Income greater than two minimum wages Approved Exposure Indicators: Population density, Urban users exposed, Exposed rural users, Exposed industrial users, Mining Users Exposed, Thermoelectricity users exposed, Animal husbandry users exposed, Irrigation users exposed Mandatory framework sources: WR_SRC_001 | Brazil | AdaptaBrasil MCTI: Índices e Indicadores | MCTI | 2023 WR_SRC_002 | International | IPCC AR6 WGII: Chapter 4: Water | IPCC | 2022 | D83: << Paste in Web AI
B84: 2. WEB AI PROMPT TO COPY | C84: WEB AI PROMPT Review the supplied sector and the complete approved Vulnerability and Exposure Level 6 indicator lists. Build a new operational source portfolio from scratch. Ignore all previously proposed candidate sources and previously proposed PDF links. MANDATORY FRAMEWORK SOURCES The following two sources must be included: WR_SRC_001 Geographic scope: Brazil Document title: AdaptaBrasil MCTI: Índices e Indicadores Issuing institution: MCTI Publication year: 2023 WR_SRC_002 Geographic scope: International Document title: IPCC AR6 WGII: Chapter 4: Water Issuing institution: IPCC Publication year: 2022 Keep these two sources as the first two records. Use the PDF links supplied below when they are functional and correspond to the stated documents. If a supplied mandatory-source PDF link does not function or does not correspond to the stated document, find a functional PDF version of the same mandatory document. FINAL PORTFOLIO COMPOSITION The final portfolio must contain exactly 10 sources: 5 sources with Geographic scope equal to Brazil. 5 sources with Geographic scope equal to International. The two mandatory sources count toward these totals. Therefore identify: 4 additional Brazilian sources. 4 additional international sources. Do not return more or fewer than 10 sources. SOURCE-SELECTION OBJECTIVE Select documents that maximise usefulness for future assessment of adaptation-action effectiveness against the approved Water Resources indicators. Prioritise documents containing: 1. Adaptation measures. 2. Implementation mechanisms. 3. Programme or policy evaluations. 4. Monitoring results. 5. Documented outcomes. 6. Quantified results. 7. Effectiveness findings. 8. Implementation barriers. 9. Implementation success factors. 10. Implementation case studies. 11. Documented limitations or trade-offs. BRAZILIAN SOURCE PRIORITIES Prioritise PDF documents published by: 1. Agência Nacional de Águas e Saneamento Básico. 2. Ministério do Meio Ambiente. 3. Ministério da Ciência, Tecnologia e Inovação. 4. Federal sanitation institutions. 5. River basin institutions. 6. Brazilian public research institutions. 7. Brazilian programme-monitoring and evaluation bodies. 8. Brazilian offices or partnerships of multilateral development banks. INTERNATIONAL SOURCE PRIORITIES Prioritise PDF documents published by: 1. IPCC. 2. World Bank. 3. Inter-American Development Bank. 4. UNEP. 5. UNECE. 6. FAO. 7. OECD. 8. Global Center on Adaptation. 9. Other recognised multilateral development banks. 10. Peer-reviewed scientific synthesis or evaluation publications. SOURCE ELIGIBILITY Select a source only when all of the following conditions are satisfied: 1. The exact document title is identifiable. 2. The issuing institution is identifiable. 3. The publication year is identifiable. 4. The document is relevant to one or more approved indicators. 5. The document is likely to contain page-traceable evidence about adaptation measures, mechanisms, implementation, outcomes or effectiveness. 6. A PDF version is publicly accessible. 7. The PDF link opens the document itself or an official PDF viewer that provides access to the complete PDF. 8. The PDF link corresponds to the selected document. 9. The document is not a duplicate of another selected source. PDF LINK VERIFICATION Before accepting each source: 1. Open the proposed PDF link. 2. Confirm that the link functions. 3. Confirm that the linked file is a PDF or provides direct access to the complete PDF. 4. Confirm that the PDF title or document content corresponds to the selected source. 5. Confirm that the PDF is not merely an abstract, executive-summary substitute, presentation, webpage or unrelated document. 6. Confirm that the PDF contains readable and paginated content. 7. Prefer official institutional PDF links. 8. A recognised institutional repository or co-publisher is acceptable when the official issuing institution does not host the PDF directly. 9. Do not use search-result URLs. 10. Do not invent, reconstruct or approximate a PDF URL. 11. Do not accept a broken, inaccessible or mismatched PDF link. If a document does not have a functional and corresponding PDF link, exclude it and select another eligible document. EXCLUSIONS Do not select: 1. News articles. 2. Press releases. 3. Presentations. 4. Abstract-only records. 5. Generic webpages. 6. Dashboards without analytical documentation. 7. Data portals without a paginated analytical report. 8. Duplicate documents. 9. Duplicate editions. 10. Translations of a document already selected. 11. Documents with unverifiable title, institution or year. 12. Documents without a functional PDF. 13. Documents whose proposed PDF link opens another publication. 14. Documents that provide only general background without evidence potential. METADATA RULES Use the exact document title displayed in the PDF. Use the exact issuing institution identified in the PDF. Use the publication year identified in the PDF. Use only: Brazil International for Geographic scope. Assign Source IDs exactly as follows: WR_SRC_001 to the mandatory AdaptaBrasil source. WR_SRC_002 to the mandatory IPCC source. WR_SRC_003 to WR_SRC_006 to the four additional Brazilian sources. WR_SRC_007 to WR_SRC_010 to the four additional international sources. OUTPUT REQUIREMENT Return one complete Excel Copilot prompt and nothing else. Do not return research commentary outside the Excel Copilot prompt. The returned Excel Copilot prompt must be self-contained and executable without modification. The returned Excel Copilot prompt must explicitly state: Target structured table: tbl_WR_SourceIdentification The returned prompt must rebuild only tbl_WR_SourceIdentification. The returned prompt must populate exactly these columns: Source ID Geographic scope Document title Issuing institution Publication year PDF file The returned prompt must list all 10 source records explicitly. For every source record, provide: 1. Exact Source ID. 2. Exact Geographic scope. 3. Exact Document title. 4. Exact Issuing institution. 5. Exact Publication year. 6. Exact functional PDF link. The returned Excel Copilot prompt must instruct Excel Copilot to: 1. Preserve the existing table structure. 2. Resize the table to contain exactly 10 non-empty source records. 3. Replace previous non-mandatory source records with the newly selected portfolio. 4. Preserve WR_SRC_001 and WR_SRC_002 as the first two records. 5. Use the exact Source ID sequence WR_SRC_001 to WR_SRC_010. 6. Maintain exactly 5 Brazil records. 7. Maintain exactly 5 International records. 8. Populate the PDF file column for every record. 9. Display PDF links as normal Excel hyperlinks or complete plain-text URLs. 10. Remove visible HTML anchor code. 11. Preserve table formatting, filters and validation. 12. Create no additional column. 13. Modify no other table. 14. Modify no other worksheet section. 15. Require no selected cells or ranges. The returned prompt must not use placeholders. The returned prompt must not ask the user which sources to retain. The returned prompt must not ask for confirmation. The returned prompt must not refer to research findings outside the prompt. The returned prompt must report: 1. The 10 Source IDs inserted. 2. The number of Brazil sources. 3. The number of International sources. 4. Confirmation that all 10 records contain a PDF file. 5. Confirmation that PDF links were verified during source selection. 6. Confirmation that no other table was modified. END OF WEB AI PROMPT | D84: << Paste in Web AI
B85: 3. WEB AI OUTPUT TO PASTE | C85: Paste the complete Excel Copilot prompt returned by Web AI here.
B87: OPERATIONAL SOURCE AND PDF REGISTER
B88: Source ID | C88: Geographic scope | D88: Document title | E88: Issuing institution | F88: Publication year | G88: PDF file
B89: WR_SRC_001 | C89: Brazil | D89: AdaptaBrasil MCTI — Índices e Indicadores | E89: MCTI | F89: 2023 | G89: https://www.dropbox.com/scl/fi/iln5nsaomw5iaxnrarjam/Te-rico-metodol-gico_Recursos_Hidricos_2.0_19_08_2025.pdf?rlkey=c92kudj42qafe1xxyojskd1ui&e=1&dl=0
B90: WR_SRC_002 | C90: International | D90: IPCC AR6 WGII — Chapter 4: Water | E90: IPCC | F90: 2022 | G90: https://www.ipcc.ch/report/ar6/wg2/downloads/report/IPCC_AR6_WGII_Chapter04.pdf
B91: WR_SRC_003 | C91: Brazil | D91: Plano Nacional de Segurança Hídrica | E91: Agência Nacional de Águas e Saneamento Básico (ANA) | F91: 2021 | G91: https://www.gov.br/ana/pt-br/assuntos/gestao-das-aguas/planos-de-recursos-hidricos/planos-de-recursos-hidricos-de-bacias-hidrograficas/planos-de-bacias-hidrograficas-interfederativas/planejamento-integrado-de-recursos-hidricos-nas-bacias-compartilhadas-pirh-parhs/copy_of_ManualparaavaliaodaimplementaodePlanosdeRecursosHdricos.pdf
B92: WR_SRC_004 | C92: Brazil | D92: Programa Produtor de Água: Resultados e Perspectivas | E92: Agência Nacional de Águas e Saneamento Básico (ANA) | F92: 2026
B93: WR_SRC_005 | C93: Brazil | D93: Plano Nacional de Saneamento Básico (PLANSAB) – Revisão 2019 | E93: Ministério do Desenvolvimento Regional | F93: 2020 | G93: https://www.gov.br/cidades/pt-br/acesso-a-informacao/acoes-e-programas/saneamento/plano-nacional-de-saneamento-basico-plansab/arquivos/relatriodeavaliaoanualdoplansab2020.pdf
B94: WR_SRC_006 | C94: International | D94: Under Pressure: Effects, Impacts, and Adaptation to Climate Change in Latin American and Caribbean Water Operators | E94: Inter-American Development Bank | F94: 2023 | G94: https://publications.iadb.org/publications/english/document/Under-Pressure-Effects-Impacts-and-Adaptation-to-Climate-change-in-Latin-American-and-Caribbean-Water-Operators.pdf?__cf_chl_tk=ZqmNpAp_H8fWkuEESw9HVmNxbu1evfCwt_wgYC58ivM-1787664378-1.0.1.1-NvUF9ypugZ8KnrJdU3CsSmXZDz8Hbe2E15lhlFor2X4
B95: WR_SRC_007 | C95: International | D95: Guidance on Water and Adaptation to Climate Change | E95: UNECE | F95: 2009 | G95: https://unece.org/sites/default/files/datastore/fileadmin/DAM/env/water/mop5/Guidance_FINAL.pdf
B96: WR_SRC_008 | C96: International | D96: Water and Climate Change Adaptation in Transboundary Basins: Lessons Learned and Good Practices | E96: UNECE / International Network of Basin Organizations | F96: 2015 | G96: https://unece.org/fileadmin/DAM/env/water/publications/WAT_Good_practices/ece.mp.wat.45.pdf
B97: WR_SRC_009 | C97: International | D97: Flowing Forward: Freshwater Ecosystem Adaptation to Climate Change in Water Resources Management and Biodiversity Conservation | E97: World Bank / WWF | F97: 2010 | G97: https://awsassets.panda.org/downloads/flowing_forward_freshwater_ecosystem_adaptation_to_climate_change.pdf
B98: WR_SRC_010 | C98: International | D98: Water Security and Climate Change: Insights from Country Climate and Development Reports | E98: World Bank | F98: 2026 | G98: https://documents1.worldbank.org/curated/en/099124511122431814/pdf/IDU1fa8a4c3a1fd8c14810194851fb785b73d02d.pdf
B100: Step 2A – Eligibility Assessment / Step 2B – Effectiveness Assessment
B101: Objective | C101: STEP 2A – ELIGIBILITY ASSESSMENT Using the AdaptaBrasil methodology, determine separately for Vulnerability and Exposure whether each action belongs to Water Resources through a direct relationship with an approved indicator. For each action: identify the implementation mechanism; identify the condition directly affected; test the direct indicator relationship; and exclude thematic-only links, hazard-only links, indirect pathways and co-benefits. The output is Eligible or Not eligible for each component. No effectiveness level is assigned during Step 2A. STEP 2B – EFFECTIVENESS ASSESSMENT Assess effectiveness only for components classified as Eligible in Step 2A. Review the available PDFs, record exact quotations and page references, append new evidence rather than replacing prior evidence, and maintain a cumulative evidence base. Each new PDF review may change the evidence-supported effectiveness level. Use only High effectiveness, Medium effectiveness, Low effectiveness or No demonstrated effectiveness. These values become inputs to the Impact Assessment calculations.
B102: Approved Vulnerability Indicators | C102: =$C$73 -> Inefficiency in water production, Inefficiency in water distribution, Average per capita water consumption, Water balance for agriculture, Water balance for industry, Diseases due to inadequate sanitation, Water quality, Degraded and/or deforested areas, Areas with soils susceptible to erosion, Ecological flow for ecosystem uses, Dam and mining safety, Municipal basic sanitation plan, Level of activity in basin committees, Drought-related prevention actions, Alternatives to water supply, Investments in water resources, Investments in adaptation policies, Resilient cities program, Cisterns program: water for consumption, Nature reserve, Artificial reserve, Underground storage potential, Agricultural participation in GDP, Industrial participation in GDP, Income not affected by water prices, Income greater than two minimum wages | D102: << Paste in Web AI
B103: Approved Exposure Indicators | C103: =$C$78 -> Population density, Urban users exposed, Exposed rural users, Exposed industrial users, Mining Users Exposed, Thermoelectricity users exposed, Animal husbandry users exposed, Irrigation users exposed | D103: << Paste in Web AI
B104: Assessment Tables | C104: Copy the complete current tbl_WR_Assessment table. Copy the complete current tbl_WR_AdditionalActions table. Paste both tables into the same Web AI conversation. | D104: << Attach in Web AI
B105: PDF Input | C105: Attach one complete PDF manually. One PDF per execution. | D105: << Attach in Web AI
